Workbook

Sheet try LAP JULI
A1: LAPORAN PENJUALAN BULANAN | AP1: 45839
A2: NAMA BARANG | B2: STOK AWAL | C2: =UPPER("HARI / BULAN : " & TEXT(AP1, "MMMM YYYY")) -> HARI / BULAN : JULI 2025
C3: =TEXT(C4,"dddd") -> Selasa | D3: =TEXT(D4,"dddd") -> Rabu | E3: =TEXT(E4,"dddd") -> Kamis | F3: =TEXT(F4,"dddd") -> Jumat | G3: =TEXT(G4,"dddd") -> Sabtu | H3: =TEXT(H4,"dddd") -> Minggu | I3: =TEXT(I4,"dddd") -> Senin | J3: =TEXT(J4,"dddd") -> Selasa | ... AG3: =TEXT(AG4,"dddd") -> Kamis | AH3: TOTAL | AI3: STOCK | AJ3: SYSTEM | AK3: KET/SELISIH | AL3: HARGA BELI | AM3: HARGA JUAL | AN3: OMSET | AO3: PROFIT
C4: =AP1 -> 45839 | D4: =IF(AND(MONTH(C4+1) = MONTH(C4), C4<>""),C4 + 1, "") -> 45840 | E4: =IF(AND(MONTH(D4+1) = MONTH(D4), D4<>""),D4 + 1, "") -> 45841 | F4: =IF(AND(MONTH(E4+1) = MONTH(E4), E4<>""),E4 + 1, "") -> 45842 | G4: =IF(AND(MONTH(F4+1) = MONTH(F4), F4<>""),F4 + 1, "") -> 45843 | H4: =IF(AND(MONTH(G4+1) = MONTH(G4), G4<>""),G4 + 1, "") -> 45844 | I4: =IF(AND(MONTH(H4+1) = MONTH(H4), H4<>""),H4 + 1, "") -> 45845 | J4: =IF(AND(MONTH(I4+1) = MONTH(I4), I4<>""),I4 + 1, "") -> 45846 | K4: =IF(AND(MONTH(J4+1) = MONTH(J4), J4<>""),J4 + 1, "") -> 45847 | ... AG4: =IF(AND(MONTH(AF4+1) = MONTH(AF4), AF4<>""),AF4 + 1, "") -> 45869
A5: ='MASTER STOCK'!F2 -> Fitting Gantung | B5: ='MASTER STOCK'!G2 -> 12 | AH5: =SUM(C5:AG5) -> 0 | AI5: =B5-SUM(C5:AG5) -> 12 | AJ5: =B5-AH5 -> 12 | AK5: =AJ5-AI5 -> 0 | AL5: ='MASTER STOCK'!I2 -> 1400 | AM5: ='MASTER STOCK'!L2 -> 1820 | AN5: =AH5*AM5 -> 0 | AO5: =(AH5*AM5)-(AH5*AL5) -> 0
A6: ='MASTER STOCK'!F3 -> Colokan T | B6: ='MASTER STOCK'!G3 -> 12 | AH6: =SUM(C6:AG6) -> 0 | AI6: =B6-SUM(C6:AG6) -> 12 | AJ6: =B6-AH6 -> 12 | AK6: =AJ6-AI6 -> 0 | AL6: ='MASTER STOCK'!I3 -> 3000 | AM6: ='MASTER STOCK'!L3 -> 3900 | AN6: =AH6*AM6 -> 0 | AO6: =(AH6*AM6)-(AH6*AL6) -> 0
A7: ='MASTER STOCK'!F4 -> Steker Bulat | B7: ='MASTER STOCK'!G4 -> 12 | AH7: =SUM(C7:AG7) -> 0 | AI7: =B7-SUM(C7:AG7) -> 12 | AJ7: =B7-AH7 -> 12 | AK7: =AJ7-AI7 -> 0 | AL7: ='MASTER STOCK'!I4 -> 3000 | AM7: ='MASTER STOCK'!L4 -> 6000 | AN7: =AH7*AM7 -> 0 | AO7: =(AH7*AM7)-(AH7*AL7) -> 0
A8: ='MASTER STOCK'!F5 -> Steker Gepeng | B8: ='MASTER STOCK'!G5 -> 12 | AH8: =SUM(C8:AG8) -> 0 | AI8: =B8-SUM(C8:AG8) -> 12 | AJ8: =B8-AH8 -> 12 | AK8: =AJ8-AI8 -> 0 | AL8: ='MASTER STOCK'!I5 -> 1100 | AM8: ='MASTER STOCK'!L5 -> 1430 | AN8: =AH8*AM8 -> 0 | AO8: =(AH8*AM8)-(AH8*AL8) -> 0
A9: ='MASTER STOCK'!F6 -> Saklar Gantung Putih jumbo | B9: ='MASTER STOCK'!G6 -> 12 | AH9: =SUM(C9:AG9) -> 0 | AI9: =B9-SUM(C9:AG9) -> 12 | AJ9: =B9-AH9 -> 12 | AK9: =AJ9-AI9 -> 0 | AL9: ='MASTER STOCK'!I6 -> 2250 | AM9: ='MASTER STOCK'!L6 -> 4000 | AN9: =AH9*AM9 -> 0 | AO9: =(AH9*AM9)-(AH9*AL9) -> 0
A10: ='MASTER STOCK'!F7 -> Saklar Gantung Hitam | B10: ='MASTER STOCK'!G7 -> 12 | AH10: =SUM(C10:AG10) -> 0 | AI10: =B10-SUM(C10:AG10) -> 12 | AJ10: =B10-AH10 -> 12 | AK10: =AJ10-AI10 -> 0 | AL10: ='MASTER STOCK'!I7 -> 1850 | AM10: ='MASTER STOCK'!L7 -> 4000 | AN10: =AH10*AM10 -> 0 | AO10: =(AH10*AM10)-(AH10*AL10) -> 0
A11: ='MASTER STOCK'!F8 -> Isolasi Hitam National | B11: ='MASTER STOCK'!G8 -> 20 | AH11: =SUM(C11:AG11) -> 0 | AI11: =B11-SUM(C11:AG11) -> 20 | AJ11: =B11-AH11 -> 20 | AK11: =AJ11-AI11 -> 0 | AL11: ='MASTER STOCK'!I8 -> 5150 | AM11: ='MASTER STOCK'!L8 -> 7982.5 | AN11: =AH11*AM11 -> 0 | AO11: =(AH11*AM11)-(AH11*AL11) -> 0
A12: ='MASTER STOCK'!F9 -> Lem PVC Isarplas 40gram | B12: ='MASTER STOCK'!G9 -> 24 | AH12: =SUM(C12:AG12) -> 0 | AI12: =B12-SUM(C12:AG12) -> 24 | AJ12: =B12-AH12 -> 24 | AK12: =AJ12-AI12 -> 0 | AL12: ='MASTER STOCK'!I9 -> 6900 | AM12: ='MASTER STOCK'!L9 -> 9500 | AN12: =AH12*AM12 -> 0 | AO12: =(AH12*AM12)-(AH12*AL12) -> 0
A13: ='MASTER STOCK'!F10 -> Isolasi Kran air onda | B13: ='MASTER STOCK'!G10 -> 60 | AH13: =SUM(C13:AG13) -> 0 | AI13: =B13-SUM(C13:AG13) -> 60 | AJ13: =B13-AH13 -> 60 | AK13: =AJ13-AI13 -> 0 | AL13: ='MASTER STOCK'!I10 -> 1150 | AM13: ='MASTER STOCK'!L10 -> 1495 | AN13: =AH13*AM13 -> 0 | AO13: =(AH13*AM13)-(AH13*AL13) -> 0
A14: ='MASTER STOCK'!F11 -> Tutup Pipa 3/4" | B14: ='MASTER STOCK'!G11 -> 50 | AH14: =SUM(C14:AG14) -> 0 | AI14: =B14-SUM(C14:AG14) -> 50 | AJ14: =B14-AH14 -> 50 | AK14: =AJ14-AI14 -> 0 | AL14: ='MASTER STOCK'!I11 -> 850 | AM14: ='MASTER STOCK'!L11 -> 1275 | AN14: =AH14*AM14 -> 0 | AO14: =(AH14*AM14)-(AH14*AL14) -> 0
A15: ='MASTER STOCK'!F12 -> Fitting lampu gantung outdoor (10 m 5 fitting) | B15: ='MASTER STOCK'!G12 -> 1 | AH15: =SUM(C15:AG15) -> 0 | AI15: =B15-SUM(C15:AG15) -> 1 | AJ15: =B15-AH15 -> 1 | AK15: =AJ15-AI15 -> 0 | AL15: ='MASTER STOCK'!I12 -> 38000 | AM15: ='MASTER STOCK'!L12 -> 49400 | AN15: =AH15*AM15 -> 0 | AO15: =(AH15*AM15)-(AH15*AL15) -> 0
A16: ='MASTER STOCK'!F13 -> Obeng karet 4" plus | B16: ='MASTER STOCK'!G13 -> 5 | AH16: =SUM(C16:AG16) -> 0 | AI16: =B16-SUM(C16:AG16) -> 5 | AJ16: =B16-AH16 -> 5 | AK16: =AJ16-AI16 -> 0 | AL16: ='MASTER STOCK'!I13 -> 5500 | AM16: ='MASTER STOCK'!L13 -> 7150 | AN16: =AH16*AM16 -> 0 | AO16: =(AH16*AM16)-(AH16*AL16) -> 0
A17: ='MASTER STOCK'!F14 -> Obeng karet 4" minus | B17: ='MASTER STOCK'!G14 -> 5 | S17: 1 | AH17: =SUM(C17:AG17) -> 1 | AI17: =B17-SUM(C17:AG17) -> 4 | AJ17: =B17-AH17 -> 4 | AK17: =AJ17-AI17 -> 0 | AL17: ='MASTER STOCK'!I14 -> 5500 | AM17: ='MASTER STOCK'!L14 -> 7150 | AN17: =AH17*AM17 -> 7150 | AO17: =(AH17*AM17)-(AH17*AL17) -> 1650
A18: ='MASTER STOCK'!F15 -> Obeng karet 6" plus | B18: ='MASTER STOCK'!G15 -> 5 | AH18: =SUM(C18:AG18) -> 0 | AI18: =B18-SUM(C18:AG18) -> 5 | AJ18: =B18-AH18 -> 5 | AK18: =AJ18-AI18 -> 0 | AL18: ='MASTER STOCK'!I15 -> 7000 | AM18: ='MASTER STOCK'!L15 -> 9100 | AN18: =AH18*AM18 -> 0 | AO18: =(AH18*AM18)-(AH18*AL18) -> 0
A19: ='MASTER STOCK'!F16 -> Obeng karet 6" Minus | B19: ='MASTER STOCK'!G16 -> 5 | AH19: =SUM(C19:AG19) -> 0 | AI19: =B19-SUM(C19:AG19) -> 5 | AJ19: =B19-AH19 -> 5 | AK19: =AJ19-AI19 -> 0 | AL19: ='MASTER STOCK'!I16 -> 7000 | AM19: ='MASTER STOCK'!L16 -> 9100 | AN19: =AH19*AM19 -> 0 | AO19: =(AH19*AM19)-(AH19*AL19) -> 0
A20: ='MASTER STOCK'!F17 -> Kabel Awg 24 Double 2x18 merah hitam | B20: ='MASTER STOCK'!G17 -> 2 | AH20: =SUM(C20:AG20) -> 0 | AI20: =B20-SUM(C20:AG20) -> 2 | AJ20: =B20-AH20 -> 2 | AK20: =AJ20-AI20 -> 0 | AL20: ='MASTER STOCK'!I17 -> 106500 | AM20: ='MASTER STOCK'!L17 -> 181050 | AN20: =AH20*AM20 -> 0 | AO20: =(AH20*AM20)-(AH20*AL20) -> 0
A21: ='MASTER STOCK'!F18 -> Kabel bintik serabut tembaga motor mobil 20mx0.5mm/0,85mm merah 0,5mm | B21: ='MASTER STOCK'!G18 -> 2 | AH21: =SUM(C21:AG21) -> 0 | AI21: =B21-SUM(C21:AG21) -> 2 | AJ21: =B21-AH21 -> 2 | AK21: =AJ21-AI21 -> 0 | AL21: ='MASTER STOCK'!I18 -> 33700 | AM21: ='MASTER STOCK'!L18 -> 57290 | AN21: =AH21*AM21 -> 0 | AO21: =(AH21*AM21)-(AH21*AL21) -> 0
A22: ='MASTER STOCK'!F19 -> Kabel bintik serabut tembaga motor mobil 20mx0.5mm/0,85mm hitam 0,5mm | B22: ='MASTER STOCK'!G19 -> 2 | AH22: =SUM(C22:AG22) -> 0 | AI22: =B22-SUM(C22:AG22) -> 2 | AJ22: =B22-AH22 -> 2 | AK22: =AJ22-AI22 -> 0 | AL22: ='MASTER STOCK'!I19 -> 33700 | AM22: ='MASTER STOCK'!L19 -> 57290 | AN22: =AH22*AM22 -> 0 | AO22: =(AH22*AM22)-(AH22*AL22) -> 0
A23: ='MASTER STOCK'!F20 -> Mata Gerinda keramik 4 inch kering | B23: ='MASTER STOCK'!G20 -> 5 | AH23: =SUM(C23:AG23) -> 0 | AI23: =B23-SUM(C23:AG23) -> 5 | AJ23: =B23-AH23 -> 5 | AK23: =AJ23-AI23 -> 0 | AL23: ='MASTER STOCK'!I20 -> 12000 | AM23: ='MASTER STOCK'!L20 -> 18000 | AN23: =AH23*AM23 -> 0 | AO23: =(AH23*AM23)-(AH23*AL23) -> 0
A24: ='MASTER STOCK'!F21 -> Kabel tunggal serabut 0.8mmx25m biru 25m | B24: ='MASTER STOCK'!G21 -> 1 | AH24: =SUM(C24:AG24) -> 0 | AI24: =B24-SUM(C24:AG24) -> 1 | AJ24: =B24-AH24 -> 1 | AK24: =AJ24-AI24 -> 0 | AL24: ='MASTER STOCK'!I21 -> 17500 | AM24: ='MASTER STOCK'!L21 -> 29750 | AN24: =AH24*AM24 -> 0 | AO24: =(AH24*AM24)-(AH24*AL24) -> 0
A25: ='MASTER STOCK'!F22 -> Kabel tunggal serabut 0.8mmx25m Hitam 25m | B25: ='MASTER STOCK'!G22 -> 1 | AH25: =SUM(C25:AG25) -> 0 | AI25: =B25-SUM(C25:AG25) -> 1 | AJ25: =B25-AH25 -> 1 | AK25: =AJ25-AI25 -> 0 | AL25: ='MASTER STOCK'!I22 -> 17500 | AM25: ='MASTER STOCK'!L22 -> 29750 | AN25: =AH25*AM25 -> 0 | AO25: =(AH25*AM25)-(AH25*AL25) -> 0
A26: ='MASTER STOCK'!F23 -> Lampu Hias LED strip USB 10m+adaptor | B26: ='MASTER STOCK'!G23 -> 2 | AH26: =SUM(C26:AG26) -> 0 | AI26: =B26-SUM(C26:AG26) -> 2 | AJ26: =B26-AH26 -> 2 | AK26: =AJ26-AI26 -> 0 | AL26: ='MASTER STOCK'!I23 -> 50000 | AM26: ='MASTER STOCK'!L23 -> 65000 | AN26: =AH26*AM26 -> 0 | AO26: =(AH26*AM26)-(AH26*AL26) -> 0
A27: ='MASTER STOCK'!F24 -> Lampu LED strip outdoor rainbow 10m +adaptor | B27: ='MASTER STOCK'!G24 -> 5 | AH27: =SUM(C27:AG27) -> 0 | AI27: =B27-SUM(C27:AG27) -> 5 | AJ27: =B27-AH27 -> 5 | AK27: =AJ27-AI27 -> 0 | AL27: ='MASTER STOCK'!I24 -> 27000 | AM27: ='MASTER STOCK'!L24 -> 35100 | AN27: =AH27*AM27 -> 0 | AO27: =(AH27*AM27)-(AH27*AL27) -> 0
A28: ='MASTER STOCK'!F25 -> Lampu LED strip outdoor merah putih 10m +adaptor | B28: ='MASTER STOCK'!G25 -> 5 | AH28: =SUM(C28:AG28) -> 0 | AI28: =B28-SUM(C28:AG28) -> 5 | AJ28: =B28-AH28 -> 5 | AK28: =AJ28-AI28 -> 0 | AL28: ='MASTER STOCK'!I25 -> 30000 | AM28: ='MASTER STOCK'!L25 -> 40500 | AN28: =AH28*AM28 -> 0 | AO28: =(AH28*AM28)-(AH28*AL28) -> 0
A29: ='MASTER STOCK'!F26 -> Lampu tumbler 10m (rainbow) | B29: ='MASTER STOCK'!G26 -> 5 | AH29: =SUM(C29:AG29) -> 0 | AI29: =B29-SUM(C29:AG29) -> 5 | AJ29: =B29-AH29 -> 5 | AK29: =AJ29-AI29 -> 0 | AL29: ='MASTER STOCK'!I26 -> 11000 | AM29: ='MASTER STOCK'!L26 -> 14300 | AN29: =AH29*AM29 -> 0 | AO29: =(AH29*AM29)-(AH29*AL29) -> 0
A30: ='MASTER STOCK'!F27 -> WD Gerinda potong besi | B30: ='MASTER STOCK'!G27 -> 60 | Z30: 1 | AA30: 1 | AH30: =SUM(C30:AG30) -> 2 | AI30: =B30-SUM(C30:AG30) -> 58 | AJ30: =B30-AH30 -> 58 | AK30: =AJ30-AI30 -> 0 | AL30: ='MASTER STOCK'!I27 -> 2900 | AM30: ='MASTER STOCK'!L27 -> 5000 | AN30: =AH30*AM30 -> 10000 | AO30: =(AH30*AM30)-(AH30*AL30) -> 4200
A31: ='MASTER STOCK'!F28 -> Meteran karet 7,5m (merk HPP) | B31: ='MASTER STOCK'!G28 -> 3 | AH31: =SUM(C31:AG31) -> 0 | AI31: =B31-SUM(C31:AG31) -> 3 | AJ31: =B31-AH31 -> 3 | AK31: =AJ31-AI31 -> 0 | AL31: ='MASTER STOCK'!I28 -> 12800 | AM31: ='MASTER STOCK'!L28 -> 16640 | AN31: =AH31*AM31 -> 0 | AO31: =(AH31*AM31)-(AH31*AL31) -> 0
A32: ='MASTER STOCK'!F29 -> Meteran karet 5m (merk VPR) | B32: ='MASTER STOCK'!G29 -> 3 | AH32: =SUM(C32:AG32) -> 0 | AI32: =B32-SUM(C32:AG32) -> 3 | AJ32: =B32-AH32 -> 3 | AK32: =AJ32-AI32 -> 0 | AL32: ='MASTER STOCK'!I29 -> 7000 | AM32: ='MASTER STOCK'!L29 -> 9100 | AN32: =AH32*AM32 -> 0 | AO32: =(AH32*AM32)-(AH32*AL32) -> 0
A33: ='MASTER STOCK'!F30 -> Kuas cat 2 1/2" (merk MDN) | B33: ='MASTER STOCK'!G30 -> 5 | AH33: =SUM(C33:AG33) -> 0 | AI33: =B33-SUM(C33:AG33) -> 5 | AJ33: =B33-AH33 -> 5 | AK33: =AJ33-AI33 -> 0 | AL33: ='MASTER STOCK'!I30 -> 5300 | AM33: ='MASTER STOCK'!L30 -> 6890 | AN33: =AH33*AM33 -> 0 | AO33: =(AH33*AM33)-(AH33*AL33) -> 0
A34: ='MASTER STOCK'!F31 -> Kuas cat 2" (merk MDN) | B34: ='MASTER STOCK'!G31 -> 5 | AH34: =SUM(C34:AG34) -> 0 | AI34: =B34-SUM(C34:AG34) -> 5 | AJ34: =B34-AH34 -> 5 | AK34: =AJ34-AI34 -> 0 | AL34: ='MASTER STOCK'!I31 -> 4400 | AM34: ='MASTER STOCK'!L31 -> 5720 | AN34: =AH34*AM34 -> 0 | AO34: =(AH34*AM34)-(AH34*AL34) -> 0
A35: ='MASTER STOCK'!F32 -> Kuas cat 3" (merk MDN) | B35: ='MASTER STOCK'!G32 -> 5 | AH35: =SUM(C35:AG35) -> 0 | AI35: =B35-SUM(C35:AG35) -> 5 | AJ35: =B35-AH35 -> 5 | AK35: =AJ35-AI35 -> 0 | AL35: ='MASTER STOCK'!I32 -> 6300 | AM35: ='MASTER STOCK'!L32 -> 8190 | AN35: =AH35*AM35 -> 0 | AO35: =(AH35*AM35)-(AH35*AL35) -> 0
A36: ='MASTER STOCK'!F33 -> Kuas cat 1 1/2" (merk MDN) | B36: ='MASTER STOCK'!G33 -> 5 | AH36: =SUM(C36:AG36) -> 0 | AI36: =B36-SUM(C36:AG36) -> 5 | AJ36: =B36-AH36 -> 5 | AK36: =AJ36-AI36 -> 0 | AL36: ='MASTER STOCK'!I33 -> 3400 | AM36: ='MASTER STOCK'!L33 -> 4420 | AN36: =AH36*AM36 -> 0 | AO36: =(AH36*AM36)-(AH36*AL36) -> 0
A37: ='MASTER STOCK'!F34 -> Kuas cat 1" (merk MDN) | B37: ='MASTER STOCK'!G34 -> 5 | AH37: =SUM(C37:AG37) -> 0 | AI37: =B37-SUM(C37:AG37) -> 5 | AJ37: =B37-AH37 -> 5 | AK37: =AJ37-AI37 -> 0 | AL37: ='MASTER STOCK'!I34 -> 2300 | AM37: ='MASTER STOCK'!L34 -> 2990 | AN37: =AH37*AM37 -> 0 | AO37: =(AH37*AM37)-(AH37*AL37) -> 0
A38: ='MASTER STOCK'!F35 -> Kran PVC Tembok 3/4" | B38: ='MASTER STOCK'!G35 -> 24 | AH38: =SUM(C38:AG38) -> 0 | AI38: =B38-SUM(C38:AG38) -> 24 | AJ38: =B38-AH38 -> 24 | AK38: =AJ38-AI38 -> 0 | AL38: ='MASTER STOCK'!I35 -> 4200 | AM38: ='MASTER STOCK'!L35 -> 6000 | AN38: =AH38*AM38 -> 0 | AO38: =(AH38*AM38)-(AH38*AL38) -> 0
A39: ='MASTER STOCK'!F36 -> Kran PVC Tembok 1/2" | B39: ='MASTER STOCK'!G36 -> 24 | AH39: =SUM(C39:AG39) -> 0 | AI39: =B39-SUM(C39:AG39) -> 24 | AJ39: =B39-AH39 -> 24 | AK39: =AJ39-AI39 -> 0 | AL39: ='MASTER STOCK'!I36 -> 4200 | AM39: ='MASTER STOCK'!L36 -> 6000 | AN39: =AH39*AM39 -> 0 | AO39: =(AH39*AM39)-(AH39*AL39) -> 0
A40: ='MASTER STOCK'!F37 -> Lampu bohlam inlite 5w Putih | B40: ='MASTER STOCK'!G37 -> 7 | AH40: =SUM(C40:AG40) -> 0 | AI40: =B40-SUM(C40:AG40) -> 7 | AJ40: =B40-AH40 -> 7 | AK40: =AJ40-AI40 -> 0 | AL40: ='MASTER STOCK'!I37 -> 13000 | AM40: ='MASTER STOCK'!L37 -> 18200 | AN40: =AH40*AM40 -> 0 | AO40: =(AH40*AM40)-(AH40*AL40) -> 0
A41: ='MASTER STOCK'!F38 -> Lampu bohlam inlite 7w Putih | B41: ='MASTER STOCK'!G38 -> 2 | AH41: =SUM(C41:AG41) -> 0 | AI41: =B41-SUM(C41:AG41) -> 2 | AJ41: =B41-AH41 -> 2 | AK41: =AJ41-AI41 -> 0 | AL41: ='MASTER STOCK'!I38 -> 16200 | AM41: ='MASTER STOCK'!L38 -> 22680 | AN41: =AH41*AM41 -> 0 | AO41: =(AH41*AM41)-(AH41*AL41) -> 0
A42: ='MASTER STOCK'!F39 -> Lampu bohlam inlite 15w Putih | B42: ='MASTER STOCK'!G39 -> 4 | AH42: =SUM(C42:AG42) -> 0 | AI42: =B42-SUM(C42:AG42) -> 4 | AJ42: =B42-AH42 -> 4 | AK42: =AJ42-AI42 -> 0 | AL42: ='MASTER STOCK'!I39 -> 28000 | AM42: ='MASTER STOCK'!L39 -> 39200 | AN42: =AH42*AM42 -> 0 | AO42: =(AH42*AM42)-(AH42*AL42) -> 0
A43: ='MASTER STOCK'!F40 -> Lampu bohlam inlite 12w Putih | B43: ='MASTER STOCK'!G40 -> 6 | AH43: =SUM(C43:AG43) -> 0 | AI43: =B43-SUM(C43:AG43) -> 6 | AJ43: =B43-AH43 -> 6 | AK43: =AJ43-AI43 -> 0 | AL43: ='MASTER STOCK'!I40 -> 25000 | AM43: ='MASTER STOCK'!L40 -> 30000 | AN43: =AH43*AM43 -> 0 | AO43: =(AH43*AM43)-(AH43*AL43) -> 0
A44: ='MASTER STOCK'!F41 -> Lampu tintin platinum LED 9w | B44: ='MASTER STOCK'!G41 -> 5 | R44: 1 | AH44: =SUM(C44:AG44) -> 1 | AI44: =B44-SUM(C44:AG44) -> 4 | AJ44: =B44-AH44 -> 4 | AK44: =AJ44-AI44 -> 0 | AL44: ='MASTER STOCK'!I41 -> 7000 | AM44: ='MASTER STOCK'!L41 -> 9800 | AN44: =AH44*AM44 -> 9800 | AO44: =(AH44*AM44)-(AH44*AL44) -> 2800
A45: ='MASTER STOCK'!F42 -> Lampu tintin platinum LED 5w | B45: ='MASTER STOCK'!G42 -> 5 | R45: 1 | AH45: =SUM(C45:AG45) -> 1 | AI45: =B45-SUM(C45:AG45) -> 4 | AJ45: =B45-AH45 -> 4 | AK45: =AJ45-AI45 -> 0 | AL45: ='MASTER STOCK'!I42 -> 5000 | AM45: ='MASTER STOCK'!L42 -> 7000 | AN45: =AH45*AM45 -> 7000 | AO45: =(AH45*AM45)-(AH45*AL45) -> 2000
A46: ='MASTER STOCK'!F43 -> Lampu tintin platinum LED 21w | B46: ='MASTER STOCK'!G43 -> 3 | AH46: =SUM(C46:AG46) -> 0 | AI46: =B46-SUM(C46:AG46) -> 3 | AJ46: =B46-AH46 -> 3 | AK46: =AJ46-AI46 -> 0 | AL46: ='MASTER STOCK'!I43 -> 15500 | AM46: ='MASTER STOCK'!L43 -> 21700 | AN46: =AH46*AM46 -> 0 | AO46: =(AH46*AM46)-(AH46*AL46) -> 0
A47: ='MASTER STOCK'!F44 -> Lampu tintin platinum LED 15w | B47: ='MASTER STOCK'!G44 -> 5 | AH47: =SUM(C47:AG47) -> 0 | AI47: =B47-SUM(C47:AG47) -> 5 | AJ47: =B47-AH47 -> 5 | AK47: =AJ47-AI47 -> 0 | AL47: ='MASTER STOCK'!I44 -> 8800 | AM47: ='MASTER STOCK'!L44 -> 13000 | AN47: =AH47*AM47 -> 0 | AO47: =(AH47*AM47)-(AH47*AL47) -> 0
A48: ='MASTER STOCK'!F45 -> Lampu tintin platinum LED 12w | B48: ='MASTER STOCK'!G45 -> 5 | AH48: =SUM(C48:AG48) -> 0 | AI48: =B48-SUM(C48:AG48) -> 5 | AJ48: =B48-AH48 -> 5 | AK48: =AJ48-AI48 -> 0 | AL48: ='MASTER STOCK'!I45 -> 7800 | AM48: ='MASTER STOCK'!L45 -> 10920 | AN48: =AH48*AM48 -> 0 | AO48: =(AH48*AM48)-(AH48*AL48) -> 0
A49: ='MASTER STOCK'!F46 -> Lampu tintin platinum LED 7w | B49: ='MASTER STOCK'!G46 -> 5 | AH49: =SUM(C49:AG49) -> 0 | AI49: =B49-SUM(C49:AG49) -> 5 | AJ49: =B49-AH49 -> 5 | AK49: =AJ49-AI49 -> 0 | AL49: ='MASTER STOCK'!I46 -> 5800 | AM49: ='MASTER STOCK'!L46 -> 8120 | AN49: =AH49*AM49 -> 0 | AO49: =(AH49*AM49)-(AH49*AL49) -> 0
A50: ='MASTER STOCK'!F47 -> Gergaji kayu (POPEYE) 18 inch | B50: ='MASTER STOCK'!G47 -> 4 | AH50: =SUM(C50:AG50) -> 0 | AI50: =B50-SUM(C50:AG50) -> 4 | AJ50: =B50-AH50 -> 4 | AK50: =AJ50-AI50 -> 0 | AL50: ='MASTER STOCK'!I47 -> 15000 | AM50: ='MASTER STOCK'!L47 -> 19500 | AN50: =AH50*AM50 -> 0 | AO50: =(AH50*AM50)-(AH50*AL50) -> 0
A51: ='MASTER STOCK'!F48 -> Kapi plamir plastik PVC 9" (23cm) | B51: ='MASTER STOCK'!G48 -> 10 | AH51: =SUM(C51:AG51) -> 0 | AI51: =B51-SUM(C51:AG51) -> 10 | AJ51: =B51-AH51 -> 10 | AK51: =AJ51-AI51 -> 0 | AL51: ='MASTER STOCK'!I48 -> 2200 | AM51: ='MASTER STOCK'!L48 -> 3300 | AN51: =AH51*AM51 -> 0 | AO51: =(AH51*AM51)-(AH51*AL51) -> 0
A52: ='MASTER STOCK'!F49 -> Kapi plamir plastik PVC 5" (12cm) | B52: ='MASTER STOCK'!G49 -> 5 | AH52: =SUM(C52:AG52) -> 0 | AI52: =B52-SUM(C52:AG52) -> 5 | AJ52: =B52-AH52 -> 5 | AK52: =AJ52-AI52 -> 0 | AL52: ='MASTER STOCK'!I49 -> 1100 | AM52: ='MASTER STOCK'!L49 -> 1650 | AN52: =AH52*AM52 -> 0 | AO52: =(AH52*AM52)-(AH52*AL52) -> 0
A53: ='MASTER STOCK'!F50 -> Kapi plamir plastik PVC 7" (18cm) | B53: ='MASTER STOCK'!G50 -> 10 | AH53: =SUM(C53:AG53) -> 0 | AI53: =B53-SUM(C53:AG53) -> 10 | AJ53: =B53-AH53 -> 10 | AK53: =AJ53-AI53 -> 0 | AL53: ='MASTER STOCK'!I50 -> 1500 | AM53: ='MASTER STOCK'!L50 -> 2250 | AN53: =AH53*AM53 -> 0 | AO53: =(AH53*AM53)-(AH53*AL53) -> 0
A54: ='MASTER STOCK'!F51 -> Tang Kombinasi karet 8" | B54: ='MASTER STOCK'!G51 -> 5 | AH54: =SUM(C54:AG54) -> 0 | AI54: =B54-SUM(C54:AG54) -> 5 | AJ54: =B54-AH54 -> 5 | AK54: =AJ54-AI54 -> 0 | AL54: ='MASTER STOCK'!I51 -> 12000 | AM54: ='MASTER STOCK'!L51 -> 15600 | AN54: =AH54*AM54 -> 0 | AO54: =(AH54*AM54)-(AH54*AL54) -> 0
A55: ='MASTER STOCK'!F52 -> Tang Kombinasi 8" | B55: ='MASTER STOCK'!G52 -> 5 | AH55: =SUM(C55:AG55) -> 0 | AI55: =B55-SUM(C55:AG55) -> 5 | AJ55: =B55-AH55 -> 5 | AK55: =AJ55-AI55 -> 0 | AL55: ='MASTER STOCK'!I52 -> 12500 | AM55: ='MASTER STOCK'!L52 -> 16250 | AN55: =AH55*AM55 -> 0 | AO55: =(AH55*AM55)-(AH55*AL55) -> 0
A56: ='MASTER STOCK'!F53 -> Stop Kontak Hitam 3L 5M | B56: ='MASTER STOCK'!G53 -> 2 | AH56: =SUM(C56:AG56) -> 0 | AI56: =B56-SUM(C56:AG56) -> 2 | AJ56: =B56-AH56 -> 2 | AK56: =AJ56-AI56 -> 0 | AL56: ='MASTER STOCK'!I53 -> 18400 | AM56: ='MASTER STOCK'!L53 -> 27600 | AN56: =AH56*AM56 -> 0 | AO56: =(AH56*AM56)-(AH56*AL56) -> 0
A57: ='MASTER STOCK'!F54 -> Stop Kontak Hitam 4L 5M | B57: ='MASTER STOCK'!G54 -> 3 | AH57: =SUM(C57:AG57) -> 0 | AI57: =B57-SUM(C57:AG57) -> 3 | AJ57: =B57-AH57 -> 3 | AK57: =AJ57-AI57 -> 0 | AL57: ='MASTER STOCK'!I54 -> 19600 | AM57: ='MASTER STOCK'!L54 -> 29400 | AN57: =AH57*AM57 -> 0 | AO57: =(AH57*AM57)-(AH57*AL57) -> 0
... A60: ='MASTER STOCK'!F57 -> Palu Konde besi cor gagang kayu ukuran 1LB | B60: ='MASTER STOCK'!G57 -> 3 | AH60: =SUM(C60:AG60) -> 0 | AI60: =B60-SUM(C60:AG60) -> 3 | AJ60: =B60-AH60 -> 3 | AK60: =AJ60-AI60 -> 0 | AL60: ='MASTER STOCK'!I57 -> 17000 | AM60: ='MASTER STOCK'!L57 -> 22100 | AN60: =AH60*AM60 -> 0 | AO60: =(AH60*AM60)-(AH60*AL60) -> 0
A61: ='MASTER STOCK'!F58 -> Lem kuning 100gr | B61: ='MASTER STOCK'!G58 -> 25 | Z61: 1 | AH61: =SUM(C61:AG61) -> 1 | AI61: =B61-SUM(C61:AG61) -> 24 | AJ61: =B61-AH61 -> 24 | AK61: =AJ61-AI61 -> 0 | AL61: ='MASTER STOCK'!I58 -> 10000 | AM61: ='MASTER STOCK'!L58 -> 15000 | AN61: =AH61*AM61 -> 15000 | AO61: =(AH61*AM61)-(AH61*AL61) -> 5000
A62: ='MASTER STOCK'!F59 -> Lem aica aibon kuning 125gr | B62: ='MASTER STOCK'!G59 -> 2 | AH62: =SUM(C62:AG62) -> 0 | AI62: =B62-SUM(C62:AG62) -> 2 | AJ62: =B62-AH62 -> 2 | AK62: =AJ62-AI62 -> 0 | AL62: ='MASTER STOCK'!I59 -> 18200 | AM62: ='MASTER STOCK'!L59 -> 27300 | AN62: =AH62*AM62 -> 0 | AO62: =(AH62*AM62)-(AH62*AL62) -> 0
A63: ='MASTER STOCK'!F60 -> Kuas 4" incco | B63: ='MASTER STOCK'!G60 -> 3 | AH63: =SUM(C63:AG63) -> 0 | AI63: =B63-SUM(C63:AG63) -> 3 | AJ63: =B63-AH63 -> 3 | AK63: =AJ63-AI63 -> 0 | AL63: ='MASTER STOCK'!I60 -> 15000 | AM63: ='MASTER STOCK'!L60 -> 19500 | AN63: =AH63*AM63 -> 0 | AO63: =(AH63*AM63)-(AH63*AL63) -> 0
A64: ='MASTER STOCK'!F61 -> Meteran Autostop Wilmer 5m*19mm | B64: ='MASTER STOCK'!G61 -> 2 | AH64: =SUM(C64:AG64) -> 0 | AI64: =B64-SUM(C64:AG64) -> 2 | AJ64: =B64-AH64 -> 2 | AK64: =AJ64-AI64 -> 0 | AL64: ='MASTER STOCK'!I61 -> 25000 | AM64: ='MASTER STOCK'!L61 -> 30000 | AN64: =AH64*AM64 -> 0 | AO64: =(AH64*AM64)-(AH64*AL64) -> 0
A65: ='MASTER STOCK'!F62 -> Precision S/Driver Obeng 6S DIY | B65: ='MASTER STOCK'!G62 -> 2 | AH65: =SUM(C65:AG65) -> 0 | AI65: =B65-SUM(C65:AG65) -> 2 | AJ65: =B65-AH65 -> 2 | AK65: =AJ65-AI65 -> 0 | AL65: ='MASTER STOCK'!I62 -> 9500 | AM65: ='MASTER STOCK'!L62 -> 13300 | AN65: =AH65*AM65 -> 0 | AO65: =(AH65*AM65)-(AH65*AL65) -> 0
A66: ='MASTER STOCK'!F63 -> Blades / Isi Cutter Besar DIY | B66: ='MASTER STOCK'!G63 -> 20 | AH66: =SUM(C66:AG66) -> 0 | AI66: =B66-SUM(C66:AG66) -> 20 | AJ66: =B66-AH66 -> 20 | AK66: =AJ66-AI66 -> 0 | AL66: ='MASTER STOCK'!I63 -> 1150 | AM66: ='MASTER STOCK'!L63 -> 1495 | AN66: =AH66*AM66 -> 0 | AO66: =(AH66*AM66)-(AH66*AL66) -> 0
A67: ='MASTER STOCK'!F64 -> Blades / Isi Cutter Kecil DIY | B67: ='MASTER STOCK'!G64 -> 20 | AH67: =SUM(C67:AG67) -> 0 | AI67: =B67-SUM(C67:AG67) -> 20 | AJ67: =B67-AH67 -> 20 | AK67: =AJ67-AI67 -> 0 | AL67: ='MASTER STOCK'!I64 -> 700 | AM67: ='MASTER STOCK'!L64 -> 1050 | AN67: =AH67*AM67 -> 0 | AO67: =(AH67*AM67)-(AH67*AL67) -> 0
A68: ='MASTER STOCK'!F65 -> Screwdriver / Obeng 4" isi 2 DIY | B68: ='MASTER STOCK'!G65 -> 2 | AH68: =SUM(C68:AG68) -> 0 | AI68: =B68-SUM(C68:AG68) -> 2 | AJ68: =B68-AH68 -> 2 | AK68: =AJ68-AI68 -> 0 | AL68: ='MASTER STOCK'!I65 -> 12000 | AM68: ='MASTER STOCK'!L65 -> 15600 | AN68: =AH68*AM68 -> 0 | AO68: =(AH68*AM68)-(AH68*AL68) -> 0
A69: ='MASTER STOCK'!F66 -> Test Pen DIY | B69: ='MASTER STOCK'!G66 -> 2 | AH69: =SUM(C69:AG69) -> 0 | AI69: =B69-SUM(C69:AG69) -> 2 | AJ69: =B69-AH69 -> 2 | AK69: =AJ69-AI69 -> 0 | AL69: ='MASTER STOCK'!I66 -> 12000 | AM69: ='MASTER STOCK'!L66 -> 15600 | AN69: =AH69*AM69 -> 0 | AO69: =(AH69*AM69)-(AH69*AL69) -> 0
A70: ='MASTER STOCK'!F67 -> Door Bolt / Selot Pintu DIY 4" | B70: ='MASTER STOCK'!G67 -> 3 | AH70: =SUM(C70:AG70) -> 0 | AI70: =B70-SUM(C70:AG70) -> 3 | AJ70: =B70-AH70 -> 3 | AK70: =AJ70-AI70 -> 0 | AL70: ='MASTER STOCK'!I67 -> 7500 | AM70: ='MASTER STOCK'!L67 -> 9750 | AN70: =AH70*AM70 -> 0 | AO70: =(AH70*AM70)-(AH70*AL70) -> 0
A71: ='MASTER STOCK'!F68 -> Door Bolt / Selot Pintu DIY 3" | B71: ='MASTER STOCK'!G68 -> 2 | AH71: =SUM(C71:AG71) -> 0 | AI71: =B71-SUM(C71:AG71) -> 2 | AJ71: =B71-AH71 -> 2 | AK71: =AJ71-AI71 -> 0 | AL71: ='MASTER STOCK'!I68 -> 10500 | AM71: ='MASTER STOCK'!L68 -> 13650 | AN71: =AH71*AM71 -> 0 | AO71: =(AH71*AM71)-(AH71*AL71) -> 0
A72: ='MASTER STOCK'!F69 -> Kuas 2" incco | B72: ='MASTER STOCK'!G69 -> 3 | AH72: =SUM(C72:AG72) -> 0 | AI72: =B72-SUM(C72:AG72) -> 3 | AJ72: =B72-AH72 -> 3 | AK72: =AJ72-AI72 -> 0 | AL72: ='MASTER STOCK'!I69 -> 7000 | AM72: ='MASTER STOCK'!L69 -> 9100 | AN72: =AH72*AM72 -> 0 | AO72: =(AH72*AM72)-(AH72*AL72) -> 0
A73: ='MASTER STOCK'!F70 -> Kuas 1" incco | B73: ='MASTER STOCK'!G70 -> 5 | AH73: =SUM(C73:AG73) -> 0 | AI73: =B73-SUM(C73:AG73) -> 5 | AJ73: =B73-AH73 -> 5 | AK73: =AJ73-AI73 -> 0 | AL73: ='MASTER STOCK'!I70 -> 3500 | AM73: ='MASTER STOCK'!L70 -> 4550 | AN73: =AH73*AM73 -> 0 | AO73: =(AH73*AM73)-(AH73*AL73) -> 0
... A365: ='MASTER STOCK'!F362 -> WATERMUR 3/4 | B365: ='MASTER STOCK'!G362 -> 5 | AH365: =SUM(C365:AG365) -> 0 | AI365: =B365-SUM(C365:AG365) -> 5 | AJ365: =B365-AH365 -> 5 | AK365: =AJ365-AI365 -> 0 | AL365: ='MASTER STOCK'!I362 -> 4700 | AM365: ='MASTER STOCK'!L362 -> 7000 | AN365: =AH365*AM365 -> 0 | AO365: =(AH365*AM365)-(AH365*AL365) -> 0
A366: ='MASTER STOCK'!F363 -> SOLDER GAGANG KAYU 40W | B366: ='MASTER STOCK'!G363 -> 5 | AH366: =SUM(C366:AG366) -> 0 | AI366: =B366-SUM(C366:AG366) -> 5 | AJ366: =B366-AH366 -> 5 | AK366: =AJ366-AI366 -> 0 | AM366: ='MASTER STOCK'!L363 -> 12000 | AN366: =AH366*AM366 -> 0 | AO366: =(AH366*AM366)-(AH366*AL366) -> 0
A367: ='MASTER STOCK'!F364 -> KUAS GRT 3" | B367: ='MASTER STOCK'!G364 -> 12 | AH367: =SUM(C367:AG367) -> 0 | AI367: =B367-SUM(C367:AG367) -> 12 | AJ367: =B367-AH367 -> 12 | AK367: =AJ367-AI367 -> 0 | AM367: ='MASTER STOCK'!L364 -> 7500 | AN367: =AH367*AM367 -> 0 | AO367: =(AH367*AM367)-(AH367*AL367) -> 0
A368: ='MASTER STOCK'!F365 -> PENGAMAN REGULATOR | B368: ='MASTER STOCK'!G365 -> 3 | AK368: =AJ368-AI368 -> 0 | AM368: ='MASTER STOCK'!L365 -> 12000 | AN368: =AH368*AM368 -> 0 | AO368: =(AH368*AM368)-(AH368*AL368) -> 0
A369: ='MASTER STOCK'!F366 -> KLEM REGULATOR | B369: ='MASTER STOCK'!G366 -> 20 | AM369: ='MASTER STOCK'!L366 -> 2500
A370: ='MASTER STOCK'!F367 -> TIMBA STANDART | B370: ='MASTER STOCK'!G367 -> 10 | AM370: ='MASTER STOCK'!L367 -> 8000
A371: ='MASTER STOCK'!F368 -> KNEE DRAT DALAM 1/2 DIM | B371: ='MASTER STOCK'!G368 -> 15 | AM371: ='MASTER STOCK'!L368 -> 3500
A372: ='MASTER STOCK'!F369 -> AMPLAS UK 60 | B372: ='MASTER STOCK'!G369 -> 10 | AM372: ='MASTER STOCK'!L369 -> 7000
A373: ='MASTER STOCK'!F370 -> AMPLAS UK 150 | B373: ='MASTER STOCK'!G370 -> 10 | AM373: ='MASTER STOCK'!L370 -> 7000
A374: ='MASTER STOCK'!F371 -> AMPLAS UK 240 | B374: ='MASTER STOCK'!G371 -> 10 | AM374: ='MASTER STOCK'!L371 -> 7000
A375: ='MASTER STOCK'!F372 -> WATERMUR DD 3/4 | B375: ='MASTER STOCK'!G372 -> 5 | AM375: ='MASTER STOCK'!L372 -> 8000
A376: ='MASTER STOCK'!F373 -> BENDRAT 5KG | B376: ='MASTER STOCK'!G373 -> 5 | AM376: ='MASTER STOCK'!L373 -> 25000
A377: ='MASTER STOCK'!F374 -> S MERDEKA 5 | B377: ='MASTER STOCK'!G374 -> 5 | AM377: ='MASTER STOCK'!L374 -> 4300
A378: ='MASTER STOCK'!F375 | B378: ='MASTER STOCK'!G375 -> 0 | AM378: ='MASTER STOCK'!L375
A379: ='MASTER STOCK'!F376 | B379: ='MASTER STOCK'!G376 -> 0 | AM379: ='MASTER STOCK'!L376
A380: ='MASTER STOCK'!F377 | B380: ='MASTER STOCK'!G377 -> 0 | AM380: ='MASTER STOCK'!L377
... A398: ='MASTER STOCK'!F395 | B398: ='MASTER STOCK'!G395 | AM398: ='MASTER STOCK'!L395
A399: ='MASTER STOCK'!F396 | B399: ='MASTER STOCK'!G396
A400: ='MASTER STOCK'!F397 | B400: ='MASTER STOCK'!G397
A401: ='MASTER STOCK'!F398 | B401: ='MASTER STOCK'!G398
A402: ='MASTER STOCK'!F399 | B402: ='MASTER STOCK'!G399
A403: ='MASTER STOCK'!F400 | B403: ='MASTER STOCK'!G400
A404: ='MASTER STOCK'!F401 | B404: ='MASTER STOCK'!G401
A405: ='MASTER STOCK'!F402 | B405: ='MASTER STOCK'!G402
B406: ='MASTER STOCK'!G403
B407: ='MASTER STOCK'!G404
B408: ='MASTER STOCK'!G405
B409: ='MASTER STOCK'!G406
B410: ='MASTER STOCK'!G407
...

Sheet MASTER STOCK
A1: NO | B1: TANGGAL | C1: KODE BARANG | D1: KATEGORI | E1: NOMOR RESI | F1: NAMA BARANG | G1: QTY | H1: STOK AWAL | I1: HARGA BELI | J1: NOMINAL | K1: MARGIN | L1: HARGA JUAL | M1: HARGA ATAS | N1: HARGA BAWAH | O1: SUPPLIER | P1: STATUS | Q1: STATUS BARANG | R1: JATUH TEMPO | S1: QTY KULAK
A2: 1 | B2: 45847 | E2: 250709NWY3UCWW | F2: Fitting Gantung | G2: =H2+S2 -> 12 | H2: 12 | I2: 1400 | J2: =I2*G2 -> 16800 | K2: 0.3 | L2: =I2+((K2)*I2) -> 1820 | M2: 4000 | O2: Toko A8 (SHOPEE) | P2: LUNAS | Q2: TRUE | S2: 0
A3: 2 | B3: 45847 | E3: 250709NWY3UCWW | F3: Colokan T | G3: =H3+S3 -> 12 | H3: 12 | I3: 3000 | J3: =I3*G3 -> 36000 | K3: 0.3 | L3: =I3+((K3)*I3) -> 3900 | M3: 4000 | O3: Toko A8 (SHOPEE) | P3: LUNAS | Q3: TRUE | S3: 0
A4: 3 | B4: 45847 | E4: 250709NWY3UCWW | F4: Steker Bulat | G4: =H4+S4 -> 12 | H4: 12 | I4: 3000 | J4: =I4*G4 -> 36000 | K4: 0.3 | L4: 6000 | M4: 6000 | O4: Toko A8 (SHOPEE) | P4: LUNAS | Q4: TRUE | S4: 0
A5: 4 | B5: 45847 | E5: 250709NWY3UCWW | F5: Steker Gepeng | G5: =H5+S5 -> 12 | H5: 12 | I5: 1100 | J5: =I5*G5 -> 13200 | K5: 0.3 | L5: =I5+((K5)*I5) -> 1430 | M5: 3000 | O5: Toko A8 (SHOPEE) | P5: LUNAS | Q5: TRUE | S5: 0
A6: 5 | B6: 45847 | E6: 250709NWY3UCWW | F6: Saklar Gantung Putih jumbo | G6: =H6+S6 -> 12 | H6: 12 | I6: 2250 | J6: =I6*G6 -> 27000 | K6: 0.3 | L6: 4000 | M6: 4000 | O6: Toko A8 (SHOPEE) | P6: LUNAS | Q6: TRUE | S6: 0
A7: 6 | B7: 45847 | E7: 250709NWY3UCWW | F7: Saklar Gantung Hitam | G7: =H7+S7 -> 12 | H7: 12 | I7: 1850 | J7: =I7*G7 -> 22200 | K7: 0.3 | L7: 4000 | M7: 3500 | O7: Toko A8 (SHOPEE) | P7: LUNAS | Q7: TRUE | S7: 0
A8: 7 | B8: 45847 | C8: 8997777080323 | E8: 250709NWY3UCWX | F8: Isolasi Hitam National | G8: =H8+S8 -> 20 | H8: 20 | I8: 5150 | J8: =I8*G8 -> 103000 | K8: 0.55 | L8: =I8+((K8)*I8) -> 7982.5 | M8: 8000 | N8: 8000 | O8: ksam_uuwyn (SHOPEE) | P8: LUNAS | Q8: TRUE | S8: 0
A9: 8 | B9: 45847 | E9: 250709NXRSWD52 | F9: Lem PVC Isarplas 40gram | G9: =H9+S9 -> 24 | H9: 24 | I9: 6900 | J9: =I9*G9 -> 165600 | K9: 0.45 | L9: 9500 | M9: 9500 | O9: Arvella (SHOPEE) | P9: LUNAS | Q9: TRUE | S9: 0
A10: 9 | B10: 45847 | E10: 579559980040946979 | F10: Isolasi Kran air onda | G10: =H10+S10 -> 60 | H10: 60 | I10: 1150 | J10: =I10*G10 -> 69000 | K10: 0.3 | L10: =I10+((K10)*I10) -> 1495 | M10: 3000 | O10: Cakra Tools (TOKOPEDIA) | P10: LUNAS | Q10: TRUE | S10: 0
A11: 10 | B11: 45847 | E11: 579669984986359075 | F11: Tutup Pipa 3/4" | G11: =H11+S11 -> 50 | H11: 50 | I11: 850 | J11: =I11*G11 -> 42500 | K11: 0.5 | L11: =I11+((K11)*I11) -> 1275 | M11: 3000 | O11: PionTools Sby (TOKOPEDIA) | P11: LUNAS | Q11: TRUE | S11: 0
A12: 11 | B12: 45847 | E12: 579560031901418787 | F12: Fitting lampu gantung outdoor (10 m 5 fitting) | G12: =H12+S12 -> 1 | H12: 1 | I12: 38000 | J12: =I12*G12 -> 38000 | K12: 0.3 | L12: =I12+((K12)*I12) -> 49400 | M12: 48000 | O12: Msizg shop (TOKOPEDIA) | P12: LUNAS | Q12: TRUE | S12: 0
A13: 12 | B13: 45847 | E13: 579560282645497123 | F13: Obeng karet 4" plus | G13: =H13+S13 -> 5 | H13: 5 | I13: 5500 | J13: =I13*G13 -> 27500 | K13: 0.3 | L13: =I13+((K13)*I13) -> 7150 | M13: 11000 | O13: TripleWayElektrik (TOKOPEDIA) | P13: LUNAS | Q13: TRUE | S13: 0
A14: 13 | B14: 45847 | E14: 579560282645497123 | F14: Obeng karet 4" minus | G14: =H14+S14 -> 5 | H14: 5 | I14: 5500 | J14: =I14*G14 -> 27500 | K14: 0.3 | L14: =I14+((K14)*I14) -> 7150 | M14: 11000 | O14: TripleWayElektrik (TOKOPEDIA) | P14: LUNAS | Q14: TRUE | S14: 0
A15: 14 | B15: 45847 | E15: 579560282645497123 | F15: Obeng karet 6" plus | G15: =H15+S15 -> 5 | H15: 5 | I15: 7000 | J15: =I15*G15 -> 35000 | K15: 0.3 | L15: =I15+((K15)*I15) -> 9100 | M15: 14000 | O15: TripleWayElektrik (TOKOPEDIA) | P15: LUNAS | Q15: TRUE | S15: 0
A16: 15 | B16: 45847 | E16: 579560282645497123 | F16: Obeng karet 6" Minus | G16: =H16+S16 -> 5 | H16: 5 | I16: 7000 | J16: =I16*G16 -> 35000 | K16: 0.3 | L16: =I16+((K16)*I16) -> 9100 | M16: 14000 | O16: TripleWayElektrik (TOKOPEDIA) | P16: LUNAS | Q16: TRUE | S16: 0
A17: 16 | B17: 45847 | E17: 579560388730455331 | F17: Kabel Awg 24 Double 2x18 merah hitam | G17: =H17+S17 -> 2 | H17: 2 | I17: 106500 | J17: =I17*G17 -> 213000 | K17: 0.7 | L17: =I17+((K17)*I17) -> 181050 | M17: 3500 | O17: manse.strore (TOKOPEDIA) | P17: LUNAS | Q17: TRUE | S17: 0
A18: 17 | B18: 45847 | E18: 579560388730127651 | F18: Kabel bintik serabut tembaga motor mobil 20mx0.5mm/0,85mm merah 0,5mm | G18: =H18+S18 -> 2 | H18: 2 | I18: 33700 | J18: =I18*G18 -> 67400 | K18: 0.7 | L18: =I18+((K18)*I18) -> 57290 | M18: 3000 | O18: GLOBAL LED MOTORINDO (TOKOPEDIA) | P18: LUNAS | Q18: TRUE | S18: 0
A19: 18 | B19: 45847 | E19: 579560388730127651 | F19: Kabel bintik serabut tembaga motor mobil 20mx0.5mm/0,85mm hitam 0,5mm | G19: =H19+S19 -> 2 | H19: 2 | I19: 33700 | J19: =I19*G19 -> 67400 | K19: 0.7 | L19: =I19+((K19)*I19) -> 57290 | M19: 3000 | O19: GLOBAL LED MOTORINDO (TOKOPEDIA) | P19: LUNAS | Q19: TRUE | S19: 0
A20: 19 | B20: 45847 | F20: Mata Gerinda keramik 4 inch kering | G20: =H20+S20 -> 5 | H20: 5 | I20: 12000 | J20: =I20*G20 -> 60000 | K20: 0.5 | L20: =I20+((K20)*I20) -> 18000 | M20: 18000 | P20: LUNAS | Q20: TRUE | S20: 0
A21: 20 | B21: 45847 | F21: Kabel tunggal serabut 0.8mmx25m biru 25m | G21: =H21+S21 -> 1 | H21: 1 | I21: 17500 | J21: =I21*G21 -> 17500 | K21: 0.7 | L21: =I21+((K21)*I21) -> 29750 | M21: 2000 | O21: Bintang Terang Listrik (TOKOPEDIA) | P21: LUNAS | Q21: TRUE | S21: 0
A22: 21 | B22: 45847 | F22: Kabel tunggal serabut 0.8mmx25m Hitam 25m | G22: =H22+S22 -> 1 | H22: 1 | I22: 17500 | J22: =I22*G22 -> 17500 | K22: 0.7 | L22: =I22+((K22)*I22) -> 29750 | M22: 2000 | O22: Bintang Terang Listrik (TOKOPEDIA) | P22: LUNAS | Q22: TRUE | S22: 0
A23: 22 | B23: 45847 | F23: Lampu Hias LED strip USB 10m+adaptor | G23: =H23+S23 -> 2 | H23: 2 | I23: 50000 | J23: =I23*G23 -> 100000 | K23: 0.3 | L23: =I23+((K23)*I23) -> 65000 | M23: 65000 | P23: LUNAS | Q23: TRUE | S23: 0
A24: 23 | B24: 45847 | F24: Lampu LED strip outdoor rainbow 10m +adaptor | G24: =H24+S24 -> 5 | H24: 5 | I24: 27000 | J24: =I24*G24 -> 135000 | K24: 0.3 | L24: =I24+((K24)*I24) -> 35100 | M24: 45000 | P24: LUNAS | Q24: TRUE | S24: 0
A25: 24 | B25: 45847 | F25: Lampu LED strip outdoor merah putih 10m +adaptor | G25: =H25+S25 -> 5 | H25: 5 | I25: 30000 | J25: =I25*G25 -> 150000 | K25: 0.35 | L25: =I25+((K25)*I25) -> 40500 | M25: 40000 | P25: LUNAS | Q25: TRUE | S25: 0
A26: 25 | B26: 45847 | F26: Lampu tumbler 10m (rainbow) | G26: =H26+S26 -> 5 | H26: 5 | I26: 11000 | J26: =I26*G26 -> 55000 | K26: 0.3 | L26: =I26+((K26)*I26) -> 14300 | M26: 15000 | P26: LUNAS | Q26: TRUE | S26: 0
A27: 26 | B27: 45847 | E27: 250709NYQK3BEY | F27: WD Gerinda potong besi | G27: =H27+S27 -> 60 | H27: 20 | I27: 2900 | J27: =I27*G27 -> 174000 | K27: 0.5 | L27: 5000 | M27: 5000 | O27: Artha Tirta Bangunan (SHOPEE) | P27: LUNAS | Q27: TRUE | S27: 40
A28: 27 | B28: 45847 | E28: 250709NYQK3BEY | F28: Meteran karet 7,5m (merk HPP) | G28: =H28+S28 -> 3 | H28: 3 | I28: 12800 | J28: =I28*G28 -> 38400 | K28: 0.3 | L28: =I28+((K28)*I28) -> 16640 | M28: 17000 | O28: Artha Tirta Bangunan (SHOPEE) | P28: LUNAS | Q28: TRUE | S28: 0
A29: 28 | B29: 45847 | E29: 250709NYQK3BEY | F29: Meteran karet 5m (merk VPR) | G29: =H29+S29 -> 3 | H29: 3 | I29: 7000 | J29: =I29*G29 -> 21000 | K29: 0.3 | L29: =I29+((K29)*I29) -> 9100 | M29: 11000 | O29: Artha Tirta Bangunan (SHOPEE) | P29: LUNAS | Q29: TRUE | S29: 0
A30: 29 | B30: 45847 | E30: 250709NYQK3BEY | F30: Kuas cat 2 1/2" (merk MDN) | G30: =H30+S30 -> 5 | H30: 5 | I30: 5300 | J30: =I30*G30 -> 26500 | K30: 0.3 | L30: =I30+((K30)*I30) -> 6890 | M30: 7000 | O30: Artha Tirta Bangunan (SHOPEE) | P30: LUNAS | Q30: TRUE | S30: 0
A31: 30 | B31: 45847 | E31: 250709NYQK3BEY | F31: Kuas cat 2" (merk MDN) | G31: =H31+S31 -> 5 | H31: 5 | I31: 4400 | J31: =I31*G31 -> 22000 | K31: 0.3 | L31: =I31+((K31)*I31) -> 5720 | M31: 6000 | O31: Artha Tirta Bangunan (SHOPEE) | P31: LUNAS | Q31: TRUE | S31: 0
A32: 31 | B32: 45847 | E32: 250709NYQK3BEY | F32: Kuas cat 3" (merk MDN) | G32: =H32+S32 -> 5 | H32: 5 | I32: 6300 | J32: =I32*G32 -> 31500 | K32: 0.3 | L32: =I32+((K32)*I32) -> 8190 | M32: 8500 | O32: Artha Tirta Bangunan (SHOPEE) | P32: LUNAS | Q32: TRUE | S32: 0
A33: 32 | B33: 45847 | E33: 250709NYQK3BEY | F33: Kuas cat 1 1/2" (merk MDN) | G33: =H33+S33 -> 5 | H33: 5 | I33: 3400 | J33: =I33*G33 -> 17000 | K33: 0.3 | L33: =I33+((K33)*I33) -> 4420 | M33: 5000 | O33: Artha Tirta Bangunan (SHOPEE) | P33: LUNAS | Q33: TRUE | S33: 0
A34: 33 | B34: 45847 | E34: 250709NYQK3BEY | F34: Kuas cat 1" (merk MDN) | G34: =H34+S34 -> 5 | H34: 5 | I34: 2300 | J34: =I34*G34 -> 11500 | K34: 0.3 | L34: =I34+((K34)*I34) -> 2990 | M34: 4000 | O34: Artha Tirta Bangunan (SHOPEE) | P34: LUNAS | Q34: TRUE | S34: 0
A35: 34 | B35: 45847 | E35: 250709P0689QTR | F35: Kran PVC Tembok 3/4" | G35: =H35+S35 -> 24 | H35: 12 | I35: 4200 | J35: =I35*G35 -> 100800 | K35: 0.5 | L35: 6000 | M35: 6000 | O35: LARIS.CO* | P35: LUNAS | Q35: TRUE | S35: 12
A36: 35 | B36: 45847 | E36: 250709P0689QTR | F36: Kran PVC Tembok 1/2" | G36: =H36+S36 -> 24 | H36: 12 | I36: 4200 | J36: =I36*G36 -> 100800 | K36: 0.5 | L36: 6000 | M36: 6000 | O36: LARIS.CO* | P36: LUNAS | Q36: TRUE | S36: 12
A37: 36 | B37: 45847 | E37: 579563506087200035 | F37: Lampu bohlam inlite 5w Putih | G37: =H37+S37 -> 7 | H37: 7 | I37: 13000 | J37: =I37*G37 -> 91000 | K37: 0.4 | L37: =I37+((K37)*I37) -> 18200 | M37: 18000 | O37: GLOBAL PERKASA INDAH (TOKOPEDIA) | P37: LUNAS | Q37: TRUE | S37: 0
A38: 37 | B38: 45847 | E38: 579563506087200035 | F38: Lampu bohlam inlite 7w Putih | G38: =H38+S38 -> 2 | H38: 2 | I38: 16200 | J38: =I38*G38 -> 32400 | K38: 0.4 | L38: =I38+((K38)*I38) -> 22680 | M38: 22000 | O38: GLOBAL PERKASA INDAH (TOKOPEDIA) | P38: LUNAS | Q38: TRUE | S38: 0
A39: 38 | B39: 45847 | E39: 579563506087200035 | F39: Lampu bohlam inlite 15w Putih | G39: =H39+S39 -> 4 | H39: 4 | I39: 28000 | J39: =I39*G39 -> 112000 | K39: 0.4 | L39: =I39+((K39)*I39) -> 39200 | M39: 37000 | O39: GLOBAL PERKASA INDAH (TOKOPEDIA) | P39: LUNAS | Q39: TRUE | S39: 0
A40: 39 | B40: 45847 | E40: 579563506087200035 | F40: Lampu bohlam inlite 12w Putih | G40: =H40+S40 -> 6 | H40: 6 | I40: 25000 | J40: =I40*G40 -> 150000 | K40: 0.4 | L40: 30000 | M40: 30000 | O40: GLOBAL PERKASA INDAH (TOKOPEDIA) | P40: LUNAS | Q40: TRUE | S40: 0
A41: 40 | B41: 45847 | E41: 579563433831597347 | F41: Lampu tintin platinum LED 9w | G41: =H41+S41 -> 5 | H41: 5 | I41: 7000 | J41: =I41*G41 -> 35000 | K41: 0.4 | L41: =I41+((K41)*I41) -> 9800 | M41: 10000 | O41: Sie Ibin Store (TOKOPEDIA) | P41: LUNAS | Q41: TRUE | S41: 0
A42: 41 | B42: 45847 | E42: 579563433831597347 | F42: Lampu tintin platinum LED 5w | G42: =H42+S42 -> 5 | H42: 5 | I42: 5000 | J42: =I42*G42 -> 25000 | K42: 0.4 | L42: =I42+((K42)*I42) -> 7000 | M42: 7000 | O42: Sie Ibin Store (TOKOPEDIA) | P42: LUNAS | Q42: TRUE | S42: 0
A43: 42 | B43: 45847 | E43: 579563433831597347 | F43: Lampu tintin platinum LED 21w | G43: =H43+S43 -> 3 | H43: 3 | I43: 15500 | J43: =I43*G43 -> 46500 | K43: 0.4 | L43: =I43+((K43)*I43) -> 21700 | M43: 20000 | O43: Sie Ibin Store (TOKOPEDIA) | P43: LUNAS | Q43: TRUE | S43: 0
A44: 43 | B44: 45847 | E44: 579563433831597347 | F44: Lampu tintin platinum LED 15w | G44: =H44+S44 -> 5 | H44: 5 | I44: 8800 | J44: =I44*G44 -> 44000 | K44: 0.4 | L44: 13000 | M44: 13000 | O44: Sie Ibin Store (TOKOPEDIA) | P44: LUNAS | Q44: TRUE | S44: 0
A45: 44 | B45: 45847 | E45: 579563433831597347 | F45: Lampu tintin platinum LED 12w | G45: =H45+S45 -> 5 | H45: 5 | I45: 7800 | J45: =I45*G45 -> 39000 | K45: 0.4 | L45: =I45+((K45)*I45) -> 10920 | O45: Sie Ibin Store (TOKOPEDIA) | P45: LUNAS | Q45: TRUE | S45: 0
A46: 45 | B46: 45847 | E46: 579563433831597347 | F46: Lampu tintin platinum LED 7w | G46: =H46+S46 -> 5 | H46: 5 | I46: 5800 | J46: =I46*G46 -> 29000 | K46: 0.4 | L46: =I46+((K46)*I46) -> 8120 | M46: 8500 | O46: Sie Ibin Store (TOKOPEDIA) | P46: LUNAS | Q46: TRUE | S46: 0
A47: 46 | B47: 45847 | E47: 579563433831597347 | F47: Gergaji kayu (POPEYE) 18 inch | G47: =H47+S47 -> 4 | H47: 4 | I47: 15000 | J47: =I47*G47 -> 60000 | K47: 0.3 | L47: =I47+((K47)*I47) -> 19500 | O47: BocahDH (TOKOPEDIA) | P47: LUNAS | Q47: FALSE | S47: 0
A48: 47 | B48: 45847 | E48: 579563300860822819 | F48: Kapi plamir plastik PVC 9" (23cm) | G48: =H48+S48 -> 10 | H48: 10 | I48: 2200 | J48: =I48*G48 -> 22000 | K48: 0.5 | L48: =I48+((K48)*I48) -> 3300 | M48: 7500 | O48: S-Logam Teknik (TOKOPEDIA) | P48: LUNAS | Q48: TRUE | S48: 0
A49: 48 | B49: 45847 | E49: 579563300860822819 | F49: Kapi plamir plastik PVC 5" (12cm) | G49: =H49+S49 -> 5 | H49: 5 | I49: 1100 | J49: =I49*G49 -> 5500 | K49: 0.5 | L49: =I49+((K49)*I49) -> 1650 | M49: 3500 | O49: S-Logam Teknik (TOKOPEDIA) | P49: LUNAS | Q49: TRUE | S49: 0
A50: 49 | B50: 45847 | E50: 579563300860822819 | F50: Kapi plamir plastik PVC 7" (18cm) | G50: =H50+S50 -> 10 | H50: 10 | I50: 1500 | J50: =I50*G50 -> 15000 | K50: 0.5 | L50: =I50+((K50)*I50) -> 2250 | M50: 5000 | O50: S-Logam Teknik (TOKOPEDIA) | P50: LUNAS | Q50: TRUE | S50: 0
A51: 50 | B51: 45847 | E51: 579563324108670243 | F51: Tang Kombinasi karet 8" | G51: =H51+S51 -> 5 | H51: 5 | I51: 12000 | J51: =I51*G51 -> 60000 | K51: 0.3 | L51: =I51+((K51)*I51) -> 15600 | M51: 17000 | O51: Nika Tools (TOKOPEDIA) | P51: LUNAS | Q51: TRUE | S51: 0
A52: 51 | B52: 45847 | E52: 579563324109063459 | F52: Tang Kombinasi 8" | G52: =H52+S52 -> 5 | H52: 5 | I52: 12500 | J52: =I52*G52 -> 62500 | K52: 0.3 | L52: =I52+((K52)*I52) -> 16250 | M52: 17000 | O52: Verona Tools (TOKOPEDIA) | P52: LUNAS | Q52: TRUE | S52: 0
A53: 52 | B53: 45847 | E53: 579562774312224035 | F53: Stop Kontak Hitam 3L 5M | G53: =H53+S53 -> 2 | H53: 2 | I53: 18400 | J53: =I53*G53 -> 36800 | K53: 0.5 | L53: =I53+((K53)*I53) -> 27600 | M53: 25000 | O53: Twins88listrik (TOKOPEDIA) | P53: LUNAS | Q53: TRUE | S53: 0
A54: 53 | B54: 45847 | E54: 579562774312224035 | F54: Stop Kontak Hitam 4L 5M | G54: =H54+S54 -> 3 | H54: 3 | I54: 19600 | J54: =I54*G54 -> 58800 | K54: 0.5 | L54: =I54+((K54)*I54) -> 29400 | M54: 28000 | O54: Twins88listrik (TOKOPEDIA) | P54: LUNAS | Q54: TRUE | S54: 0
A55: 54 | B55: 45847 | E55: 579562774312224035 | F55: Stop Kontak Hitam 5L 5M | G55: =H55+S55 -> 6 | H55: 6 | I55: 21000 | J55: =I55*G55 -> 126000 | K55: 0.5 | L55: =I55+((K55)*I55) -> 31500 | M55: 32000 | O55: Twins88listrik (TOKOPEDIA) | P55: LUNAS | Q55: TRUE | S55: 0
A56: 55 | B56: 45847 | E56: 579562774312224035 | F56: Stop Kontak Hitam 2L 5M | G56: =H56+S56 -> 2 | H56: 2 | I56: 17000 | J56: =I56*G56 -> 34000 | K56: 0.5 | L56: =I56+((K56)*I56) -> 25500 | M56: 21000 | O56: Twins88listrik (TOKOPEDIA) | P56: LUNAS | Q56: TRUE | S56: 0
A57: 56 | B57: 45847 | E57: 579563692998231331 | F57: Palu Konde besi cor gagang kayu ukuran 1LB | G57: =H57+S57 -> 3 | H57: 3 | I57: 17000 | J57: =I57*G57 -> 51000 | K57: 0.3 | L57: =I57+((K57)*I57) -> 22100 | M57: 21000 | O57: GOnBAY Store (TOKOPEDIA) | P57: LUNAS | Q57: TRUE | S57: 0
A58: 57 | B58: 45847 | E58: 579563713467352355 | F58: Lem kuning 100gr | G58: =H58+S58 -> 25 | H58: 5 | I58: 10000 | J58: =I58*G58 -> 250000 | K58: 0.5 | L58: =I58+((K58)*I58) -> 15000 | M58: 13000 | O58: Sahabat DMP_NEW (TOKOPEDIA) | P58: LUNAS | Q58: TRUE | S58: 20
A59: 58 | B59: 45847 | E59: 579563713467745571 | F59: Lem aica aibon kuning 125gr | G59: =H59+S59 -> 2 | H59: 2 | I59: 18200 | J59: =I59*G59 -> 36400 | K59: 0.5 | L59: =I59+((K59)*I59) -> 27300 | M59: 21000 | O59: CV ANUGRAH ABADI NUSANTARA (TOKOPEDIA) | P59: LUNAS | Q59: TRUE | S59: 0
A60: 59 | B60: 45847 | F60: Kuas 4" incco | G60: =H60+S60 -> 3 | H60: 3 | I60: 15000 | J60: =I60*G60 -> 45000 | K60: 0.3 | L60: =I60+((K60)*I60) -> 19500 | M60: 19000 | O60: DIY | P60: LUNAS | Q60: TRUE | S60: 0
A61: 60 | B61: 45847 | F61: Meteran Autostop Wilmer 5m*19mm | G61: =H61+S61 -> 2 | H61: 2 | I61: 25000 | J61: =I61*G61 -> 50000 | K61: 0.25 | L61: 30000 | M61: 31000 | O61: DIY | P61: LUNAS | Q61: TRUE | S61: 0
A62: 61 | B62: 45847 | F62: Precision S/Driver Obeng 6S DIY | G62: =H62+S62 -> 2 | H62: 2 | I62: 9500 | J62: =I62*G62 -> 19000 | K62: 0.4 | L62: =I62+((K62)*I62) -> 13300 | M62: 14000 | N62: 14000 | O62: DIY | P62: LUNAS | Q62: TRUE | S62: 0
A63: 62 | B63: 45847 | F63: Blades / Isi Cutter Besar DIY | G63: =H63+S63 -> 20 | H63: 20 | I63: 1150 | J63: 23000 | K63: 0.3 | L63: =I63+((K63)*I63) -> 1495 | M63: 1500 | O63: DIY | P63: LUNAS | Q63: TRUE | S63: 0
A64: 63 | B64: 45847 | F64: Blades / Isi Cutter Kecil DIY | G64: =H64+S64 -> 20 | H64: 20 | I64: 700 | J64: =I64*G64 -> 14000 | K64: 0.5 | L64: =I64+((K64)*I64) -> 1050 | M64: 1000 | O64: DIY | P64: LUNAS | Q64: TRUE | S64: 0
A65: 64 | B65: 45847 | F65: Screwdriver / Obeng 4" isi 2 DIY | G65: =H65+S65 -> 2 | H65: 2 | I65: 12000 | J65: =I65*G65 -> 24000 | K65: 0.3 | L65: =I65+((K65)*I65) -> 15600 | M65: 20000 | N65: 16000 | O65: DIY | P65: LUNAS | Q65: TRUE | S65: 0
A66: 65 | B66: 45847 | F66: Test Pen DIY | G66: =H66+S66 -> 2 | H66: 2 | I66: 12000 | J66: =I66*G66 -> 24000 | K66: 0.3 | L66: =I66+((K66)*I66) -> 15600 | M66: 15600 | O66: DIY | P66: LUNAS | Q66: TRUE | S66: 0
A67: 66 | B67: 45847 | F67: Door Bolt / Selot Pintu DIY 4" | G67: =H67+S67 -> 3 | H67: 3 | I67: 7500 | J67: =I67*G67 -> 22500 | K67: 0.3 | L67: =I67+((K67)*I67) -> 9750 | M67: 10000 | N67: 10000 | O67: DIY | P67: LUNAS | Q67: TRUE | S67: 0
A68: 67 | B68: 45847 | F68: Door Bolt / Selot Pintu DIY 3" | G68: =H68+S68 -> 2 | H68: 2 | I68: 10500 | J68: =I68*G68 -> 21000 | K68: 0.3 | L68: =I68+((K68)*I68) -> 13650 | M68: 14000 | N68: 14000 | O68: DIY | P68: LUNAS | Q68: TRUE | S68: 0
A69: 68 | B69: 45847 | F69: Kuas 2" incco | G69: =H69+S69 -> 3 | H69: 3 | I69: 7000 | J69: =I69*G69 -> 21000 | K69: 0.3 | L69: =I69+((K69)*I69) -> 9100 | M69: 9000 | O69: DIY | P69: LUNAS | Q69: TRUE | S69: 0
A70: 69 | B70: 45847 | F70: Kuas 1" incco | G70: =H70+S70 -> 5 | H70: 5 | I70: 3500 | J70: =I70*G70 -> 17500 | K70: 0.3 | L70: =I70+((K70)*I70) -> 4550 | M70: 5000 | O70: DIY | P70: LUNAS | Q70: TRUE | S70: 0
A71: 70 | B71: 45847 | F71: Kapi Plastik Kuning DIY | G71: =H71+S71 -> 4 | H71: 4 | I71: 5500 | J71: =I71*G71 -> 22000 | K71: 0.3 | L71: =I71+((K71)*I71) -> 7150 | M71: 7500 | N71: 7500 | O71: DIY | P71: LUNAS | Q71: TRUE | S71: 0
A72: 71 | B72: 45847 | E72: 579563816346092835 | F72: Kabel Ties 3.6x300mm (85 gram) isi 100 pcs | G72: =H72+S72 -> 1 | H72: 1 | I72: 11000 | J72: =I72*G72 -> 11000 | K72: 0.5 | L72: =I72+((K72)*I72) -> 16500 | M72: 16000 | O72: Hanzcell (TOKOPEDIA) | P72: LUNAS | Q72: TRUE | S72: 0
A73: 72 | B73: 45847 | E73: 579563816346092835 | F73: Kabel Ties 3.6x150mm (60 gram) isi 100 pcs | G73: =H73+S73 -> 1 | H73: 1 | I73: 6500 | J73: =I73*G73 -> 6500 | K73: 0.5 | L73: =I73+((K73)*I73) -> 9750 | M73: 6000 | O73: Hanzcell (TOKOPEDIA) | P73: LUNAS | Q73: TRUE | S73: 0
A74: 73 | B74: 45847 | E74: 579563816346092835 | F74: Kabel Ties 2.5x200mm (50 gram) isi 100 pcs | G74: =H74+S74 -> 1 | H74: 1 | I74: 5300 | J74: =I74*G74 -> 5300 | K74: 0.5 | L74: =I74+((K74)*I74) -> 7950 | M74: 11000 | O74: Hanzcell (TOKOPEDIA) | P74: LUNAS | Q74: TRUE | S74: 0
A75: 74 | B75: 45847 | E75: 579563816346092835 | F75: Kabel Ties 2.5x100mm (50 gram) isi 100 pcs | G75: =H75+S75 -> 3 | H75: 3 | I75: 2850 | J75: =I75*G75 -> 8550 | K75: 0.5 | L75: =I75+((K75)*I75) -> 4275 | M75: 6000 | O75: Hanzcell (TOKOPEDIA) | P75: LUNAS | Q75: TRUE | S75: 0
A76: 75 | B76: 45847 | E76: 579563816346092835 | F76: Kabel Ties 3.6x300mm (85 gram) isi 100 pcs | G76: =H76+S76 -> 1 | H76: 1 | I76: 11000 | J76: =I76*G76 -> 11000 | K76: 0.5 | L76: =I76+((K76)*I76) -> 16500 | M76: 16000 | O76: Hanzcell (TOKOPEDIA) | P76: LUNAS | Q76: TRUE | S76: 0
A77: 76 | B77: 45847 | E77: 579563816346092835 | F77: Kabel Ties 2.5x150mm (50 gram) isi 100 pcs | G77: =H77+S77 -> 1 | H77: 1 | I77: 4100 | J77: =I77*G77 -> 4100 | K77: 0.5 | L77: =I77+((K77)*I77) -> 6150 | M77: 6000 | O77: Hanzcell (TOKOPEDIA) | P77: LUNAS | Q77: TRUE | S77: 0
A78: 77 | B78: 45847 | E78: 579563816346092835 | F78: Kabel Ties 3.6x250mm (80 gram) isi 100 pcs | G78: =H78+S78 -> 1 | H78: 1 | I78: 10300 | J78: =I78*G78 -> 10300 | K78: 0.5 | L78: =I78+((K78)*I78) -> 15450 | M78: 14000 | O78: Hanzcell (TOKOPEDIA) | P78: LUNAS | Q78: TRUE | S78: 0
A79: 78 | B79: 45847 | E79: 579563816346092835 | F79: Kabel Ties 4.8x200mm (85 gram) isi 100 pcs | G79: =H79+S79 -> 1 | H79: 1 | I79: 11000 | J79: =I79*G79 -> 11000 | K79: 0.5 | L79: =I79+((K79)*I79) -> 16500 | M79: 11000 | O79: Hanzcell (TOKOPEDIA) | P79: LUNAS | Q79: TRUE | S79: 0
A80: 79 | B80: 45847 | E80: 579563816346092835 | F80: Kabel Ties 2.5x100mm (50 gram) isi 100 pcs | G80: =H80+S80 -> 1 | H80: 1 | I80: 2850 | J80: =I80*G80 -> 2850 | K80: 0.5 | L80: =I80+((K80)*I80) -> 4275 | M80: 4500 | O80: Hanzcell (TOKOPEDIA) | P80: LUNAS | Q80: TRUE | S80: 0
A81: 80 | B81: 45847 | E81: 579563816346092835 | F81: Kabel Ties 3.6x150mm (70 gram) isi 100 pcs | G81: =H81+S81 -> 1 | H81: 1 | I81: 6500 | J81: =I81*G81 -> 6500 | K81: 0.5 | L81: =I81+((K81)*I81) -> 9750 | M81: 6000 | O81: Hanzcell (TOKOPEDIA) | P81: LUNAS | Q81: TRUE | S81: 0
A82: 81 | B82: 45847 | E82: 579563816346092835 | F82: Kabel Ties 4.8x200mm (85 gram) isi 100 pcs | G82: =H82+S82 -> 1 | H82: 1 | I82: 11000 | J82: =I82*G82 -> 11000 | K82: 0.5 | L82: =I82+((K82)*I82) -> 16500 | M82: 11000 | O82: Hanzcell (TOKOPEDIA) | P82: LUNAS | Q82: TRUE | S82: 0
A83: 82 | B83: 45847 | E83: 579563816346092835 | F83: Kabel Ties 3.6x250mm (70 gram) isi 100 pcs | G83: =H83+S83 -> 1 | H83: 1 | I83: 10300 | J83: =I83*G83 -> 10300 | K83: 0.5 | L83: =I83+((K83)*I83) -> 15450 | M83: 14000 | O83: Hanzcell (TOKOPEDIA) | P83: LUNAS | Q83: TRUE | S83: 0
... A93: 92 | B93: 45848 | E93: 250709PHE78DE0 | F93: Tali tampar/ Tali tukang | G93: =H93+S93 -> 20 | H93: 20 | I93: 1750 | J93: =I93*G93 -> 35000 | K93: 0.3 | L93: =I93+((K93)*I93) -> 2275 | M93: 5000 | O93: Yuanapurnomo (SHOPEE) | P93: LUNAS | Q93: TRUE | S93: 0
A94: 93 | B94: 45850 | E94: 25071207CHG44T | F94: Keranjang serbaguna | G94: =H94+S94 -> 24 | H94: 24 | I94: 4700 | J94: =I94*G94 -> 112800 | O94: Yani_Store123 (SHOPEE) | P94: LUNAS | Q94: TRUE | S94: 0
A95: 94 | B95: 45854 | E95: SI.2025.0716.00049 | F95: Paku (Nail 2000) 1 1/2" | G95: =H95+S95 -> 4 | H95: 4 | I95: 14400 | J95: =I95*G95 -> 57600 | K95: 0.3 | L95: =I95+((K95)*I95) -> 18720 | M95: 25000 | O95: Sumber Abadi (Graha SA) | P95: LUNAS | Q95: TRUE | R95: 45861 | S95: 0
A96: 95 | B96: 45854 | E96: SI.2025.0716.00049 | F96: Paku (Nail 2000) 2 1/2" | G96: =H96+S96 -> 20 | H96: 10 | I96: 13500 | J96: =I96*G96 -> 270000 | K96: 0.3 | L96: =I96+((K96)*I96) -> 17550 | M96: 24000 | O96: Sumber Abadi (Graha SA) | P96: LUNAS | Q96: TRUE | R96: 45861 | S96: 10
A97: 96 | B97: 45854 | E97: SI.2025.0716.00049 | F97: Paku (Nail 2000) 3" | G97: =H97+S97 -> 20 | H97: 10 | I97: 13500 | J97: =I97*G97 -> 270000 | K97: 0.3 | L97: =I97+((K97)*I97) -> 17550 | M97: 24000 | O97: Sumber Abadi (Graha SA) | P97: LUNAS | Q97: TRUE | R97: 45861 | S97: 10
A98: 97 | B98: 45861 | E98: SI.2025.0723.00037 | F98: Paku (Nail 2000) 1" | G98: =H98+S98 -> 4 | H98: 4 | I98: 15200 | J98: =I98*G98 -> 60800 | K98: 0.3 | L98: =I98+((K98)*I98) -> 19760 | M98: 25000 | O98: Sumber Abadi (Graha SA) | P98: LUNAS | Q98: TRUE | R98: 45875 | S98: 0
A99: 98 | B99: 45861 | E99: SI.2025.0723.00037 | F99: Paku (Nail 20000 1 3/4" | G99: =H99+S99 -> 4 | H99: 4 | I99: 14100 | J99: =I99*G99 -> 56400 | K99: 0.3 | L99: =I99+((K99)*I99) -> 18330 | M99: 25000 | O99: Sumber Abadi (Graha SA) | P99: LUNAS | Q99: TRUE | R99: 45875 | S99: 0
A100: 99 | B100: 45861 | E100: SI.2025.0723.00037 | F100: Paku (Nail 2000) 2" | G100: =H100+S100 -> 15 | H100: 5 | I100: 13500 | J100: =I100*G100 -> 202500 | K100: 0.3 | L100: =I100+((K100)*I100) -> 17550 | M100: 24000 | O100: Sumber Abadi (Graha SA) | P100: LUNAS | Q100: TRUE | R100: 45875 | S100: 10
A101: 100 | B101: 45861 | F101: Besi Beton 6mm SNI (U) | G101: =H101+S101 -> 10 | H101: 10 | I101: 22000 | J101: =I101*G101 -> 220000 | K101: 0.23 | L101: 26000 | M101: 27000 | O101: Sumber Abadi (Graha SA) | P101: LUNAS | Q101: TRUE | R101: 45869 | S101: 0
A102: 101 | B102: 45861 | F102: Besi Beton 8mm SNI (U) | G102: =H102+S102 -> 10 | H102: 10 | I102: 37000 | J102: =I102*G102 -> 370000 | K102: 0.23 | L102: 43000 | M102: 44000 | O102: Sumber Abadi (Graha SA) | P102: LUNAS | Q102: TRUE | R102: 45869 | S102: 0
A103: 102 | B103: 45861 | F103: Besi Beton 10mm SNI (U) | G103: =H103+S103 -> 5 | H103: 5 | I103: 58000 | J103: =I103*G103 -> 290000 | K103: 0.3 | L103: 73000 | M103: 74000 | O103: Sumber Abadi (Graha SA) | P103: LUNAS | Q103: TRUE | R103: 45869 | S103: 0
A104: 103 | B104: 45861 | F104: Hollow G Tube 20x40x0.4 | G104: =H104+S104 -> 20 | H104: 20 | I104: 21500 | J104: =I104*G104 -> 430000 | K104: 0.2 | L104: =I104+((K104)*I104) -> 25800 | M104: 30000 | O104: Sumber Abadi (Graha SA) | P104: LUNAS | Q104: TRUE | R104: 45869 | S104: 0
A105: 104 | B105: 45861 | F105: Hollow G Tube 40x40x0.4 | G105: =H105+S105 -> 10 | H105: 10 | I105: 28500 | J105: =I105*G105 -> 285000 | K105: 0.2 | L105: =I105+((K105)*I105) -> 34200 | M105: 28500 | O105: Sumber Abadi (Graha SA) | P105: LUNAS | Q105: TRUE | R105: 45869 | S105: 0
A106: 105 | B106: 45861 | F106: Reng Galvalum Kenana 0.45 (M) | G106: =H106+S106 -> 10 | H106: 10 | I106: 39000 | J106: =I106*G106 -> 390000 | K106: 0.1 | L106: =I106+((K106)*I106) -> 42900 | M106: 51500 | O106: Sumber Abadi (Graha SA) | P106: LUNAS | Q106: TRUE | R106: 45869 | S106: 0
A107: 106 | B107: 45861 | F107: C Truss Kencana 75x0.85 (0.75) MM | G107: =H107+S107 -> 10 | H107: 10 | I107: 85000 | J107: =I107*G107 -> 850000 | K107: 0.1 | L107: =I107+((K107)*I107) -> 93500 | M107: 110500 | O107: Sumber Abadi (Graha SA) | P107: LUNAS | Q107: TRUE | R107: 45869 | S107: 0
A108: 107 | B108: 45861 | F108: KAYU BALOK 4X6X4 | G108: =H108+S108 -> 12 | H108: 12 | I108: 39000 | J108: =I108*G108 -> 468000 | K108: 0.1 | L108: =I108+((K108)*I108) -> 42900 | Q108: FALSE | S108: 0
A109: 108 | B109: 45861 | F109: KAYU BALOK 3X5X4 | G109: =H109+S109 -> 10 | H109: 10 | I109: 24000 | J109: =I109*G109 -> 240000 | K109: 0.1 | L109: =I109+((K109)*I109) -> 26400 | Q109: FALSE | S109: 0
...

Sheet JULI 25
A1: LAPORAN PENJUALAN BULANAN | AQ1: 45839
A2: NAMA BARANG | B2: STOK AWAL | C2: =UPPER("HARI / BULAN : " & TEXT(AQ1, "MMMM YYYY")) -> HARI / BULAN : JULI 2025
C3: =TEXT(C4,"dddd") -> Selasa | D3: =TEXT(D4,"dddd") -> Rabu | E3: =TEXT(E4,"dddd") -> Kamis | F3: =TEXT(F4,"dddd") -> Jumat | G3: =TEXT(G4,"dddd") -> Sabtu | H3: =TEXT(H4,"dddd") -> Minggu | I3: =TEXT(I4,"dddd") -> Senin | J3: =TEXT(J4,"dddd") -> Selasa | ... AG3: =TEXT(AG4,"dddd") -> Kamis | AH3: TOTAL | AI3: STOCK | AJ3: SYSTEM | AK3: KET/SELISIH | AL3: HARGA BELI | AM3: HARGA JUAL | AN3: OMSET | AO3: PROFIT | AP3: TOTAL MODAL
C4: =AQ1 -> 45839 | D4: =IF(AND(MONTH(C4+1) = MONTH(C4), C4<>""),C4 + 1, "") -> 45840 | E4: =IF(AND(MONTH(D4+1) = MONTH(D4), D4<>""),D4 + 1, "") -> 45841 | F4: =IF(AND(MONTH(E4+1) = MONTH(E4), E4<>""),E4 + 1, "") -> 45842 | G4: =IF(AND(MONTH(F4+1) = MONTH(F4), F4<>""),F4 + 1, "") -> 45843 | H4: =IF(AND(MONTH(G4+1) = MONTH(G4), G4<>""),G4 + 1, "") -> 45844 | I4: =IF(AND(MONTH(H4+1) = MONTH(H4), H4<>""),H4 + 1, "") -> 45845 | J4: =IF(AND(MONTH(I4+1) = MONTH(I4), I4<>""),I4 + 1, "") -> 45846 | K4: =IF(AND(MONTH(J4+1) = MONTH(J4), J4<>""),J4 + 1, "") -> 45847 | ... AG4: =IF(AND(MONTH(AF4+1) = MONTH(AF4), AF4<>""),AF4 + 1, "") -> 45869
A5: ='MASTER STOCK'!F2 -> Fitting Gantung | B5: ='MASTER STOCK'!G2 -> 12 | AH5: =SUM(C5:AG5) -> 0 | AI5: =B5-SUM(C5:AG5) -> 12 | AJ5: =B5-AH5 -> 12 | AK5: =AJ5-AI5 -> 0 | AL5: ='MASTER STOCK'!I2 -> 1400 | AM5: ='MASTER STOCK'!L2 -> 1820 | AN5: =AH5*AM5 -> 0 | AO5: =AN5-(AH5*AL5) -> 0 | AP5: =AH5*AL5 -> 0
A6: ='MASTER STOCK'!F3 -> Colokan T | B6: ='MASTER STOCK'!G3 -> 12 | AH6: =SUM(C6:AG6) -> 0 | AI6: =B6-SUM(C6:AG6) -> 12 | AJ6: =B6-AH6 -> 12 | AK6: =AJ6-AI6 -> 0 | AL6: ='MASTER STOCK'!I3 -> 3000 | AM6: ='MASTER STOCK'!L3 -> 3900 | AN6: =AH6*AM6 -> 0 | AO6: =AN6-(AH6*AL6) -> 0 | AP6: =AH6*AL6 -> 0
A7: ='MASTER STOCK'!F4 -> Steker Bulat | B7: ='MASTER STOCK'!G4 -> 12 | AH7: =SUM(C7:AG7) -> 0 | AI7: =B7-SUM(C7:AG7) -> 12 | AJ7: =B7-AH7 -> 12 | AK7: =AJ7-AI7 -> 0 | AL7: ='MASTER STOCK'!I4 -> 3000 | AM7: ='MASTER STOCK'!L4 -> 6000 | AN7: =AH7*AM7 -> 0 | AO7: =AN7-(AH7*AL7) -> 0 | AP7: =AH7*AL7 -> 0
A8: ='MASTER STOCK'!F5 -> Steker Gepeng | B8: ='MASTER STOCK'!G5 -> 12 | AH8: =SUM(C8:AG8) -> 0 | AI8: =B8-SUM(C8:AG8) -> 12 | AJ8: =B8-AH8 -> 12 | AK8: =AJ8-AI8 -> 0 | AL8: ='MASTER STOCK'!I5 -> 1100 | AM8: ='MASTER STOCK'!L5 -> 1430 | AN8: =AH8*AM8 -> 0 | AO8: =AN8-(AH8*AL8) -> 0 | AP8: =AH8*AL8 -> 0
A9: ='MASTER STOCK'!F6 -> Saklar Gantung Putih jumbo | B9: ='MASTER STOCK'!G6 -> 12 | AH9: =SUM(C9:AG9) -> 0 | AI9: =B9-SUM(C9:AG9) -> 12 | AJ9: =B9-AH9 -> 12 | AK9: =AJ9-AI9 -> 0 | AL9: ='MASTER STOCK'!I6 -> 2250 | AM9: ='MASTER STOCK'!L6 -> 4000 | AN9: =AH9*AM9 -> 0 | AO9: =AN9-(AH9*AL9) -> 0 | AP9: =AH9*AL9 -> 0
A10: ='MASTER STOCK'!F7 -> Saklar Gantung Hitam | B10: ='MASTER STOCK'!G7 -> 12 | AH10: =SUM(C10:AG10) -> 0 | AI10: =B10-SUM(C10:AG10) -> 12 | AJ10: =B10-AH10 -> 12 | AK10: =AJ10-AI10 -> 0 | AL10: ='MASTER STOCK'!I7 -> 1850 | AM10: ='MASTER STOCK'!L7 -> 4000 | AN10: =AH10*AM10 -> 0 | AO10: =AN10-(AH10*AL10) -> 0 | AP10: =AH10*AL10 -> 0
A11: ='MASTER STOCK'!F8 -> Isolasi Hitam National | B11: ='MASTER STOCK'!G8 -> 20 | AH11: =SUM(C11:AG11) -> 0 | AI11: =B11-SUM(C11:AG11) -> 20 | AJ11: =B11-AH11 -> 20 | AK11: =AJ11-AI11 -> 0 | AL11: ='MASTER STOCK'!I8 -> 5150 | AM11: ='MASTER STOCK'!L8 -> 7982.5 | AN11: =AH11*AM11 -> 0 | AO11: =AN11-(AH11*AL11) -> 0 | AP11: =AH11*AL11 -> 0
A12: ='MASTER STOCK'!F9 -> Lem PVC Isarplas 40gram | B12: ='MASTER STOCK'!G9 -> 24 | AH12: =SUM(C12:AG12) -> 0 | AI12: =B12-SUM(C12:AG12) -> 24 | AJ12: =B12-AH12 -> 24 | AK12: =AJ12-AI12 -> 0 | AL12: ='MASTER STOCK'!I9 -> 6900 | AM12: ='MASTER STOCK'!L9 -> 9500 | AN12: =AH12*AM12 -> 0 | AO12: =AN12-(AH12*AL12) -> 0 | AP12: =AH12*AL12 -> 0
A13: ='MASTER STOCK'!F10 -> Isolasi Kran air onda | B13: ='MASTER STOCK'!G10 -> 60 | AH13: =SUM(C13:AG13) -> 0 | AI13: =B13-SUM(C13:AG13) -> 60 | AJ13: =B13-AH13 -> 60 | AK13: =AJ13-AI13 -> 0 | AL13: ='MASTER STOCK'!I10 -> 1150 | AM13: ='MASTER STOCK'!L10 -> 1495 | AN13: =AH13*AM13 -> 0 | AO13: =AN13-(AH13*AL13) -> 0 | AP13: =AH13*AL13 -> 0
A14: ='MASTER STOCK'!F11 -> Tutup Pipa 3/4" | B14: ='MASTER STOCK'!G11 -> 50 | AH14: =SUM(C14:AG14) -> 0 | AI14: =B14-SUM(C14:AG14) -> 50 | AJ14: =B14-AH14 -> 50 | AK14: =AJ14-AI14 -> 0 | AL14: ='MASTER STOCK'!I11 -> 850 | AM14: ='MASTER STOCK'!L11 -> 1275 | AN14: =AH14*AM14 -> 0 | AO14: =AN14-(AH14*AL14) -> 0 | AP14: =AH14*AL14 -> 0
A15: ='MASTER STOCK'!F12 -> Fitting lampu gantung outdoor (10 m 5 fitting) | B15: ='MASTER STOCK'!G12 -> 1 | AH15: =SUM(C15:AG15) -> 0 | AI15: =B15-SUM(C15:AG15) -> 1 | AJ15: =B15-AH15 -> 1 | AK15: =AJ15-AI15 -> 0 | AL15: ='MASTER STOCK'!I12 -> 38000 | AM15: ='MASTER STOCK'!L12 -> 49400 | AN15: =AH15*AM15 -> 0 | AO15: =AN15-(AH15*AL15) -> 0 | AP15: =AH15*AL15 -> 0
A16: ='MASTER STOCK'!F13 -> Obeng karet 4" plus | B16: ='MASTER STOCK'!G13 -> 5 | AH16: =SUM(C16:AG16) -> 0 | AI16: =B16-SUM(C16:AG16) -> 5 | AJ16: =B16-AH16 -> 5 | AK16: =AJ16-AI16 -> 0 | AL16: ='MASTER STOCK'!I13 -> 5500 | AM16: ='MASTER STOCK'!L13 -> 7150 | AN16: =AH16*AM16 -> 0 | AO16: =AN16-(AH16*AL16) -> 0 | AP16: =AH16*AL16 -> 0
A17: ='MASTER STOCK'!F14 -> Obeng karet 4" minus | B17: ='MASTER STOCK'!G14 -> 5 | S17: 1 | AH17: =SUM(C17:AG17) -> 1 | AI17: =B17-SUM(C17:AG17) -> 4 | AJ17: =B17-AH17 -> 4 | AK17: =AJ17-AI17 -> 0 | AL17: ='MASTER STOCK'!I14 -> 5500 | AM17: ='MASTER STOCK'!L14 -> 7150 | AN17: =AH17*AM17 -> 7150 | AO17: =AN17-(AH17*AL17) -> 1650 | AP17: =AH17*AL17 -> 5500
A18: ='MASTER STOCK'!F15 -> Obeng karet 6" plus | B18: ='MASTER STOCK'!G15 -> 5 | AH18: =SUM(C18:AG18) -> 0 | AI18: =B18-SUM(C18:AG18) -> 5 | AJ18: =B18-AH18 -> 5 | AK18: =AJ18-AI18 -> 0 | AL18: ='MASTER STOCK'!I15 -> 7000 | AM18: ='MASTER STOCK'!L15 -> 9100 | AN18: =AH18*AM18 -> 0 | AO18: =AN18-(AH18*AL18) -> 0 | AP18: =AH18*AL18 -> 0
A19: ='MASTER STOCK'!F16 -> Obeng karet 6" Minus | B19: ='MASTER STOCK'!G16 -> 5 | AH19: =SUM(C19:AG19) -> 0 | AI19: =B19-SUM(C19:AG19) -> 5 | AJ19: =B19-AH19 -> 5 | AK19: =AJ19-AI19 -> 0 | AL19: ='MASTER STOCK'!I16 -> 7000 | AM19: ='MASTER STOCK'!L16 -> 9100 | AN19: =AH19*AM19 -> 0 | AO19: =AN19-(AH19*AL19) -> 0 | AP19: =AH19*AL19 -> 0
A20: ='MASTER STOCK'!F17 -> Kabel Awg 24 Double 2x18 merah hitam | B20: ='MASTER STOCK'!G17 -> 2 | AH20: =SUM(C20:AG20) -> 0 | AI20: =B20-SUM(C20:AG20) -> 2 | AJ20: =B20-AH20 -> 2 | AK20: =AJ20-AI20 -> 0 | AL20: ='MASTER STOCK'!I17 -> 106500 | AM20: ='MASTER STOCK'!L17 -> 181050 | AN20: =AH20*AM20 -> 0 | AO20: =AN20-(AH20*AL20) -> 0 | AP20: =AH20*AL20 -> 0
A21: ='MASTER STOCK'!F18 -> Kabel bintik serabut tembaga motor mobil 20mx0.5mm/0,85mm merah 0,5mm | B21: ='MASTER STOCK'!G18 -> 2 | AH21: =SUM(C21:AG21) -> 0 | AI21: =B21-SUM(C21:AG21) -> 2 | AJ21: =B21-AH21 -> 2 | AK21: =AJ21-AI21 -> 0 | AL21: ='MASTER STOCK'!I18 -> 33700 | AM21: ='MASTER STOCK'!L18 -> 57290 | AN21: =AH21*AM21 -> 0 | AO21: =AN21-(AH21*AL21) -> 0 | AP21: =AH21*AL21 -> 0
A22: ='MASTER STOCK'!F19 -> Kabel bintik serabut tembaga motor mobil 20mx0.5mm/0,85mm hitam 0,5mm | B22: ='MASTER STOCK'!G19 -> 2 | AH22: =SUM(C22:AG22) -> 0 | AI22: =B22-SUM(C22:AG22) -> 2 | AJ22: =B22-AH22 -> 2 | AK22: =AJ22-AI22 -> 0 | AL22: ='MASTER STOCK'!I19 -> 33700 | AM22: ='MASTER STOCK'!L19 -> 57290 | AN22: =AH22*AM22 -> 0 | AO22: =AN22-(AH22*AL22) -> 0 | AP22: =AH22*AL22 -> 0
A23: ='MASTER STOCK'!F20 -> Mata Gerinda keramik 4 inch kering | B23: ='MASTER STOCK'!G20 -> 5 | AH23: =SUM(C23:AG23) -> 0 | AI23: =B23-SUM(C23:AG23) -> 5 | AJ23: =B23-AH23 -> 5 | AK23: =AJ23-AI23 -> 0 | AL23: ='MASTER STOCK'!I20 -> 12000 | AM23: ='MASTER STOCK'!L20 -> 18000 | AN23: =AH23*AM23 -> 0 | AO23: =AN23-(AH23*AL23) -> 0 | AP23: =AH23*AL23 -> 0
A24: ='MASTER STOCK'!F21 -> Kabel tunggal serabut 0.8mmx25m biru 25m | B24: ='MASTER STOCK'!G21 -> 1 | AH24: =SUM(C24:AG24) -> 0 | AI24: =B24-SUM(C24:AG24) -> 1 | AJ24: =B24-AH24 -> 1 | AK24: =AJ24-AI24 -> 0 | AL24: ='MASTER STOCK'!I21 -> 17500 | AM24: ='MASTER STOCK'!L21 -> 29750 | AN24: =AH24*AM24 -> 0 | AO24: =AN24-(AH24*AL24) -> 0 | AP24: =AH24*AL24 -> 0
A25: ='MASTER STOCK'!F22 -> Kabel tunggal serabut 0.8mmx25m Hitam 25m | B25: ='MASTER STOCK'!G22 -> 1 | AH25: =SUM(C25:AG25) -> 0 | AI25: =B25-SUM(C25:AG25) -> 1 | AJ25: =B25-AH25 -> 1 | AK25: =AJ25-AI25 -> 0 | AL25: ='MASTER STOCK'!I22 -> 17500 | AM25: ='MASTER STOCK'!L22 -> 29750 | AN25: =AH25*AM25 -> 0 | AO25: =AN25-(AH25*AL25) -> 0 | AP25: =AH25*AL25 -> 0
A26: ='MASTER STOCK'!F23 -> Lampu Hias LED strip USB 10m+adaptor | B26: ='MASTER STOCK'!G23 -> 2 | AH26: =SUM(C26:AG26) -> 0 | AI26: =B26-SUM(C26:AG26) -> 2 | AJ26: =B26-AH26 -> 2 | AK26: =AJ26-AI26 -> 0 | AL26: ='MASTER STOCK'!I23 -> 50000 | AM26: ='MASTER STOCK'!L23 -> 65000 | AN26: =AH26*AM26 -> 0 | AO26: =AN26-(AH26*AL26) -> 0 | AP26: =AH26*AL26 -> 0
A27: ='MASTER STOCK'!F24 -> Lampu LED strip outdoor rainbow 10m +adaptor | B27: ='MASTER STOCK'!G24 -> 5 | AH27: =SUM(C27:AG27) -> 0 | AI27: =B27-SUM(C27:AG27) -> 5 | AJ27: =B27-AH27 -> 5 | AK27: =AJ27-AI27 -> 0 | AL27: ='MASTER STOCK'!I24 -> 27000 | AM27: ='MASTER STOCK'!L24 -> 35100 | AN27: =AH27*AM27 -> 0 | AO27: =AN27-(AH27*AL27) -> 0 | AP27: =AH27*AL27 -> 0
A28: ='MASTER STOCK'!F25 -> Lampu LED strip outdoor merah putih 10m +adaptor | B28: ='MASTER STOCK'!G25 -> 5 | AH28: =SUM(C28:AG28) -> 0 | AI28: =B28-SUM(C28:AG28) -> 5 | AJ28: =B28-AH28 -> 5 | AK28: =AJ28-AI28 -> 0 | AL28: ='MASTER STOCK'!I25 -> 30000 | AM28: ='MASTER STOCK'!L25 -> 40500 | AN28: =AH28*AM28 -> 0 | AO28: =AN28-(AH28*AL28) -> 0 | AP28: =AH28*AL28 -> 0
A29: ='MASTER STOCK'!F26 -> Lampu tumbler 10m (rainbow) | B29: ='MASTER STOCK'!G26 -> 5 | AH29: =SUM(C29:AG29) -> 0 | AI29: =B29-SUM(C29:AG29) -> 5 | AJ29: =B29-AH29 -> 5 | AK29: =AJ29-AI29 -> 0 | AL29: ='MASTER STOCK'!I26 -> 11000 | AM29: ='MASTER STOCK'!L26 -> 14300 | AN29: =AH29*AM29 -> 0 | AO29: =AN29-(AH29*AL29) -> 0 | AP29: =AH29*AL29 -> 0
A30: ='MASTER STOCK'!F27 -> WD Gerinda potong besi | B30: ='MASTER STOCK'!G27 -> 60 | Z30: 1 | AA30: 1 | AH30: =SUM(C30:AG30) -> 2 | AI30: =B30-SUM(C30:AG30) -> 58 | AJ30: =B30-AH30 -> 58 | AK30: =AJ30-AI30 -> 0 | AL30: ='MASTER STOCK'!I27 -> 2900 | AM30: ='MASTER STOCK'!L27 -> 5000 | AN30: =AH30*AM30 -> 10000 | AO30: =AN30-(AH30*AL30) -> 4200 | AP30: =AH30*AL30 -> 5800
A31: ='MASTER STOCK'!F28 -> Meteran karet 7,5m (merk HPP) | B31: ='MASTER STOCK'!G28 -> 3 | AH31: =SUM(C31:AG31) -> 0 | AI31: =B31-SUM(C31:AG31) -> 3 | AJ31: =B31-AH31 -> 3 | AK31: =AJ31-AI31 -> 0 | AL31: ='MASTER STOCK'!I28 -> 12800 | AM31: ='MASTER STOCK'!L28 -> 16640 | AN31: =AH31*AM31 -> 0 | AO31: =AN31-(AH31*AL31) -> 0 | AP31: =AH31*AL31 -> 0
A32: ='MASTER STOCK'!F29 -> Meteran karet 5m (merk VPR) | B32: ='MASTER STOCK'!G29 -> 3 | AH32: =SUM(C32:AG32) -> 0 | AI32: =B32-SUM(C32:AG32) -> 3 | AJ32: =B32-AH32 -> 3 | AK32: =AJ32-AI32 -> 0 | AL32: ='MASTER STOCK'!I29 -> 7000 | AM32: ='MASTER STOCK'!L29 -> 9100 | AN32: =AH32*AM32 -> 0 | AO32: =AN32-(AH32*AL32) -> 0 | AP32: =AH32*AL32 -> 0
A33: ='MASTER STOCK'!F30 -> Kuas cat 2 1/2" (merk MDN) | B33: ='MASTER STOCK'!G30 -> 5 | AH33: =SUM(C33:AG33) -> 0 | AI33: =B33-SUM(C33:AG33) -> 5 | AJ33: =B33-AH33 -> 5 | AK33: =AJ33-AI33 -> 0 | AL33: ='MASTER STOCK'!I30 -> 5300 | AM33: ='MASTER STOCK'!L30 -> 6890 | AN33: =AH33*AM33 -> 0 | AO33: =AN33-(AH33*AL33) -> 0 | AP33: =AH33*AL33 -> 0
A34: ='MASTER STOCK'!F31 -> Kuas cat 2" (merk MDN) | B34: ='MASTER STOCK'!G31 -> 5 | AH34: =SUM(C34:AG34) -> 0 | AI34: =B34-SUM(C34:AG34) -> 5 | AJ34: =B34-AH34 -> 5 | AK34: =AJ34-AI34 -> 0 | AL34: ='MASTER STOCK'!I31 -> 4400 | AM34: ='MASTER STOCK'!L31 -> 5720 | AN34: =AH34*AM34 -> 0 | AO34: =AN34-(AH34*AL34) -> 0 | AP34: =AH34*AL34 -> 0
A35: ='MASTER STOCK'!F32 -> Kuas cat 3" (merk MDN) | B35: ='MASTER STOCK'!G32 -> 5 | AH35: =SUM(C35:AG35) -> 0 | AI35: =B35-SUM(C35:AG35) -> 5 | AJ35: =B35-AH35 -> 5 | AK35: =AJ35-AI35 -> 0 | AL35: ='MASTER STOCK'!I32 -> 6300 | AM35: ='MASTER STOCK'!L32 -> 8190 | AN35: =AH35*AM35 -> 0 | AO35: =AN35-(AH35*AL35) -> 0 | AP35: =AH35*AL35 -> 0
A36: ='MASTER STOCK'!F33 -> Kuas cat 1 1/2" (merk MDN) | B36: ='MASTER STOCK'!G33 -> 5 | AH36: =SUM(C36:AG36) -> 0 | AI36: =B36-SUM(C36:AG36) -> 5 | AJ36: =B36-AH36 -> 5 | AK36: =AJ36-AI36 -> 0 | AL36: ='MASTER STOCK'!I33 -> 3400 | AM36: ='MASTER STOCK'!L33 -> 4420 | AN36: =AH36*AM36 -> 0 | AO36: =AN36-(AH36*AL36) -> 0 | AP36: =AH36*AL36 -> 0
A37: ='MASTER STOCK'!F34 -> Kuas cat 1" (merk MDN) | B37: ='MASTER STOCK'!G34 -> 5 | AH37: =SUM(C37:AG37) -> 0 | AI37: =B37-SUM(C37:AG37) -> 5 | AJ37: =B37-AH37 -> 5 | AK37: =AJ37-AI37 -> 0 | AL37: ='MASTER STOCK'!I34 -> 2300 | AM37: ='MASTER STOCK'!L34 -> 2990 | AN37: =AH37*AM37 -> 0 | AO37: =AN37-(AH37*AL37) -> 0 | AP37: =AH37*AL37 -> 0
A38: ='MASTER STOCK'!F35 -> Kran PVC Tembok 3/4" | B38: ='MASTER STOCK'!G35 -> 24 | AH38: =SUM(C38:AG38) -> 0 | AI38: =B38-SUM(C38:AG38) -> 24 | AJ38: =B38-AH38 -> 24 | AK38: =AJ38-AI38 -> 0 | AL38: ='MASTER STOCK'!I35 -> 4200 | AM38: ='MASTER STOCK'!L35 -> 6000 | AN38: =AH38*AM38 -> 0 | AO38: =AN38-(AH38*AL38) -> 0 | AP38: =AH38*AL38 -> 0
A39: ='MASTER STOCK'!F36 -> Kran PVC Tembok 1/2" | B39: ='MASTER STOCK'!G36 -> 24 | AH39: =SUM(C39:AG39) -> 0 | AI39: =B39-SUM(C39:AG39) -> 24 | AJ39: =B39-AH39 -> 24 | AK39: =AJ39-AI39 -> 0 | AL39: ='MASTER STOCK'!I36 -> 4200 | AM39: ='MASTER STOCK'!L36 -> 6000 | AN39: =AH39*AM39 -> 0 | AO39: =AN39-(AH39*AL39) -> 0 | AP39: =AH39*AL39 -> 0
A40: ='MASTER STOCK'!F37 -> Lampu bohlam inlite 5w Putih | B40: ='MASTER STOCK'!G37 -> 7 | AH40: =SUM(C40:AG40) -> 0 | AI40: =B40-SUM(C40:AG40) -> 7 | AJ40: =B40-AH40 -> 7 | AK40: =AJ40-AI40 -> 0 | AL40: ='MASTER STOCK'!I37 -> 13000 | AM40: ='MASTER STOCK'!L37 -> 18200 | AN40: =AH40*AM40 -> 0 | AO40: =AN40-(AH40*AL40) -> 0 | AP40: =AH40*AL40 -> 0
A41: ='MASTER STOCK'!F38 -> Lampu bohlam inlite 7w Putih | B41: ='MASTER STOCK'!G38 -> 2 | AH41: =SUM(C41:AG41) -> 0 | AI41: =B41-SUM(C41:AG41) -> 2 | AJ41: =B41-AH41 -> 2 | AK41: =AJ41-AI41 -> 0 | AL41: ='MASTER STOCK'!I38 -> 16200 | AM41: ='MASTER STOCK'!L38 -> 22680 | AN41: =AH41*AM41 -> 0 | AO41: =AN41-(AH41*AL41) -> 0 | AP41: =AH41*AL41 -> 0
A42: ='MASTER STOCK'!F39 -> Lampu bohlam inlite 15w Putih | B42: ='MASTER STOCK'!G39 -> 4 | AH42: =SUM(C42:AG42) -> 0 | AI42: =B42-SUM(C42:AG42) -> 4 | AJ42: =B42-AH42 -> 4 | AK42: =AJ42-AI42 -> 0 | AL42: ='MASTER STOCK'!I39 -> 28000 | AM42: ='MASTER STOCK'!L39 -> 39200 | AN42: =AH42*AM42 -> 0 | AO42: =AN42-(AH42*AL42) -> 0 | AP42: =AH42*AL42 -> 0
A43: ='MASTER STOCK'!F40 -> Lampu bohlam inlite 12w Putih | B43: ='MASTER STOCK'!G40 -> 6 | AH43: =SUM(C43:AG43) -> 0 | AI43: =B43-SUM(C43:AG43) -> 6 | AJ43: =B43-AH43 -> 6 | AK43: =AJ43-AI43 -> 0 | AL43: ='MASTER STOCK'!I40 -> 25000 | AM43: ='MASTER STOCK'!L40 -> 30000 | AN43: =AH43*AM43 -> 0 | AO43: =AN43-(AH43*AL43) -> 0 | AP43: =AH43*AL43 -> 0
A44: ='MASTER STOCK'!F41 -> Lampu tintin platinum LED 9w | B44: ='MASTER STOCK'!G41 -> 5 | R44: 1 | AH44: =SUM(C44:AG44) -> 1 | AI44: =B44-SUM(C44:AG44) -> 4 | AJ44: =B44-AH44 -> 4 | AK44: =AJ44-AI44 -> 0 | AL44: ='MASTER STOCK'!I41 -> 7000 | AM44: ='MASTER STOCK'!L41 -> 9800 | AN44: =AH44*AM44 -> 9800 | AO44: =AN44-(AH44*AL44) -> 2800 | AP44: =AH44*AL44 -> 7000
A45: ='MASTER STOCK'!F42 -> Lampu tintin platinum LED 5w | B45: ='MASTER STOCK'!G42 -> 5 | R45: 1 | AH45: =SUM(C45:AG45) -> 1 | AI45: =B45-SUM(C45:AG45) -> 4 | AJ45: =B45-AH45 -> 4 | AK45: =AJ45-AI45 -> 0 | AL45: ='MASTER STOCK'!I42 -> 5000 | AM45: ='MASTER STOCK'!L42 -> 7000 | AN45: =AH45*AM45 -> 7000 | AO45: =AN45-(AH45*AL45) -> 2000 | AP45: =AH45*AL45 -> 5000
A46: ='MASTER STOCK'!F43 -> Lampu tintin platinum LED 21w | B46: ='MASTER STOCK'!G43 -> 3 | AH46: =SUM(C46:AG46) -> 0 | AI46: =B46-SUM(C46:AG46) -> 3 | AJ46: =B46-AH46 -> 3 | AK46: =AJ46-AI46 -> 0 | AL46: ='MASTER STOCK'!I43 -> 15500 | AM46: ='MASTER STOCK'!L43 -> 21700 | AN46: =AH46*AM46 -> 0 | AO46: =AN46-(AH46*AL46) -> 0 | AP46: =AH46*AL46 -> 0
A47: ='MASTER STOCK'!F44 -> Lampu tintin platinum LED 15w | B47: ='MASTER STOCK'!G44 -> 5 | AH47: =SUM(C47:AG47) -> 0 | AI47: =B47-SUM(C47:AG47) -> 5 | AJ47: =B47-AH47 -> 5 | AK47: =AJ47-AI47 -> 0 | AL47: ='MASTER STOCK'!I44 -> 8800 | AM47: ='MASTER STOCK'!L44 -> 13000 | AN47: =AH47*AM47 -> 0 | AO47: =AN47-(AH47*AL47) -> 0 | AP47: =AH47*AL47 -> 0
A48: ='MASTER STOCK'!F45 -> Lampu tintin platinum LED 12w | B48: ='MASTER STOCK'!G45 -> 5 | AH48: =SUM(C48:AG48) -> 0 | AI48: =B48-SUM(C48:AG48) -> 5 | AJ48: =B48-AH48 -> 5 | AK48: =AJ48-AI48 -> 0 | AL48: ='MASTER STOCK'!I45 -> 7800 | AM48: ='MASTER STOCK'!L45 -> 10920 | AN48: =AH48*AM48 -> 0 | AO48: =AN48-(AH48*AL48) -> 0 | AP48: =AH48*AL48 -> 0
A49: ='MASTER STOCK'!F46 -> Lampu tintin platinum LED 7w | B49: ='MASTER STOCK'!G46 -> 5 | AH49: =SUM(C49:AG49) -> 0 | AI49: =B49-SUM(C49:AG49) -> 5 | AJ49: =B49-AH49 -> 5 | AK49: =AJ49-AI49 -> 0 | AL49: ='MASTER STOCK'!I46 -> 5800 | AM49: ='MASTER STOCK'!L46 -> 8120 | AN49: =AH49*AM49 -> 0 | AO49: =AN49-(AH49*AL49) -> 0 | AP49: =AH49*AL49 -> 0
A50: ='MASTER STOCK'!F47 -> Gergaji kayu (POPEYE) 18 inch | B50: ='MASTER STOCK'!G47 -> 4 | AH50: =SUM(C50:AG50) -> 0 | AI50: =B50-SUM(C50:AG50) -> 4 | AJ50: =B50-AH50 -> 4 | AK50: =AJ50-AI50 -> 0 | AL50: ='MASTER STOCK'!I47 -> 15000 | AM50: ='MASTER STOCK'!L47 -> 19500 | AN50: =AH50*AM50 -> 0 | AO50: =AN50-(AH50*AL50) -> 0 | AP50: =AH50*AL50 -> 0
A51: ='MASTER STOCK'!F48 -> Kapi plamir plastik PVC 9" (23cm) | B51: ='MASTER STOCK'!G48 -> 10 | AH51: =SUM(C51:AG51) -> 0 | AI51: =B51-SUM(C51:AG51) -> 10 | AJ51: =B51-AH51 -> 10 | AK51: =AJ51-AI51 -> 0 | AL51: ='MASTER STOCK'!I48 -> 2200 | AM51: ='MASTER STOCK'!L48 -> 3300 | AN51: =AH51*AM51 -> 0 | AO51: =AN51-(AH51*AL51) -> 0 | AP51: =AH51*AL51 -> 0
A52: ='MASTER STOCK'!F49 -> Kapi plamir plastik PVC 5" (12cm) | B52: ='MASTER STOCK'!G49 -> 5 | AH52: =SUM(C52:AG52) -> 0 | AI52: =B52-SUM(C52:AG52) -> 5 | AJ52: =B52-AH52 -> 5 | AK52: =AJ52-AI52 -> 0 | AL52: ='MASTER STOCK'!I49 -> 1100 | AM52: ='MASTER STOCK'!L49 -> 1650 | AN52: =AH52*AM52 -> 0 | AO52: =AN52-(AH52*AL52) -> 0 | AP52: =AH52*AL52 -> 0
A53: ='MASTER STOCK'!F50 -> Kapi plamir plastik PVC 7" (18cm) | B53: ='MASTER STOCK'!G50 -> 10 | AH53: =SUM(C53:AG53) -> 0 | AI53: =B53-SUM(C53:AG53) -> 10 | AJ53: =B53-AH53 -> 10 | AK53: =AJ53-AI53 -> 0 | AL53: ='MASTER STOCK'!I50 -> 1500 | AM53: ='MASTER STOCK'!L50 -> 2250 | AN53: =AH53*AM53 -> 0 | AO53: =AN53-(AH53*AL53) -> 0 | AP53: =AH53*AL53 -> 0
A54: ='MASTER STOCK'!F51 -> Tang Kombinasi karet 8" | B54: ='MASTER STOCK'!G51 -> 5 | AH54: =SUM(C54:AG54) -> 0 | AI54: =B54-SUM(C54:AG54) -> 5 | AJ54: =B54-AH54 -> 5 | AK54: =AJ54-AI54 -> 0 | AL54: ='MASTER STOCK'!I51 -> 12000 | AM54: ='MASTER STOCK'!L51 -> 15600 | AN54: =AH54*AM54 -> 0 | AO54: =AN54-(AH54*AL54) -> 0 | AP54: =AH54*AL54 -> 0
A55: ='MASTER STOCK'!F52 -> Tang Kombinasi 8" | B55: ='MASTER STOCK'!G52 -> 5 | AH55: =SUM(C55:AG55) -> 0 | AI55: =B55-SUM(C55:AG55) -> 5 | AJ55: =B55-AH55 -> 5 | AK55: =AJ55-AI55 -> 0 | AL55: ='MASTER STOCK'!I52 -> 12500 | AM55: ='MASTER STOCK'!L52 -> 16250 | AN55: =AH55*AM55 -> 0 | AO55: =AN55-(AH55*AL55) -> 0 | AP55: =AH55*AL55 -> 0
A56: ='MASTER STOCK'!F53 -> Stop Kontak Hitam 3L 5M | B56: ='MASTER STOCK'!G53 -> 2 | AH56: =SUM(C56:AG56) -> 0 | AI56: =B56-SUM(C56:AG56) -> 2 | AJ56: =B56-AH56 -> 2 | AK56: =AJ56-AI56 -> 0 | AL56: ='MASTER STOCK'!I53 -> 18400 | AM56: ='MASTER STOCK'!L53 -> 27600 | AN56: =AH56*AM56 -> 0 | AO56: =AN56-(AH56*AL56) -> 0 | AP56: =AH56*AL56 -> 0
A57: ='MASTER STOCK'!F54 -> Stop Kontak Hitam 4L 5M | B57: ='MASTER STOCK'!G54 -> 3 | AH57: =SUM(C57:AG57) -> 0 | AI57: =B57-SUM(C57:AG57) -> 3 | AJ57: =B57-AH57 -> 3 | AK57: =AJ57-AI57 -> 0 | AL57: ='MASTER STOCK'!I54 -> 19600 | AM57: ='MASTER STOCK'!L54 -> 29400 | AN57: =AH57*AM57 -> 0 | AO57: =AN57-(AH57*AL57) -> 0 | AP57: =AH57*AL57 -> 0
... A60: ='MASTER STOCK'!F57 -> Palu Konde besi cor gagang kayu ukuran 1LB | B60: ='MASTER STOCK'!G57 -> 3 | AH60: =SUM(C60:AG60) -> 0 | AI60: =B60-SUM(C60:AG60) -> 3 | AJ60: =B60-AH60 -> 3 | AK60: =AJ60-AI60 -> 0 | AL60: ='MASTER STOCK'!I57 -> 17000 | AM60: ='MASTER STOCK'!L57 -> 22100 | AN60: =AH60*AM60 -> 0 | AO60: =AN60-(AH60*AL60) -> 0 | AP60: =AH60*AL60 -> 0
A61: ='MASTER STOCK'!F58 -> Lem kuning 100gr | B61: ='MASTER STOCK'!G58 -> 25 | Z61: 1 | AH61: =SUM(C61:AG61) -> 1 | AI61: =B61-SUM(C61:AG61) -> 24 | AJ61: =B61-AH61 -> 24 | AK61: =AJ61-AI61 -> 0 | AL61: ='MASTER STOCK'!I58 -> 10000 | AM61: ='MASTER STOCK'!L58 -> 15000 | AN61: =AH61*AM61 -> 15000 | AO61: =AN61-(AH61*AL61) -> 5000 | AP61: =AH61*AL61 -> 10000
A62: ='MASTER STOCK'!F59 -> Lem aica aibon kuning 125gr | B62: ='MASTER STOCK'!G59 -> 2 | AH62: =SUM(C62:AG62) -> 0 | AI62: =B62-SUM(C62:AG62) -> 2 | AJ62: =B62-AH62 -> 2 | AK62: =AJ62-AI62 -> 0 | AL62: ='MASTER STOCK'!I59 -> 18200 | AM62: ='MASTER STOCK'!L59 -> 27300 | AN62: =AH62*AM62 -> 0 | AO62: =AN62-(AH62*AL62) -> 0 | AP62: =AH62*AL62 -> 0
A63: ='MASTER STOCK'!F60 -> Kuas 4" incco | B63: ='MASTER STOCK'!G60 -> 3 | AH63: =SUM(C63:AG63) -> 0 | AI63: =B63-SUM(C63:AG63) -> 3 | AJ63: =B63-AH63 -> 3 | AK63: =AJ63-AI63 -> 0 | AL63: ='MASTER STOCK'!I60 -> 15000 | AM63: ='MASTER STOCK'!L60 -> 19500 | AN63: =AH63*AM63 -> 0 | AO63: =AN63-(AH63*AL63) -> 0 | AP63: =AH63*AL63 -> 0
A64: ='MASTER STOCK'!F61 -> Meteran Autostop Wilmer 5m*19mm | B64: ='MASTER STOCK'!G61 -> 2 | AH64: =SUM(C64:AG64) -> 0 | AI64: =B64-SUM(C64:AG64) -> 2 | AJ64: =B64-AH64 -> 2 | AK64: =AJ64-AI64 -> 0 | AL64: ='MASTER STOCK'!I61 -> 25000 | AM64: ='MASTER STOCK'!L61 -> 30000 | AN64: =AH64*AM64 -> 0 | AO64: =AN64-(AH64*AL64) -> 0 | AP64: =AH64*AL64 -> 0
A65: ='MASTER STOCK'!F62 -> Precision S/Driver Obeng 6S DIY | B65: ='MASTER STOCK'!G62 -> 2 | AH65: =SUM(C65:AG65) -> 0 | AI65: =B65-SUM(C65:AG65) -> 2 | AJ65: =B65-AH65 -> 2 | AK65: =AJ65-AI65 -> 0 | AL65: ='MASTER STOCK'!I62 -> 9500 | AM65: ='MASTER STOCK'!L62 -> 13300 | AN65: =AH65*AM65 -> 0 | AO65: =AN65-(AH65*AL65) -> 0 | AP65: =AH65*AL65 -> 0
A66: ='MASTER STOCK'!F63 -> Blades / Isi Cutter Besar DIY | B66: ='MASTER STOCK'!G63 -> 20 | AH66: =SUM(C66:AG66) -> 0 | AI66: =B66-SUM(C66:AG66) -> 20 | AJ66: =B66-AH66 -> 20 | AK66: =AJ66-AI66 -> 0 | AL66: ='MASTER STOCK'!I63 -> 1150 | AM66: ='MASTER STOCK'!L63 -> 1495 | AN66: =AH66*AM66 -> 0 | AO66: =AN66-(AH66*AL66) -> 0 | AP66: =AH66*AL66 -> 0
A67: ='MASTER STOCK'!F64 -> Blades / Isi Cutter Kecil DIY | B67: ='MASTER STOCK'!G64 -> 20 | AH67: =SUM(C67:AG67) -> 0 | AI67: =B67-SUM(C67:AG67) -> 20 | AJ67: =B67-AH67 -> 20 | AK67: =AJ67-AI67 -> 0 | AL67: ='MASTER STOCK'!I64 -> 700 | AM67: ='MASTER STOCK'!L64 -> 1050 | AN67: =AH67*AM67 -> 0 | AO67: =AN67-(AH67*AL67) -> 0 | AP67: =AH67*AL67 -> 0
A68: ='MASTER STOCK'!F65 -> Screwdriver / Obeng 4" isi 2 DIY | B68: ='MASTER STOCK'!G65 -> 2 | AH68: =SUM(C68:AG68) -> 0 | AI68: =B68-SUM(C68:AG68) -> 2 | AJ68: =B68-AH68 -> 2 | AK68: =AJ68-AI68 -> 0 | AL68: ='MASTER STOCK'!I65 -> 12000 | AM68: ='MASTER STOCK'!L65 -> 15600 | AN68: =AH68*AM68 -> 0 | AO68: =AN68-(AH68*AL68) -> 0 | AP68: =AH68*AL68 -> 0
A69: ='MASTER STOCK'!F66 -> Test Pen DIY | B69: ='MASTER STOCK'!G66 -> 2 | AH69: =SUM(C69:AG69) -> 0 | AI69: =B69-SUM(C69:AG69) -> 2 | AJ69: =B69-AH69 -> 2 | AK69: =AJ69-AI69 -> 0 | AL69: ='MASTER STOCK'!I66 -> 12000 | AM69: ='MASTER STOCK'!L66 -> 15600 | AN69: =AH69*AM69 -> 0 | AO69: =AN69-(AH69*AL69) -> 0 | AP69: =AH69*AL69 -> 0
A70: ='MASTER STOCK'!F67 -> Door Bolt / Selot Pintu DIY 4" | B70: ='MASTER STOCK'!G67 -> 3 | AH70: =SUM(C70:AG70) -> 0 | AI70: =B70-SUM(C70:AG70) -> 3 | AJ70: =B70-AH70 -> 3 | AK70: =AJ70-AI70 -> 0 | AL70: ='MASTER STOCK'!I67 -> 7500 | AM70: ='MASTER STOCK'!L67 -> 9750 | AN70: =AH70*AM70 -> 0 | AO70: =AN70-(AH70*AL70) -> 0 | AP70: =AH70*AL70 -> 0
A71: ='MASTER STOCK'!F68 -> Door Bolt / Selot Pintu DIY 3" | B71: ='MASTER STOCK'!G68 -> 2 | AH71: =SUM(C71:AG71) -> 0 | AI71: =B71-SUM(C71:AG71) -> 2 | AJ71: =B71-AH71 -> 2 | AK71: =AJ71-AI71 -> 0 | AL71: ='MASTER STOCK'!I68 -> 10500 | AM71: ='MASTER STOCK'!L68 -> 13650 | AN71: =AH71*AM71 -> 0 | AO71: =AN71-(AH71*AL71) -> 0 | AP71: =AH71*AL71 -> 0
A72: ='MASTER STOCK'!F69 -> Kuas 2" incco | B72: ='MASTER STOCK'!G69 -> 3 | AH72: =SUM(C72:AG72) -> 0 | AI72: =B72-SUM(C72:AG72) -> 3 | AJ72: =B72-AH72 -> 3 | AK72: =AJ72-AI72 -> 0 | AL72: ='MASTER STOCK'!I69 -> 7000 | AM72: ='MASTER STOCK'!L69 -> 9100 | AN72: =AH72*AM72 -> 0 | AO72: =AN72-(AH72*AL72) -> 0 | AP72: =AH72*AL72 -> 0
A73: ='MASTER STOCK'!F70 -> Kuas 1" incco | B73: ='MASTER STOCK'!G70 -> 5 | AH73: =SUM(C73:AG73) -> 0 | AI73: =B73-SUM(C73:AG73) -> 5 | AJ73: =B73-AH73 -> 5 | AK73: =AJ73-AI73 -> 0 | AL73: ='MASTER STOCK'!I70 -> 3500 | AM73: ='MASTER STOCK'!L70 -> 4550 | AN73: =AH73*AM73 -> 0 | AO73: =AN73-(AH73*AL73) -> 0 | AP73: =AH73*AL73 -> 0
... A370: ='MASTER STOCK'!F367 -> TIMBA STANDART | B370: ='MASTER STOCK'!G367 -> 10 | AH370: =SUM(C370:AG370) -> 0 | AI370: =B370-SUM(C370:AG370) -> 10 | AJ370: =B370-AH370 -> 10 | AK370: =AJ370-AI370 -> 0 | AL370: ='MASTER STOCK'!I367 -> 5000 | AM370: ='MASTER STOCK'!L367 -> 8000 | AN370: =AH370*AM370 -> 0 | AO370: =AN370-(AH370*AL370) -> 0 | AP370: =AH370*AL370 -> 0
A371: ='MASTER STOCK'!F368 -> KNEE DRAT DALAM 1/2 DIM | B371: ='MASTER STOCK'!G368 -> 15 | AH371: =SUM(C371:AG371) -> 0 | AI371: =B371-SUM(C371:AG371) -> 15 | AJ371: =B371-AH371 -> 15 | AK371: =AJ371-AI371 -> 0 | AL371: ='MASTER STOCK'!I368 -> 1400 | AM371: ='MASTER STOCK'!L368 -> 3500 | AP371: =AH371*AL371 -> 0
A372: ='MASTER STOCK'!F369 -> AMPLAS UK 60 | B372: ='MASTER STOCK'!G369 -> 10 | AH372: =SUM(C372:AG372) -> 0 | AI372: =B372-SUM(C372:AG372) -> 10 | AJ372: =B372-AH372 -> 10 | AK372: =AJ372-AI372 -> 0 | AL372: ='MASTER STOCK'!I369 -> 4500 | AM372: ='MASTER STOCK'!L369 -> 7000 | AP372: =AH372*AL372 -> 0
A373: ='MASTER STOCK'!F370 -> AMPLAS UK 150 | B373: ='MASTER STOCK'!G370 -> 10 | AH373: =SUM(C373:AG373) -> 0 | AI373: =B373-SUM(C373:AG373) -> 10 | AJ373: =B373-AH373 -> 10 | AK373: =AJ373-AI373 -> 0 | AL373: ='MASTER STOCK'!I370 -> 4500 | AM373: ='MASTER STOCK'!L370 -> 7000 | AP373: =AH373*AL373 -> 0
A374: ='MASTER STOCK'!F371 -> AMPLAS UK 240 | B374: ='MASTER STOCK'!G371 -> 10 | AH374: =SUM(C374:AG374) -> 0 | AI374: =B374-SUM(C374:AG374) -> 10 | AJ374: =B374-AH374 -> 10 | AK374: =AJ374-AI374 -> 0 | AL374: ='MASTER STOCK'!I371 -> 4500 | AM374: ='MASTER STOCK'!L371 -> 7000 | AP374: =AH374*AL374 -> 0
A375: ='MASTER STOCK'!F372 -> WATERMUR DD 3/4 | B375: ='MASTER STOCK'!G372 -> 5 | AH375: =SUM(C375:AG375) -> 0 | AI375: =B375-SUM(C375:AG375) -> 5 | AJ375: =B375-AH375 -> 5 | AK375: =AJ375-AI375 -> 0 | AL375: ='MASTER STOCK'!I372 -> 6000 | AM375: ='MASTER STOCK'!L372 -> 8000 | AP375: =AH375*AL375 -> 0
A376: ='MASTER STOCK'!F373 -> BENDRAT 5KG | B376: ='MASTER STOCK'!G373 -> 5 | AH376: =SUM(C376:AG376) -> 0 | AI376: =B376-SUM(C376:AG376) -> 5 | AJ376: =B376-AH376 -> 5 | AK376: =AJ376-AI376 -> 0 | AL376: ='MASTER STOCK'!I373 -> 19000 | AM376: ='MASTER STOCK'!L373 -> 25000 | AP376: =AH376*AL376 -> 0
A377: ='MASTER STOCK'!F374 -> S MERDEKA 5 | B377: ='MASTER STOCK'!G374 -> 5 | AH377: =SUM(C377:AG377) -> 0 | AI377: =B377-SUM(C377:AG377) -> 5 | AJ377: =B377-AH377 -> 5 | AK377: =AJ377-AI377 -> 0 | AL377: ='MASTER STOCK'!I374 -> 41500 | AM377: ='MASTER STOCK'!L374 -> 4300 | AP377: =AH377*AL377 -> 0
A378: ='MASTER STOCK'!F375 | B378: ='MASTER STOCK'!G375 -> 0 | AH378: =SUM(C378:AG378) -> 0 | AI378: =B378-SUM(C378:AG378) -> 0 | AJ378: =B378-AH378 -> 0 | AK378: =AJ378-AI378 -> 0 | AL378: ='MASTER STOCK'!I375 | AM378: ='MASTER STOCK'!L375 | AP378: =AH378*AL378 -> 0
A379: ='MASTER STOCK'!F376 | B379: ='MASTER STOCK'!G376 -> 0 | AH379: =SUM(C379:AG379) -> 0 | AL379: ='MASTER STOCK'!I376 | AM379: ='MASTER STOCK'!L376 | AP379: =AH379*AL379 -> 0
A380: ='MASTER STOCK'!F377 | B380: ='MASTER STOCK'!G377 -> 0 | AH380: =SUM(C380:AG380) -> 0 | AL380: ='MASTER STOCK'!I377 | AM380: ='MASTER STOCK'!L377 | AP380: =AH380*AL380 -> 0
A381: ='MASTER STOCK'!F378 | B381: ='MASTER STOCK'!G378 -> 0 | AH381: =SUM(C381:AG381) -> 0 | AL381: ='MASTER STOCK'!I378 | AM381: ='MASTER STOCK'!L378 | AP381: =AH381*AL381 -> 0
A382: ='MASTER STOCK'!F379 | B382: ='MASTER STOCK'!G379 -> 0 | AH382: =SUM(C382:AG382) -> 0 | AL382: ='MASTER STOCK'!I379 | AM382: ='MASTER STOCK'!L379 | AP382: =AH382*AL382 -> 0
A383: ='MASTER STOCK'!F380 | B383: ='MASTER STOCK'!G380 -> 0 | AH383: =SUM(C383:AG383) -> 0 | AL383: ='MASTER STOCK'!I380 | AM383: ='MASTER STOCK'!L380 | AP383: =AH383*AL383 -> 0
A384: ='MASTER STOCK'!F381 | B384: ='MASTER STOCK'!G381 -> 0 | AH384: =SUM(C384:AG384) -> 0 | AL384: ='MASTER STOCK'!I381 | AM384: ='MASTER STOCK'!L381 | AP384: =AH384*AL384 -> 0
A385: ='MASTER STOCK'!F382 | B385: ='MASTER STOCK'!G382 -> 0 | AL385: ='MASTER STOCK'!I382 | AM385: ='MASTER STOCK'!L382 | AP385: =AH385*AL385 -> 0
A386: ='MASTER STOCK'!F383 | B386: ='MASTER STOCK'!G383 -> 0 | AL386: ='MASTER STOCK'!I383 | AM386: ='MASTER STOCK'!L383 | AP386: =AH386*AL386 -> 0
A387: ='MASTER STOCK'!F384 | B387: ='MASTER STOCK'!G384 -> 0 | AL387: ='MASTER STOCK'!I384 | AM387: ='MASTER STOCK'!L384 | AP387: =AH387*AL387 -> 0

Sheet AGS 25
A1: LAPORAN PENJUALAN BULANAN | AQ1: 45870
A2: NAMA BARANG | B2: STOK AWAL | C2: =UPPER("HARI / BULAN : " & TEXT(AQ1, "MMMM YYYY")) -> HARI / BULAN : AGUSTUS 2025
C3: =TEXT(C4,"dddd") -> Jumat | D3: =TEXT(D4,"dddd") -> Sabtu | E3: =TEXT(E4,"dddd") -> Minggu | F3: =TEXT(F4,"dddd") -> Senin | G3: =TEXT(G4,"dddd") -> Selasa | H3: =TEXT(H4,"dddd") -> Rabu | I3: =TEXT(I4,"dddd") -> Kamis | J3: =TEXT(J4,"dddd") -> Jumat | ... AG3: =TEXT(AG4,"dddd") -> Minggu | AH3: TOTAL | AI3: STOCK | AJ3: SYSTEM | AK3: KET/SELISIH | AL3: HARGA BELI | AM3: HARGA JUAL | AN3: OMSET | AO3: PROFIT | AP3: TOTAL MODAL
C4: =AQ1 -> 45870 | D4: =IF(AND(MONTH(C4+1) = MONTH(C4), C4<>""),C4 + 1, "") -> 45871 | E4: =IF(AND(MONTH(D4+1) = MONTH(D4), D4<>""),D4 + 1, "") -> 45872 | F4: =IF(AND(MONTH(E4+1) = MONTH(E4), E4<>""),E4 + 1, "") -> 45873 | G4: =IF(AND(MONTH(F4+1) = MONTH(F4), F4<>""),F4 + 1, "") -> 45874 | H4: =IF(AND(MONTH(G4+1) = MONTH(G4), G4<>""),G4 + 1, "") -> 45875 | I4: =IF(AND(MONTH(H4+1) = MONTH(H4), H4<>""),H4 + 1, "") -> 45876 | J4: =IF(AND(MONTH(I4+1) = MONTH(I4), I4<>""),I4 + 1, "") -> 45877 | K4: =IF(AND(MONTH(J4+1) = MONTH(J4), J4<>""),J4 + 1, "") -> 45878 | ... AG4: =IF(AND(MONTH(AF4+1) = MONTH(AF4), AF4<>""),AF4 + 1, "") -> 45900
A5: ='MASTER STOCK'!F2 -> Fitting Gantung | B5: ='JULI 25'!AJ5:AJ362 -> 12 | AH5: =SUM(C5:AG5) -> 0 | AI5: =B5-sum(C5:AG5) -> 12 | AJ5: =B5-AH5 -> 12 | AK5: =AJ5-AI5 -> 0 | AL5: ='MASTER STOCK'!I2 -> 1400 | AM5: ='MASTER STOCK'!L2 -> 1820 | AN5: =AH5*AM5 -> 0 | AO5: =AN5-(AH5*AL5) -> 0 | AP5: =AH5*AL5 -> 0
A6: ='MASTER STOCK'!F3 -> Colokan T | B6: ='JULI 25'!AJ6:AJ363 -> 12 | AH6: =SUM(C6:AG6) -> 0 | AI6: =B6-sum(C6:AG6) -> 12 | AJ6: =B6-AH6 -> 12 | AK6: =AJ6-AI6 -> 0 | AL6: ='MASTER STOCK'!I3 -> 3000 | AM6: ='MASTER STOCK'!L3 -> 3900 | AN6: =AH6*AM6 -> 0 | AO6: =AN6-(AH6*AL6) -> 0 | AP6: =AH6*AL6 -> 0
A7: ='MASTER STOCK'!F4 -> Steker Bulat | B7: ='JULI 25'!AJ7:AJ364 -> 12 | AH7: =SUM(C7:AG7) -> 0 | AI7: =B7-sum(C7:AG7) -> 12 | AJ7: =B7-AH7 -> 12 | AK7: =AJ7-AI7 -> 0 | AL7: ='MASTER STOCK'!I4 -> 3000 | AM7: ='MASTER STOCK'!L4 -> 6000 | AN7: =AH7*AM7 -> 0 | AO7: =AN7-(AH7*AL7) -> 0 | AP7: =AH7*AL7 -> 0
A8: ='MASTER STOCK'!F5 -> Steker Gepeng | B8: ='JULI 25'!AJ8:AJ365 -> 12 | AH8: =SUM(C8:AG8) -> 0 | AI8: =B8-sum(C8:AG8) -> 12 | AJ8: =B8-AH8 -> 12 | AK8: =AJ8-AI8 -> 0 | AL8: ='MASTER STOCK'!I5 -> 1100 | AM8: ='MASTER STOCK'!L5 -> 1430 | AN8: =AH8*AM8 -> 0 | AO8: =AN8-(AH8*AL8) -> 0 | AP8: =AH8*AL8 -> 0
A9: ='MASTER STOCK'!F6 -> Saklar Gantung Putih jumbo | B9: ='JULI 25'!AJ9:AJ366 -> 12 | AH9: =SUM(C9:AG9) -> 0 | AI9: =B9-sum(C9:AG9) -> 12 | AJ9: =B9-AH9 -> 12 | AK9: =AJ9-AI9 -> 0 | AL9: ='MASTER STOCK'!I6 -> 2250 | AM9: ='MASTER STOCK'!L6 -> 4000 | AN9: =AH9*AM9 -> 0 | AO9: =AN9-(AH9*AL9) -> 0 | AP9: =AH9*AL9 -> 0
A10: ='MASTER STOCK'!F7 -> Saklar Gantung Hitam | B10: ='JULI 25'!AJ10:AJ367 -> 12 | AH10: =SUM(C10:AG10) -> 0 | AI10: =B10-sum(C10:AG10) -> 12 | AJ10: =B10-AH10 -> 12 | AK10: =AJ10-AI10 -> 0 | AL10: ='MASTER STOCK'!I7 -> 1850 | AM10: ='MASTER STOCK'!L7 -> 4000 | AN10: =AH10*AM10 -> 0 | AO10: =AN10-(AH10*AL10) -> 0 | AP10: =AH10*AL10 -> 0
A11: ='MASTER STOCK'!F8 -> Isolasi Hitam National | B11: ='JULI 25'!AJ11:AJ368 -> 20 | AH11: =SUM(C11:AG11) -> 0 | AI11: =B11-sum(C11:AG11) -> 20 | AJ11: =B11-AH11 -> 20 | AK11: =AJ11-AI11 -> 0 | AL11: ='MASTER STOCK'!I8 -> 5150 | AM11: ='MASTER STOCK'!L8 -> 7982.5 | AN11: =AH11*AM11 -> 0 | AO11: =AN11-(AH11*AL11) -> 0 | AP11: =AH11*AL11 -> 0
A12: ='MASTER STOCK'!F9 -> Lem PVC Isarplas 40gram | B12: ='JULI 25'!AJ12:AJ369 -> 24 | S12: 1 | AH12: =SUM(C12:AG12) -> 1 | AI12: =B12-sum(C12:AG12) -> 23 | AJ12: =B12-AH12 -> 23 | AK12: =AJ12-AI12 -> 0 | AL12: ='MASTER STOCK'!I9 -> 6900 | AM12: ='MASTER STOCK'!L9 -> 9500 | AN12: =AH12*AM12 -> 9500 | AO12: =AN12-(AH12*AL12) -> 2600 | AP12: =AH12*AL12 -> 6900
A13: ='MASTER STOCK'!F10 -> Isolasi Kran air onda | B13: ='JULI 25'!AJ13:AJ370 -> 60 | AH13: =SUM(C13:AG13) -> 0 | AI13: =B13-sum(C13:AG13) -> 60 | AJ13: =B13-AH13 -> 60 | AK13: =AJ13-AI13 -> 0 | AL13: ='MASTER STOCK'!I10 -> 1150 | AM13: ='MASTER STOCK'!L10 -> 1495 | AN13: =AH13*AM13 -> 0 | AO13: =AN13-(AH13*AL13) -> 0 | AP13: =AH13*AL13 -> 0
A14: ='MASTER STOCK'!F11 -> Tutup Pipa 3/4" | B14: ='JULI 25'!AJ14:AJ371 -> 50 | AH14: =SUM(C14:AG14) -> 0 | AI14: =B14-sum(C14:AG14) -> 50 | AJ14: =B14-AH14 -> 50 | AK14: =AJ14-AI14 -> 0 | AL14: ='MASTER STOCK'!I11 -> 850 | AM14: ='MASTER STOCK'!L11 -> 1275 | AN14: =AH14*AM14 -> 0 | AO14: =AN14-(AH14*AL14) -> 0 | AP14: =AH14*AL14 -> 0
A15: ='MASTER STOCK'!F12 -> Fitting lampu gantung outdoor (10 m 5 fitting) | B15: ='JULI 25'!AJ15:AJ372 -> 1 | AH15: =SUM(C15:AG15) -> 0 | AI15: =B15-sum(C15:AG15) -> 1 | AJ15: =B15-AH15 -> 1 | AK15: =AJ15-AI15 -> 0 | AL15: ='MASTER STOCK'!I12 -> 38000 | AM15: ='MASTER STOCK'!L12 -> 49400 | AN15: =AH15*AM15 -> 0 | AO15: =AN15-(AH15*AL15) -> 0 | AP15: =AH15*AL15 -> 0
A16: ='MASTER STOCK'!F13 -> Obeng karet 4" plus | B16: ='JULI 25'!AJ16:AJ373 -> 5 | AH16: =SUM(C16:AG16) -> 0 | AI16: =B16-sum(C16:AG16) -> 5 | AJ16: =B16-AH16 -> 5 | AK16: =AJ16-AI16 -> 0 | AL16: ='MASTER STOCK'!I13 -> 5500 | AM16: ='MASTER STOCK'!L13 -> 7150 | AN16: =AH16*AM16 -> 0 | AO16: =AN16-(AH16*AL16) -> 0 | AP16: =AH16*AL16 -> 0
A17: ='MASTER STOCK'!F14 -> Obeng karet 4" minus | B17: ='JULI 25'!AJ17:AJ374 -> 4 | AH17: =SUM(C17:AG17) -> 0 | AI17: =B17-sum(C17:AG17) -> 4 | AJ17: =B17-AH17 -> 4 | AK17: =AJ17-AI17 -> 0 | AL17: ='MASTER STOCK'!I14 -> 5500 | AM17: ='MASTER STOCK'!L14 -> 7150 | AN17: =AH17*AM17 -> 0 | AO17: =AN17-(AH17*AL17) -> 0 | AP17: =AH17*AL17 -> 0
A18: ='MASTER STOCK'!F15 -> Obeng karet 6" plus | B18: ='JULI 25'!AJ18:AJ375 -> 5 | AH18: =SUM(C18:AG18) -> 0 | AI18: =B18-sum(C18:AG18) -> 5 | AJ18: =B18-AH18 -> 5 | AK18: =AJ18-AI18 -> 0 | AL18: ='MASTER STOCK'!I15 -> 7000 | AM18: ='MASTER STOCK'!L15 -> 9100 | AN18: =AH18*AM18 -> 0 | AO18: =AN18-(AH18*AL18) -> 0 | AP18: =AH18*AL18 -> 0
A19: ='MASTER STOCK'!F16 -> Obeng karet 6" Minus | B19: ='JULI 25'!AJ19:AJ376 -> 5 | AH19: =SUM(C19:AG19) -> 0 | AI19: =B19-sum(C19:AG19) -> 5 | AJ19: =B19-AH19 -> 5 | AK19: =AJ19-AI19 -> 0 | AL19: ='MASTER STOCK'!I16 -> 7000 | AM19: ='MASTER STOCK'!L16 -> 9100 | AN19: =AH19*AM19 -> 0 | AO19: =AN19-(AH19*AL19) -> 0 | AP19: =AH19*AL19 -> 0
A20: ='MASTER STOCK'!F17 -> Kabel Awg 24 Double 2x18 merah hitam | B20: ='JULI 25'!AJ20:AJ377 -> 2 | AH20: =SUM(C20:AG20) -> 0 | AI20: =B20-sum(C20:AG20) -> 2 | AJ20: =B20-AH20 -> 2 | AK20: =AJ20-AI20 -> 0 | AL20: ='MASTER STOCK'!I17 -> 106500 | AM20: ='MASTER STOCK'!L17 -> 181050 | AN20: =AH20*AM20 -> 0 | AO20: =AN20-(AH20*AL20) -> 0 | AP20: =AH20*AL20 -> 0
A21: ='MASTER STOCK'!F18 -> Kabel bintik serabut tembaga motor mobil 20mx0.5mm/0,85mm merah 0,5mm | B21: ='JULI 25'!AJ21:AJ378 -> 2 | AH21: =SUM(C21:AG21) -> 0 | AI21: =B21-sum(C21:AG21) -> 2 | AJ21: =B21-AH21 -> 2 | AK21: =AJ21-AI21 -> 0 | AL21: ='MASTER STOCK'!I18 -> 33700 | AM21: ='MASTER STOCK'!L18 -> 57290 | AN21: =AH21*AM21 -> 0 | AO21: =AN21-(AH21*AL21) -> 0 | AP21: =AH21*AL21 -> 0
A22: ='MASTER STOCK'!F19 -> Kabel bintik serabut tembaga motor mobil 20mx0.5mm/0,85mm hitam 0,5mm | B22: ='JULI 25'!AJ22:AJ379 -> 2 | AH22: =SUM(C22:AG22) -> 0 | AI22: =B22-sum(C22:AG22) -> 2 | AJ22: =B22-AH22 -> 2 | AK22: =AJ22-AI22 -> 0 | AL22: ='MASTER STOCK'!I19 -> 33700 | AM22: ='MASTER STOCK'!L19 -> 57290 | AN22: =AH22*AM22 -> 0 | AO22: =AN22-(AH22*AL22) -> 0 | AP22: =AH22*AL22 -> 0
A23: ='MASTER STOCK'!F20 -> Mata Gerinda keramik 4 inch kering | B23: ='JULI 25'!AJ23:AJ380 -> 5 | AH23: =SUM(C23:AG23) -> 0 | AI23: =B23-sum(C23:AG23) -> 5 | AJ23: =B23-AH23 -> 5 | AK23: =AJ23-AI23 -> 0 | AL23: ='MASTER STOCK'!I20 -> 12000 | AM23: ='MASTER STOCK'!L20 -> 18000 | AN23: =AH23*AM23 -> 0 | AO23: =AN23-(AH23*AL23) -> 0 | AP23: =AH23*AL23 -> 0
A24: ='MASTER STOCK'!F21 -> Kabel tunggal serabut 0.8mmx25m biru 25m | B24: ='JULI 25'!AJ24:AJ381 -> 1 | AH24: =SUM(C24:AG24) -> 0 | AI24: =B24-sum(C24:AG24) -> 1 | AJ24: =B24-AH24 -> 1 | AK24: =AJ24-AI24 -> 0 | AL24: ='MASTER STOCK'!I21 -> 17500 | AM24: ='MASTER STOCK'!L21 -> 29750 | AN24: =AH24*AM24 -> 0 | AO24: =AN24-(AH24*AL24) -> 0 | AP24: =AH24*AL24 -> 0
... A27: ='MASTER STOCK'!F24 -> Lampu LED strip outdoor rainbow 10m +adaptor | B27: ='JULI 25'!AJ27:AJ384 -> 5 | AH27: =SUM(C27:AG27) -> 0 | AI27: =B27-sum(C27:AG27) -> 5 | AJ27: =B27-AH27 -> 5 | AK27: =AJ27-AI27 -> 0 | AL27: ='MASTER STOCK'!I24 -> 27000 | AM27: ='MASTER STOCK'!L24 -> 35100 | AN27: =AH27*AM27 -> 0 | AO27: =AN27-(AH27*AL27) -> 0 | AP27: =AH27*AL27 -> 0
A28: ='MASTER STOCK'!F25 -> Lampu LED strip outdoor merah putih 10m +adaptor | B28: ='JULI 25'!AJ28:AJ385 -> 5 | T28: 1 | AH28: =SUM(C28:AG28) -> 1 | AI28: =B28-sum(C28:AG28) -> 4 | AJ28: =B28-AH28 -> 4 | AK28: =AJ28-AI28 -> 0 | AL28: ='MASTER STOCK'!I25 -> 30000 | AM28: ='MASTER STOCK'!L25 -> 40500 | AN28: =AH28*AM28 -> 40500 | AO28: =AN28-(AH28*AL28) -> 10500 | AP28: =AH28*AL28 -> 30000
A29: ='MASTER STOCK'!F26 -> Lampu tumbler 10m (rainbow) | B29: ='JULI 25'!AJ29:AJ386 -> 5 | AH29: =SUM(C29:AG29) -> 0 | AI29: =B29-sum(C29:AG29) -> 5 | AJ29: =B29-AH29 -> 5 | AK29: =AJ29-AI29 -> 0 | AL29: ='MASTER STOCK'!I26 -> 11000 | AM29: ='MASTER STOCK'!L26 -> 14300 | AN29: =AH29*AM29 -> 0 | AO29: =AN29-(AH29*AL29) -> 0 | AP29: =AH29*AL29 -> 0
A30: ='MASTER STOCK'!F27 -> WD Gerinda potong besi | B30: ='JULI 25'!AJ30:AJ387 -> 58 | AH30: =SUM(C30:AG30) -> 0 | AI30: =B30-sum(C30:AG30) -> 58 | AJ30: =B30-AH30 -> 58 | AK30: =AJ30-AI30 -> 0 | AL30: ='MASTER STOCK'!I27 -> 2900 | AM30: ='MASTER STOCK'!L27 -> 5000 | AN30: =AH30*AM30 -> 0 | AO30: =AN30-(AH30*AL30) -> 0 | AP30: =AH30*AL30 -> 0
A31: ='MASTER STOCK'!F28 -> Meteran karet 7,5m (merk HPP) | B31: ='JULI 25'!AJ31:AJ388 -> 3 | AH31: =SUM(C31:AG31) -> 0 | AI31: =B31-sum(C31:AG31) -> 3 | AJ31: =B31-AH31 -> 3 | AK31: =AJ31-AI31 -> 0 | AL31: ='MASTER STOCK'!I28 -> 12800 | AM31: ='MASTER STOCK'!L28 -> 16640 | AN31: =AH31*AM31 -> 0 | AO31: =AN31-(AH31*AL31) -> 0 | AP31: =AH31*AL31 -> 0
A32: ='MASTER STOCK'!F29 -> Meteran karet 5m (merk VPR) | B32: ='JULI 25'!AJ32:AJ389 -> 3 | AH32: =SUM(C32:AG32) -> 0 | AI32: =B32-sum(C32:AG32) -> 3 | AJ32: =B32-AH32 -> 3 | AK32: =AJ32-AI32 -> 0 | AL32: ='MASTER STOCK'!I29 -> 7000 | AM32: ='MASTER STOCK'!L29 -> 9100 | AN32: =AH32*AM32 -> 0 | AO32: =AN32-(AH32*AL32) -> 0 | AP32: =AH32*AL32 -> 0
A33: ='MASTER STOCK'!F30 -> Kuas cat 2 1/2" (merk MDN) | B33: ='JULI 25'!AJ33:AJ390 -> 5 | AH33: =SUM(C33:AG33) -> 0 | AI33: =B33-sum(C33:AG33) -> 5 | AJ33: =B33-AH33 -> 5 | AK33: =AJ33-AI33 -> 0 | AL33: ='MASTER STOCK'!I30 -> 5300 | AM33: ='MASTER STOCK'!L30 -> 6890 | AN33: =AH33*AM33 -> 0 | AO33: =AN33-(AH33*AL33) -> 0 | AP33: =AH33*AL33 -> 0
A34: ='MASTER STOCK'!F31 -> Kuas cat 2" (merk MDN) | B34: ='JULI 25'!AJ34:AJ391 -> 5 | AH34: =SUM(C34:AG34) -> 0 | AI34: =B34-sum(C34:AG34) -> 5 | AJ34: =B34-AH34 -> 5 | AK34: =AJ34-AI34 -> 0 | AL34: ='MASTER STOCK'!I31 -> 4400 | AM34: ='MASTER STOCK'!L31 -> 5720 | AN34: =AH34*AM34 -> 0 | AO34: =AN34-(AH34*AL34) -> 0 | AP34: =AH34*AL34 -> 0
A35: ='MASTER STOCK'!F32 -> Kuas cat 3" (merk MDN) | B35: ='JULI 25'!AJ35:AJ392 -> 5 | T35: 1 | AH35: =SUM(C35:AG35) -> 1 | AI35: =B35-sum(C35:AG35) -> 4 | AJ35: =B35-AH35 -> 4 | AK35: =AJ35-AI35 -> 0 | AL35: ='MASTER STOCK'!I32 -> 6300 | AM35: ='MASTER STOCK'!L32 -> 8190 | AN35: =AH35*AM35 -> 8190 | AO35: =AN35-(AH35*AL35) -> 1890 | AP35: =AH35*AL35 -> 6300
A36: ='MASTER STOCK'!F33 -> Kuas cat 1 1/2" (merk MDN) | B36: ='JULI 25'!AJ36:AJ393 -> 5 | AH36: =SUM(C36:AG36) -> 0 | AI36: =B36-sum(C36:AG36) -> 5 | AJ36: =B36-AH36 -> 5 | AK36: =AJ36-AI36 -> 0 | AL36: ='MASTER STOCK'!I33 -> 3400 | AM36: ='MASTER STOCK'!L33 -> 4420 | AN36: =AH36*AM36 -> 0 | AO36: =AN36-(AH36*AL36) -> 0 | AP36: =AH36*AL36 -> 0
A37: ='MASTER STOCK'!F34 -> Kuas cat 1" (merk MDN) | B37: ='JULI 25'!AJ37:AJ394 -> 5 | T37: 1 | AH37: =SUM(C37:AG37) -> 1 | AI37: =B37-sum(C37:AG37) -> 4 | AJ37: =B37-AH37 -> 4 | AK37: =AJ37-AI37 -> 0 | AL37: ='MASTER STOCK'!I34 -> 2300 | AM37: ='MASTER STOCK'!L34 -> 2990 | AN37: =AH37*AM37 -> 2990 | AO37: =AN37-(AH37*AL37) -> 690 | AP37: =AH37*AL37 -> 2300
A38: ='MASTER STOCK'!F35 -> Kran PVC Tembok 3/4" | B38: ='JULI 25'!AJ38:AJ395 -> 24 | AH38: =SUM(C38:AG38) -> 0 | AI38: =B38-sum(C38:AG38) -> 24 | AJ38: =B38-AH38 -> 24 | AK38: =AJ38-AI38 -> 0 | AL38: ='MASTER STOCK'!I35 -> 4200 | AM38: ='MASTER STOCK'!L35 -> 6000 | AN38: =AH38*AM38 -> 0 | AO38: =AN38-(AH38*AL38) -> 0 | AP38: =AH38*AL38 -> 0
A39: ='MASTER STOCK'!F36 -> Kran PVC Tembok 1/2" | B39: ='JULI 25'!AJ39:AJ396 -> 24 | AH39: =SUM(C39:AG39) -> 0 | AI39: =B39-sum(C39:AG39) -> 24 | AJ39: =B39-AH39 -> 24 | AK39: =AJ39-AI39 -> 0 | AL39: ='MASTER STOCK'!I36 -> 4200 | AM39: ='MASTER STOCK'!L36 -> 6000 | AN39: =AH39*AM39 -> 0 | AO39: =AN39-(AH39*AL39) -> 0 | AP39: =AH39*AL39 -> 0
A40: ='MASTER STOCK'!F37 -> Lampu bohlam inlite 5w Putih | B40: ='JULI 25'!AJ40:AJ397 -> 7 | AH40: =SUM(C40:AG40) -> 0 | AI40: =B40-sum(C40:AG40) -> 7 | AJ40: =B40-AH40 -> 7 | AK40: =AJ40-AI40 -> 0 | AL40: ='MASTER STOCK'!I37 -> 13000 | AM40: ='MASTER STOCK'!L37 -> 18200 | AN40: =AH40*AM40 -> 0 | AO40: =AN40-(AH40*AL40) -> 0 | AP40: =AH40*AL40 -> 0
A41: ='MASTER STOCK'!F38 -> Lampu bohlam inlite 7w Putih | B41: ='JULI 25'!AJ41:AJ398 -> 2 | AH41: =SUM(C41:AG41) -> 0 | AI41: =B41-sum(C41:AG41) -> 2 | AJ41: =B41-AH41 -> 2 | AK41: =AJ41-AI41 -> 0 | AL41: ='MASTER STOCK'!I38 -> 16200 | AM41: ='MASTER STOCK'!L38 -> 22680 | AN41: =AH41*AM41 -> 0 | AO41: =AN41-(AH41*AL41) -> 0 | AP41: =AH41*AL41 -> 0
A42: ='MASTER STOCK'!F39 -> Lampu bohlam inlite 15w Putih | B42: ='JULI 25'!AJ42:AJ399 -> 4 | AH42: =SUM(C42:AG42) -> 0 | AI42: =B42-sum(C42:AG42) -> 4 | AJ42: =B42-AH42 -> 4 | AK42: =AJ42-AI42 -> 0 | AL42: ='MASTER STOCK'!I39 -> 28000 | AM42: ='MASTER STOCK'!L39 -> 39200 | AN42: =AH42*AM42 -> 0 | AO42: =AN42-(AH42*AL42) -> 0 | AP42: =AH42*AL42 -> 0
A43: ='MASTER STOCK'!F40 -> Lampu bohlam inlite 12w Putih | B43: ='JULI 25'!AJ43:AJ400 -> 6 | AH43: =SUM(C43:AG43) -> 0 | AI43: =B43-sum(C43:AG43) -> 6 | AJ43: =B43-AH43 -> 6 | AK43: =AJ43-AI43 -> 0 | AL43: ='MASTER STOCK'!I40 -> 25000 | AM43: ='MASTER STOCK'!L40 -> 30000 | AN43: =AH43*AM43 -> 0 | AO43: =AN43-(AH43*AL43) -> 0 | AP43: =AH43*AL43 -> 0
A44: ='MASTER STOCK'!F41 -> Lampu tintin platinum LED 9w | B44: ='JULI 25'!AJ44:AJ401 -> 4 | AH44: =SUM(C44:AG44) -> 0 | AI44: =B44-sum(C44:AG44) -> 4 | AJ44: =B44-AH44 -> 4 | AK44: =AJ44-AI44 -> 0 | AL44: ='MASTER STOCK'!I41 -> 7000 | AM44: ='MASTER STOCK'!L41 -> 9800 | AN44: =AH44*AM44 -> 0 | AO44: =AN44-(AH44*AL44) -> 0 | AP44: =AH44*AL44 -> 0
A45: ='MASTER STOCK'!F42 -> Lampu tintin platinum LED 5w | B45: ='JULI 25'!AJ45:AJ402 -> 4 | AH45: =SUM(C45:AG45) -> 0 | AI45: =B45-sum(C45:AG45) -> 4 | AJ45: =B45-AH45 -> 4 | AK45: =AJ45-AI45 -> 0 | AL45: ='MASTER STOCK'!I42 -> 5000 | AM45: ='MASTER STOCK'!L42 -> 7000 | AN45: =AH45*AM45 -> 0 | AO45: =AN45-(AH45*AL45) -> 0 | AP45: =AH45*AL45 -> 0
A46: ='MASTER STOCK'!F43 -> Lampu tintin platinum LED 21w | B46: ='JULI 25'!AJ46:AJ403 -> 3 | AH46: =SUM(C46:AG46) -> 0 | AI46: =B46-sum(C46:AG46) -> 3 | AJ46: =B46-AH46 -> 3 | AK46: =AJ46-AI46 -> 0 | AL46: ='MASTER STOCK'!I43 -> 15500 | AM46: ='MASTER STOCK'!L43 -> 21700 | AN46: =AH46*AM46 -> 0 | AO46: =AN46-(AH46*AL46) -> 0 | AP46: =AH46*AL46 -> 0
A47: ='MASTER STOCK'!F44 -> Lampu tintin platinum LED 15w | B47: ='JULI 25'!AJ47:AJ404 -> 5 | AH47: =SUM(C47:AG47) -> 0 | AI47: =B47-sum(C47:AG47) -> 5 | AJ47: =B47-AH47 -> 5 | AK47: =AJ47-AI47 -> 0 | AL47: ='MASTER STOCK'!I44 -> 8800 | AM47: ='MASTER STOCK'!L44 -> 13000 | AN47: =AH47*AM47 -> 0 | AO47: =AN47-(AH47*AL47) -> 0 | AP47: =AH47*AL47 -> 0
A48: ='MASTER STOCK'!F45 -> Lampu tintin platinum LED 12w | B48: ='JULI 25'!AJ48:AJ405 -> 5 | AH48: =SUM(C48:AG48) -> 0 | AI48: =B48-sum(C48:AG48) -> 5 | AJ48: =B48-AH48 -> 5 | AK48: =AJ48-AI48 -> 0 | AL48: ='MASTER STOCK'!I45 -> 7800 | AM48: ='MASTER STOCK'!L45 -> 10920 | AN48: =AH48*AM48 -> 0 | AO48: =AN48-(AH48*AL48) -> 0 | AP48: =AH48*AL48 -> 0
A49: ='MASTER STOCK'!F46 -> Lampu tintin platinum LED 7w | B49: ='JULI 25'!AJ49:AJ406 -> 5 | AH49: =SUM(C49:AG49) -> 0 | AI49: =B49-sum(C49:AG49) -> 5 | AJ49: =B49-AH49 -> 5 | AK49: =AJ49-AI49 -> 0 | AL49: ='MASTER STOCK'!I46 -> 5800 | AM49: ='MASTER STOCK'!L46 -> 8120 | AN49: =AH49*AM49 -> 0 | AO49: =AN49-(AH49*AL49) -> 0 | AP49: =AH49*AL49 -> 0
... A60: ='MASTER STOCK'!F57 -> Palu Konde besi cor gagang kayu ukuran 1LB | B60: ='JULI 25'!AJ60:AJ417 -> 3 | AH60: =SUM(C60:AG60) -> 0 | AI60: =B60-sum(C60:AG60) -> 3 | AJ60: =B60-AH60 -> 3 | AK60: =AJ60-AI60 -> 0 | AL60: ='MASTER STOCK'!I57 -> 17000 | AM60: ='MASTER STOCK'!L57 -> 22100 | AN60: =AH60*AM60 -> 0 | AO60: =AN60-(AH60*AL60) -> 0 | AP60: =AH60*AL60 -> 0
A61: ='MASTER STOCK'!F58 -> Lem kuning 100gr | B61: ='JULI 25'!AJ61:AJ418 -> 24 | C61: 1 | D61: 1 | AH61: =SUM(C61:AG61) -> 2 | AI61: =B61-sum(C61:AG61) -> 22 | AJ61: =B61-AH61 -> 22 | AK61: =AJ61-AI61 -> 0 | AL61: ='MASTER STOCK'!I58 -> 10000 | AM61: ='MASTER STOCK'!L58 -> 15000 | AN61: =AH61*AM61 -> 30000 | AO61: =AN61-(AH61*AL61) -> 10000 | AP61: =AH61*AL61 -> 20000
A62: ='MASTER STOCK'!F59 -> Lem aica aibon kuning 125gr | B62: ='JULI 25'!AJ62:AJ419 -> 2 | T62: 1 | AH62: =SUM(C62:AG62) -> 1 | AI62: =B62-sum(C62:AG62) -> 1 | AJ62: =B62-AH62 -> 1 | AK62: =AJ62-AI62 -> 0 | AL62: ='MASTER STOCK'!I59 -> 18200 | AM62: ='MASTER STOCK'!L59 -> 27300 | AN62: =AH62*AM62 -> 27300 | AO62: =AN62-(AH62*AL62) -> 9100 | AP62: =AH62*AL62 -> 18200
A63: ='MASTER STOCK'!F60 -> Kuas 4" incco | B63: ='JULI 25'!AJ63:AJ420 -> 3 | T63: 1 | AH63: =SUM(C63:AG63) -> 1 | AI63: =B63-sum(C63:AG63) -> 2 | AJ63: =B63-AH63 -> 2 | AK63: =AJ63-AI63 -> 0 | AL63: ='MASTER STOCK'!I60 -> 15000 | AM63: ='MASTER STOCK'!L60 -> 19500 | AN63: =AH63*AM63 -> 19500 | AO63: =AN63-(AH63*AL63) -> 4500 | AP63: =AH63*AL63 -> 15000
A64: ='MASTER STOCK'!F61 -> Meteran Autostop Wilmer 5m*19mm | B64: ='JULI 25'!AJ64:AJ421 -> 2 | AH64: =SUM(C64:AG64) -> 0 | AI64: =B64-sum(C64:AG64) -> 2 | AJ64: =B64-AH64 -> 2 | AK64: =AJ64-AI64 -> 0 | AL64: ='MASTER STOCK'!I61 -> 25000 | AM64: ='MASTER STOCK'!L61 -> 30000 | AN64: =AH64*AM64 -> 0 | AO64: =AN64-(AH64*AL64) -> 0 | AP64: =AH64*AL64 -> 0
A65: ='MASTER STOCK'!F62 -> Precision S/Driver Obeng 6S DIY | B65: ='JULI 25'!AJ65:AJ422 -> 2 | AH65: =SUM(C65:AG65) -> 0 | AI65: =B65-sum(C65:AG65) -> 2 | AJ65: =B65-AH65 -> 2 | AK65: =AJ65-AI65 -> 0 | AL65: ='MASTER STOCK'!I62 -> 9500 | AM65: ='MASTER STOCK'!L62 -> 13300 | AN65: =AH65*AM65 -> 0 | AO65: =AN65-(AH65*AL65) -> 0 | AP65: =AH65*AL65 -> 0
A66: ='MASTER STOCK'!F63 -> Blades / Isi Cutter Besar DIY | B66: ='JULI 25'!AJ66:AJ423 -> 20 | AH66: =SUM(C66:AG66) -> 0 | AI66: =B66-sum(C66:AG66) -> 20 | AJ66: =B66-AH66 -> 20 | AK66: =AJ66-AI66 -> 0 | AL66: ='MASTER STOCK'!I63 -> 1150 | AM66: ='MASTER STOCK'!L63 -> 1495 | AN66: =AH66*AM66 -> 0 | AO66: =AN66-(AH66*AL66) -> 0 | AP66: =AH66*AL66 -> 0
A67: ='MASTER STOCK'!F64 -> Blades / Isi Cutter Kecil DIY | B67: ='JULI 25'!AJ67:AJ424 -> 20 | AH67: =SUM(C67:AG67) -> 0 | AI67: =B67-sum(C67:AG67) -> 20 | AJ67: =B67-AH67 -> 20 | AK67: =AJ67-AI67 -> 0 | AL67: ='MASTER STOCK'!I64 -> 700 | AM67: ='MASTER STOCK'!L64 -> 1050 | AN67: =AH67*AM67 -> 0 | AO67: =AN67-(AH67*AL67) -> 0 | AP67: =AH67*AL67 -> 0
A68: ='MASTER STOCK'!F65 -> Screwdriver / Obeng 4" isi 2 DIY | B68: ='JULI 25'!AJ68:AJ425 -> 2 | AH68: =SUM(C68:AG68) -> 0 | AI68: =B68-sum(C68:AG68) -> 2 | AJ68: =B68-AH68 -> 2 | AK68: =AJ68-AI68 -> 0 | AL68: ='MASTER STOCK'!I65 -> 12000 | AM68: ='MASTER STOCK'!L65 -> 15600 | AN68: =AH68*AM68 -> 0 | AO68: =AN68-(AH68*AL68) -> 0 | AP68: =AH68*AL68 -> 0
A69: ='MASTER STOCK'!F66 -> Test Pen DIY | B69: ='JULI 25'!AJ69:AJ426 -> 2 | AH69: =SUM(C69:AG69) -> 0 | AI69: =B69-sum(C69:AG69) -> 2 | AJ69: =B69-AH69 -> 2 | AK69: =AJ69-AI69 -> 0 | AL69: ='MASTER STOCK'!I66 -> 12000 | AM69: ='MASTER STOCK'!L66 -> 15600 | AN69: =AH69*AM69 -> 0 | AO69: =AN69-(AH69*AL69) -> 0 | AP69: =AH69*AL69 -> 0
A70: ='MASTER STOCK'!F67 -> Door Bolt / Selot Pintu DIY 4" | B70: ='JULI 25'!AJ70:AJ427 -> 3 | AH70: =SUM(C70:AG70) -> 0 | AI70: =B70-sum(C70:AG70) -> 3 | AJ70: =B70-AH70 -> 3 | AK70: =AJ70-AI70 -> 0 | AL70: ='MASTER STOCK'!I67 -> 7500 | AM70: ='MASTER STOCK'!L67 -> 9750 | AN70: =AH70*AM70 -> 0 | AO70: =AN70-(AH70*AL70) -> 0 | AP70: =AH70*AL70 -> 0
A71: ='MASTER STOCK'!F68 -> Door Bolt / Selot Pintu DIY 3" | B71: ='JULI 25'!AJ71:AJ428 -> 2 | AH71: =SUM(C71:AG71) -> 0 | AI71: =B71-sum(C71:AG71) -> 2 | AJ71: =B71-AH71 -> 2 | AK71: =AJ71-AI71 -> 0 | AL71: ='MASTER STOCK'!I68 -> 10500 | AM71: ='MASTER STOCK'!L68 -> 13650 | AN71: =AH71*AM71 -> 0 | AO71: =AN71-(AH71*AL71) -> 0 | AP71: =AH71*AL71 -> 0
A72: ='MASTER STOCK'!F69 -> Kuas 2" incco | B72: ='JULI 25'!AJ72:AJ429 -> 3 | AH72: =SUM(C72:AG72) -> 0 | AI72: =B72-sum(C72:AG72) -> 3 | AJ72: =B72-AH72 -> 3 | AK72: =AJ72-AI72 -> 0 | AL72: ='MASTER STOCK'!I69 -> 7000 | AM72: ='MASTER STOCK'!L69 -> 9100 | AN72: =AH72*AM72 -> 0 | AO72: =AN72-(AH72*AL72) -> 0 | AP72: =AH72*AL72 -> 0
A73: ='MASTER STOCK'!F70 -> Kuas 1" incco | B73: ='JULI 25'!AJ73:AJ430 -> 5 | AH73: =SUM(C73:AG73) -> 0 | AI73: =B73-sum(C73:AG73) -> 5 | AJ73: =B73-AH73 -> 5 | AK73: =AJ73-AI73 -> 0 | AL73: ='MASTER STOCK'!I70 -> 3500 | AM73: ='MASTER STOCK'!L70 -> 4550 | AN73: =AH73*AM73 -> 0 | AO73: =AN73-(AH73*AL73) -> 0 | AP73: =AH73*AL73 -> 0
A74: ='MASTER STOCK'!F71 -> Kapi Plastik Kuning DIY | B74: ='JULI 25'!AJ74:AJ431 -> 4 | AH74: =SUM(C74:AG74) -> 0 | AI74: =B74-sum(C74:AG74) -> 4 | AJ74: =B74-AH74 -> 4 | AK74: =AJ74-AI74 -> 0 | AL74: ='MASTER STOCK'!I71 -> 5500 | AM74: ='MASTER STOCK'!L71 -> 7150 | AN74: =AH74*AM74 -> 0 | AO74: =AN74-(AH74*AL74) -> 0 | AP74: =AH74*AL74 -> 0
A75: ='MASTER STOCK'!F72 -> Kabel Ties 3.6x300mm (85 gram) isi 100 pcs | B75: ='JULI 25'!AJ75:AJ432 -> 1 | AH75: =SUM(C75:AG75) -> 0 | AI75: =B75-sum(C75:AG75) -> 1 | AJ75: =B75-AH75 -> 1 | AK75: =AJ75-AI75 -> 0 | AL75: ='MASTER STOCK'!I72 -> 11000 | AM75: ='MASTER STOCK'!L72 -> 16500 | AN75: =AH75*AM75 -> 0 | AO75: =AN75-(AH75*AL75) -> 0 | AP75: =AH75*AL75 -> 0
... A97: ='MASTER STOCK'!F94 -> Keranjang serbaguna | B97: ='JULI 25'!AJ97:AJ454 -> 24 | AH97: =SUM(C97:AG97) -> 0 | AI97: =B97-sum(C97:AG97) -> 24 | AJ97: =B97-AH97 -> 24 | AK97: =AJ97-AI97 -> 0 | AL97: ='MASTER STOCK'!I94 -> 4700 | AM97: ='MASTER STOCK'!L94 | AN97: =AH97*AM97 -> 0 | AO97: =AN97-(AH97*AL97) -> 0 | AP97: =AH97*AL97 -> 0
A98: ='MASTER STOCK'!F95 -> Paku (Nail 2000) 1 1/2" | B98: ='JULI 25'!AJ98:AJ455 -> 4 | Z98: 2.7 | AH98: =SUM(C98:AG98) -> 2.7 | AI98: =B98-sum(C98:AG98) -> 1.3 | AJ98: =B98-AH98 -> 1.3 | AK98: =AJ98-AI98 -> 0 | AL98: ='MASTER STOCK'!I95 -> 14400 | AM98: ='MASTER STOCK'!L95 -> 18720 | AN98: =AH98*AM98 -> 50544 | AO98: =AN98-(AH98*AL98) -> 11664 | AP98: =AH98*AL98 -> 38880
A99: ='MASTER STOCK'!F96 -> Paku (Nail 2000) 2 1/2" | B99: ='JULI 25'!AJ99:AJ456 -> 20 | C99: 0.1 | AH99: =SUM(C99:AG99) -> 0.1 | AI99: =B99-sum(C99:AG99) -> 19.9 | AJ99: =B99-AH99 -> 19.9 | AK99: =AJ99-AI99 -> 0 | AL99: ='MASTER STOCK'!I96 -> 13500 | AM99: ='MASTER STOCK'!L96 -> 17550 | AN99: =AH99*AM99 -> 1755 | AO99: =AN99-(AH99*AL99) -> 405 | AP99: =AH99*AL99 -> 1350
A100: ='MASTER STOCK'!F97 -> Paku (Nail 2000) 3" | B100: ='JULI 25'!AJ100:AJ457 -> 20 | F100: 0.5 | U100: 0.7 | AH100: =SUM(C100:AG100) -> 1.2 | AI100: =B100-sum(C100:AG100) -> 18.8 | AJ100: =B100-AH100 -> 18.8 | AK100: =AJ100-AI100 -> 0 | AL100: ='MASTER STOCK'!I97 -> 13500 | AM100: ='MASTER STOCK'!L97 -> 17550 | AN100: =AH100*AM100 -> 21060 | AO100: =AN100-(AH100*AL100) -> 4860 | AP100: =AH100*AL100 -> 16200
A101: ='MASTER STOCK'!F98 -> Paku (Nail 2000) 1" | B101: ='JULI 25'!AJ101:AJ458 -> 4 | C101: 0.15 | AG101: 0.5 | AH101: =SUM(C101:AG101) -> 0.65 | AI101: =B101-sum(C101:AG101) -> 3.35 | AJ101: =B101-AH101 -> 3.35 | AK101: =AJ101-AI101 -> 0 | AL101: ='MASTER STOCK'!I98 -> 15200 | AM101: ='MASTER STOCK'!L98 -> 19760 | AN101: =AH101*AM101 -> 12844 | AO101: =AN101-(AH101*AL101) -> 2964 | AP101: =AH101*AL101 -> 9880
A102: ='MASTER STOCK'!F99 -> Paku (Nail 20000 1 3/4" | B102: ='JULI 25'!AJ102:AJ459 -> 4 | C102: 0.1 | F102: 0.35 | I102: 0.15 | S102: 0.35 | AH102: =SUM(C102:AG102) -> 0.95 | AI102: =B102-sum(C102:AG102) -> 3.05 | AJ102: =B102-AH102 -> 3.05 | AK102: =AJ102-AI102 -> 0 | AL102: ='MASTER STOCK'!I99 -> 14100 | AM102: ='MASTER STOCK'!L99 -> 18330 | AN102: =AH102*AM102 -> 17413.5 | AO102: =AN102-(AH102*AL102) -> 4018.5 | AP102: =AH102*AL102 -> 13395
A103: ='MASTER STOCK'!F100 -> Paku (Nail 2000) 2" | B103: ='JULI 25'!AJ103:AJ460 -> 15 | U103: 1 | AH103: =SUM(C103:AG103) -> 1 | AI103: =B103-sum(C103:AG103) -> 14 | AJ103: =B103-AH103 -> 14 | AK103: =AJ103-AI103 -> 0 | AL103: ='MASTER STOCK'!I100 -> 13500 | AM103: ='MASTER STOCK'!L100 -> 17550 | AN103: =AH103*AM103 -> 17550 | AO103: =AN103-(AH103*AL103) -> 4050 | AP103: =AH103*AL103 -> 13500
A104: ='MASTER STOCK'!F101 -> Besi Beton 6mm SNI (U) | B104: ='JULI 25'!AJ104:AJ461 -> 10 | AH104: =SUM(C104:AG104) -> 0 | AI104: =B104-sum(C104:AG104) -> 10 | AJ104: =B104-AH104 -> 10 | AK104: =AJ104-AI104 -> 0 | AL104: ='MASTER STOCK'!I101 -> 22000 | AM104: ='MASTER STOCK'!L101 -> 26000 | AN104: =AH104*AM104 -> 0 | AO104: =AN104-(AH104*AL104) -> 0 | AP104: =AH104*AL104 -> 0
A105: ='MASTER STOCK'!F102 -> Besi Beton 8mm SNI (U) | B105: ='JULI 25'!AJ105:AJ462 -> 10 | M105: 2 | AH105: =SUM(C105:AG105) -> 2 | AI105: =B105-sum(C105:AG105) -> 8 | AJ105: =B105-AH105 -> 8 | AK105: =AJ105-AI105 -> 0 | AL105: ='MASTER STOCK'!I102 -> 37000 | AM105: ='MASTER STOCK'!L102 -> 43000 | AN105: =AH105*AM105 -> 86000 | AO105: =AN105-(AH105*AL105) -> 12000 | AP105: =AH105*AL105 -> 74000
A106: ='MASTER STOCK'!F103 -> Besi Beton 10mm SNI (U) | B106: ='JULI 25'!AJ106:AJ463 -> 5 | AH106: =SUM(C106:AG106) -> 0 | AI106: =B106-sum(C106:AG106) -> 5 | AJ106: =B106-AH106 -> 5 | AK106: =AJ106-AI106 -> 0 | AL106: ='MASTER STOCK'!I103 -> 58000 | AM106: ='MASTER STOCK'!L103 -> 73000 | AN106: =AH106*AM106 -> 0 | AO106: =AN106-(AH106*AL106) -> 0 | AP106: =AH106*AL106 -> 0
A107: ='MASTER STOCK'!F104 -> Hollow G Tube 20x40x0.4 | B107: ='JULI 25'!AJ107:AJ464 -> 20 | AD107: 2 | AH107: =SUM(C107:AG107) -> 2 | AI107: =B107-sum(C107:AG107) -> 18 | AJ107: =B107-AH107 -> 18 | AK107: =AJ107-AI107 -> 0 | AL107: ='MASTER STOCK'!I104 -> 21500 | AM107: ='MASTER STOCK'!L104 -> 25800 | AN107: =AH107*AM107 -> 51600 | AO107: =AN107-(AH107*AL107) -> 8600 | AP107: =AH107*AL107 -> 43000
A108: ='MASTER STOCK'!F105 -> Hollow G Tube 40x40x0.4 | B108: ='JULI 25'!AJ108:AJ465 -> 10 | AH108: =SUM(C108:AG108) -> 0 | AI108: =B108-sum(C108:AG108) -> 10 | AJ108: =B108-AH108 -> 10 | AK108: =AJ108-AI108 -> 0 | AL108: ='MASTER STOCK'!I105 -> 28500 | AM108: ='MASTER STOCK'!L105 -> 34200 | AN108: =AH108*AM108 -> 0 | AO108: =AN108-(AH108*AL108) -> 0 | AP108: =AH108*AL108 -> 0
A109: ='MASTER STOCK'!F106 -> Reng Galvalum Kenana 0.45 (M) | B109: ='JULI 25'!AJ109:AJ466 -> 10 | AH109: =SUM(C109:AG109) -> 0 | AI109: =B109-sum(C109:AG109) -> 10 | AJ109: =B109-AH109 -> 10 | AK109: =AJ109-AI109 -> 0 | AL109: ='MASTER STOCK'!I106 -> 39000 | AM109: ='MASTER STOCK'!L106 -> 42900 | AN109: =AH109*AM109 -> 0 | AO109: =AN109-(AH109*AL109) -> 0 | AP109: =AH109*AL109 -> 0
A110: ='MASTER STOCK'!F107 -> C Truss Kencana 75x0.85 (0.75) MM | B110: ='JULI 25'!AJ110:AJ467 -> 10 | AH110: =SUM(C110:AG110) -> 0 | AI110: =B110-sum(C110:AG110) -> 10 | AJ110: =B110-AH110 -> 10 | AK110: =AJ110-AI110 -> 0 | AL110: ='MASTER STOCK'!I107 -> 85000 | AM110: ='MASTER STOCK'!L107 -> 93500 | AN110: =AH110*AM110 -> 0 | AO110: =AN110-(AH110*AL110) -> 0 | AP110: =AH110*AL110 -> 0
A111: ='MASTER STOCK'!F108 -> KAYU BALOK 4X6X4 | B111: ='JULI 25'!AJ111:AJ468 -> 12 | AH111: =SUM(C111:AG111) -> 0 | AI111: =B111-sum(C111:AG111) -> 12 | AJ111: =B111-AH111 -> 12 | AK111: =AJ111-AI111 -> 0 | AL111: ='MASTER STOCK'!I108 -> 39000 | AM111: ='MASTER STOCK'!L108 -> 42900 | AN111: =AH111*AM111 -> 0 | AO111: =AN111-(AH111*AL111) -> 0 | AP111: =AH111*AL111 -> 0
A112: ='MASTER STOCK'!F109 -> KAYU BALOK 3X5X4 | B112: ='JULI 25'!AJ112:AJ469 -> 10 | AH112: =SUM(C112:AG112) -> 0 | AI112: =B112-sum(C112:AG112) -> 10 | AJ112: =B112-AH112 -> 10 | AK112: =AJ112-AI112 -> 0 | AL112: ='MASTER STOCK'!I109 -> 24000 | AM112: ='MASTER STOCK'!L109 -> 26400 | AN112: =AH112*AM112 -> 0 | AO112: =AN112-(AH112*AL112) -> 0 | AP112: =AH112*AL112 -> 0
A113: ='MASTER STOCK'!F110 -> KAYU BALOK 2X3X4 | B113: ='JULI 25'!AJ113:AJ470 -> 25 | AH113: =SUM(C113:AG113) -> 0 | AI113: =B113-sum(C113:AG113) -> 25 | AJ113: =B113-AH113 -> 25 | AK113: =AJ113-AI113 -> 0 | AL113: ='MASTER STOCK'!I110 -> 9600 | AM113: ='MASTER STOCK'!L110 -> 10560 | AN113: =AH113*AM113 -> 0 | AO113: =AN113-(AH113*AL113) -> 0 | AP113: =AH113*AL113 -> 0
A114: ='MASTER STOCK'!F111 -> CANGKUL | B114: ='JULI 25'!AJ114:AJ471 -> 1 | AH114: =SUM(C114:AG114) -> 0 | AI114: =B114-sum(C114:AG114) -> 1 | AJ114: =B114-AH114 -> 1 | AK114: =AJ114-AI114 -> 0 | AL114: ='MASTER STOCK'!I111 -> 33580 | AM114: ='MASTER STOCK'!L111 -> 57086 | AN114: =AH114*AM114 -> 0 | AO114: =AN114-(AH114*AL114) -> 0 | AP114: =AH114*AL114 -> 0
A115: ='MASTER STOCK'!F112 -> SEKOP PASIR | B115: ='JULI 25'!AJ115:AJ472 -> 2 | AH115: =SUM(C115:AG115) -> 0 | AI115: =B115-sum(C115:AG115) -> 2 | AJ115: =B115-AH115 -> 2 | AK115: =AJ115-AI115 -> 0 | AL115: ='MASTER STOCK'!I112 -> 20000 | AM115: ='MASTER STOCK'!L112 -> 34000 | AN115: =AH115*AM115 -> 0 | AO115: =AN115-(AH115*AL115) -> 0 | AP115: =AH115*AL115 -> 0
A116: ='MASTER STOCK'!F113 -> Baut Drilling Galvalum Baja Ringan 100 Pcs Per Plastik - WL 12x50 100Pcs | B116: ='JULI 25'!AJ116:AJ473 -> 100 | AH116: =SUM(C116:AG116) -> 0 | AI116: =B116-sum(C116:AG116) -> 100 | AJ116: =B116-AH116 -> 100 | AK116: =AJ116-AI116 -> 0 | AL116: ='MASTER STOCK'!I113 -> 250 | AM116: ='MASTER STOCK'!L113 -> 500 | AN116: =AH116*AM116 -> 0 | AO116: =AN116-(AH116*AL116) -> 0 | AP116: =AH116*AL116 -> 0
A117: ='MASTER STOCK'!F114 -> Baut Drilling Galvalum Baja Ringan 100 Pcs Per Plastik - WL 12x60 100Pcs | B117: ='JULI 25'!AJ117:AJ474 -> 100 | AH117: =SUM(C117:AG117) -> 0 | AI117: =B117-sum(C117:AG117) -> 100 | AJ117: =B117-AH117 -> 100 | AK117: =AJ117-AI117 -> 0 | AL117: ='MASTER STOCK'!I114 -> 300 | AM117: ='MASTER STOCK'!L114 -> 600 | AN117: =AH117*AM117 -> 0 | AO117: =AN117-(AH117*AL117) -> 0 | AP117: =AH117*AL117 -> 0
A118: ='MASTER STOCK'!F115 -> Baut Drilling Galvalum Baja Ringan 100 Pcs Per Plastik - WL 12x30 100Pcs | B118: ='JULI 25'!AJ118:AJ475 -> 100 | AH118: =SUM(C118:AG118) -> 0 | AI118: =B118-sum(C118:AG118) -> 100 | AJ118: =B118-AH118 -> 100 | AK118: =AJ118-AI118 -> 0 | AL118: ='MASTER STOCK'!I115 -> 170 | AM118: ='MASTER STOCK'!L115 -> 340 | AN118: =AH118*AM118 -> 0 | AO118: =AN118-(AH118*AL118) -> 0 | AP118: =AH118*AL118 -> 0
A119: ='MASTER STOCK'!F116 -> Baut Drilling Galvalum Baja Ringan 100 Pcs Per Plastik - WL 12x40 100Pcs | B119: ='JULI 25'!AJ119:AJ476 -> 100 | AH119: =SUM(C119:AG119) -> 0 | AI119: =B119-sum(C119:AG119) -> 100 | AJ119: =B119-AH119 -> 100 | AK119: =AJ119-AI119 -> 0 | AL119: ='MASTER STOCK'!I116 -> 220 | AM119: ='MASTER STOCK'!L116 -> 440 | AN119: =AH119*AM119 -> 0 | AO119: =AN119-(AH119*AL119) -> 0 | AP119: =AH119*AL119 -> 0
A120: ='MASTER STOCK'!F117 -> Baut Drilling Galvalum Baja Ringan 100 Pcs Per Plastik - WL 12x20 100Pcs | B120: ='JULI 25'!AJ120:AJ477 -> 100 | AH120: =SUM(C120:AG120) -> 0 | AI120: =B120-sum(C120:AG120) -> 100 | AJ120: =B120-AH120 -> 100 | AK120: =AJ120-AI120 -> 0 | AL120: ='MASTER STOCK'!I117 -> 150 | AM120: ='MASTER STOCK'!L117 -> 300 | AN120: =AH120*AM120 -> 0 | AO120: =AN120-(AH120*AL120) -> 0 | AP120: =AH120*AL120 -> 0
A121: ='MASTER STOCK'!F118 -> Batu Kumbung | B121: ='JULI 25'!AJ121:AJ478 -> 570 | Y121: 42 | AH121: =SUM(C121:AG121) -> 42 | AI121: =B121-sum(C121:AG121) -> 528 | AJ121: =B121-AH121 -> 528 | AK121: =AJ121-AI121 -> 0 | AL121: ='MASTER STOCK'!I118 -> 8000 | AM121: ='MASTER STOCK'!L118 -> 12000 | AN121: =AH121*AM121 -> 504000 | AO121: =AN121-(AH121*AL121) -> 168000 | AP121: =AH121*AL121 -> 336000
A122: ='MASTER STOCK'!F119 -> Triplek 8m sengon | B122: ='JULI 25'!AJ122:AJ479 -> 5 | AH122: =SUM(C122:AG122) -> 0 | AI122: =B122-sum(C122:AG122) -> 5 | AJ122: =B122-AH122 -> 5 | AK122: =AJ122-AI122 -> 0 | AL122: ='MASTER STOCK'!I119 -> 67000 | AM122: ='MASTER STOCK'!L119 -> 70350 | AN122: =AH122*AM122 -> 0 | AO122: =AN122-(AH122*AL122) -> 0 | AP122: =AH122*AL122 -> 0
A123: ='MASTER STOCK'!F120 -> Triplek 6m sengon | B123: ='JULI 25'!AJ123:AJ480 -> 10 | AH123: =SUM(C123:AG123) -> 0 | AI123: =B123-sum(C123:AG123) -> 10 | AJ123: =B123-AH123 -> 10 | AK123: =AJ123-AI123 -> 0 | AL123: ='MASTER STOCK'!I120 -> 56500 | AM123: ='MASTER STOCK'!L120 -> 59325 | AN123: =AH123*AM123 -> 0 | AO123: =AN123-(AH123*AL123) -> 0 | AP123: =AH123*AL123 -> 0
A124: ='MASTER STOCK'!F121 -> Triplek 3m sengon | B124: ='JULI 25'!AJ124:AJ481 -> 10 | AH124: =SUM(C124:AG124) -> 0 | AI124: =B124-sum(C124:AG124) -> 10 | AJ124: =B124-AH124 -> 10 | AK124: =AJ124-AI124 -> 0 | AL124: ='MASTER STOCK'!I121 -> 38500 | AM124: ='MASTER STOCK'!L121 -> 40425 | AN124: =AH124*AM124 -> 0 | AO124: =AN124-(AH124*AL124) -> 0 | AP124: =AH124*AL124 -> 0
A125: ='MASTER STOCK'!F122 -> Semen Gresik | B125: ='JULI 25'!AJ125:AJ482 -> 105 | T125: 1 | AH125: =SUM(C125:AG125) -> 1 | AI125: =B125-sum(C125:AG125) -> 104 | AJ125: =B125-AH125 -> 104 | AK125: =AJ125-AI125 -> 0 | AL125: ='MASTER STOCK'!I122 -> 55000 | AM125: ='MASTER STOCK'!L122 -> 56485 | AN125: =AH125*AM125 -> 56485 | AO125: =AN125-(AH125*AL125) -> 1485 | AP125: =AH125*AL125 -> 55000
A126: ='MASTER STOCK'!F123 -> Kapur | B126: ='JULI 25'!AJ126:AJ483 -> 100 | AH126: =SUM(C126:AG126) -> 0 | AI126: =B126-sum(C126:AG126) -> 100 | AJ126: =B126-AH126 -> 100 | AK126: =AJ126-AI126 -> 0 | AL126: ='MASTER STOCK'!I123 -> 17000 | AM126: ='MASTER STOCK'!L123 -> 18700 | AN126: =AH126*AM126 -> 0 | AO126: =AN126-(AH126*AL126) -> 0 | AP126: =AH126*AL126 -> 0
A127: ='MASTER STOCK'!F124 -> Pasir | B127: ='JULI 25'!AJ127:AJ484 -> 1 | AH127: =SUM(C127:AG127) -> 0 | AI127: =B127-sum(C127:AG127) -> 1 | AJ127: =B127-AH127 -> 1 | AK127: =AJ127-AI127 -> 0 | AL127: ='MASTER STOCK'!I124 -> 1000000 | AM127: ='MASTER STOCK'!L124 -> 1100000 | AN127: =AH127*AM127 -> 0 | AO127: =AN127-(AH127*AL127) -> 0 | AP127: =AH127*AL127 -> 0
A128: ='MASTER STOCK'!F125 -> Stop kontak 1 lubang | B128: ='JULI 25'!AJ128:AJ485 -> 5 | AH128: =SUM(C128:AG128) -> 0 | AI128: =B128-sum(C128:AG128) -> 5 | AJ128: =B128-AH128 -> 5 | AK128: =AJ128-AI128 -> 0 | AL128: ='MASTER STOCK'!I125 -> 4125 | AM128: ='MASTER STOCK'!L125 -> 416625 | AN128: =AH128*AM128 -> 0 | AO128: =AN128-(AH128*AL128) -> 0 | AP128: =AH128*AL128 -> 0
A129: ='MASTER STOCK'!F126 -> Stop kontak 2 lubang | B129: ='JULI 25'!AJ129:AJ486 -> 5 | AH129: =SUM(C129:AG129) -> 0 | AI129: =B129-sum(C129:AG129) -> 5 | AJ129: =B129-AH129 -> 5 | AK129: =AJ129-AI129 -> 0 | AL129: ='MASTER STOCK'!I126 -> 5250 | AM129: ='MASTER STOCK'!L126 -> 8925 | AN129: =AH129*AM129 -> 0 | AO129: =AN129-(AH129*AL129) -> 0 | AP129: =AH129*AL129 -> 0
A130: ='MASTER STOCK'!F127 -> Stop kontak 3 lubang | B130: ='JULI 25'!AJ130:AJ487 -> 5 | AH130: =SUM(C130:AG130) -> 0 | AI130: =B130-sum(C130:AG130) -> 5 | AJ130: =B130-AH130 -> 5 | AK130: =AJ130-AI130 -> 0 | AL130: ='MASTER STOCK'!I127 -> 6750 | AM130: ='MASTER STOCK'!L127 -> 14000 | AN130: =AH130*AM130 -> 0 | AO130: =AN130-(AH130*AL130) -> 0 | AP130: =AH130*AL130 -> 0
A131: ='MASTER STOCK'!F128 -> Stop kontak 4 lubang | B131: ='JULI 25'!AJ131:AJ488 -> 5 | AH131: =SUM(C131:AG131) -> 0 | AI131: =B131-sum(C131:AG131) -> 5 | AJ131: =B131-AH131 -> 5 | AK131: =AJ131-AI131 -> 0 | AL131: ='MASTER STOCK'!I128 -> 8100 | AM131: ='MASTER STOCK'!L128 -> 16000 | AN131: =AH131*AM131 -> 0 | AO131: =AN131-(AH131*AL131) -> 0 | AP131: =AH131*AL131 -> 0
A132: ='MASTER STOCK'!F129 -> Stop kontak 5 lubang | B132: ='JULI 25'!AJ132:AJ489 -> 5 | AH132: =SUM(C132:AG132) -> 0 | AI132: =B132-sum(C132:AG132) -> 5 | AJ132: =B132-AH132 -> 5 | AK132: =AJ132-AI132 -> 0 | AL132: ='MASTER STOCK'!I129 -> 9750 | AM132: ='MASTER STOCK'!L129 -> 16575 | AN132: =AH132*AM132 -> 0 | AO132: =AN132-(AH132*AL132) -> 0 | AP132: =AH132*AL132 -> 0
A133: ='MASTER STOCK'!F130 -> Baterai ABC | B133: ='JULI 25'!AJ133:AJ490 -> 24 | AH133: =SUM(C133:AG133) -> 0 | AI133: =B133-sum(C133:AG133) -> 24 | AJ133: =B133-AH133 -> 24 | AK133: =AJ133-AI133 -> 0 | AL133: ='MASTER STOCK'!I130 -> 2600 | AM133: ='MASTER STOCK'!L130 -> 3900 | AN133: =AH133*AM133 -> 0 | AO133: =AN133-(AH133*AL133) -> 0 | AP133: =AH133*AL133 -> 0
...

Sheet SEP 25
A1: LAPORAN PENJUALAN BULANAN | AQ1: 45901
A2: NAMA BARANG | B2: STOK AWAL | C2: =UPPER("HARI / BULAN : " & TEXT(AQ1, "MMMM YYYY")) -> HARI / BULAN : SEPTEMBER 2025
C3: =TEXT(C4,"dddd") -> Senin | D3: =TEXT(D4,"dddd") -> Selasa | E3: =TEXT(E4,"dddd") -> Rabu | F3: =TEXT(F4,"dddd") -> Kamis | G3: =TEXT(G4,"dddd") -> Jumat | H3: =TEXT(H4,"dddd") -> Sabtu | I3: =TEXT(I4,"dddd") -> Minggu | J3: =TEXT(J4,"dddd") -> Senin | ... AG3: =TEXT(AG4,"dddd") | AH3: TOTAL | AI3: STOCK | AJ3: SYSTEM | AK3: KET/SELISIH | AL3: HARGA BELI | AM3: HARGA JUAL | AN3: OMSET | AO3: PROFIT | AP3: TOTAL MODAL
C4: =AQ1 -> 45901 | D4: =IF(AND(MONTH(C4+1) = MONTH(C4), C4<>""),C4 + 1, "") -> 45902 | E4: =IF(AND(MONTH(D4+1) = MONTH(D4), D4<>""),D4 + 1, "") -> 45903 | F4: =IF(AND(MONTH(E4+1) = MONTH(E4), E4<>""),E4 + 1, "") -> 45904 | G4: =IF(AND(MONTH(F4+1) = MONTH(F4), F4<>""),F4 + 1, "") -> 45905 | H4: =IF(AND(MONTH(G4+1) = MONTH(G4), G4<>""),G4 + 1, "") -> 45906 | I4: =IF(AND(MONTH(H4+1) = MONTH(H4), H4<>""),H4 + 1, "") -> 45907 | J4: =IF(AND(MONTH(I4+1) = MONTH(I4), I4<>""),I4 + 1, "") -> 45908 | K4: =IF(AND(MONTH(J4+1) = MONTH(J4), J4<>""),J4 + 1, "") -> 45909 | ... AG4: =IF(AND(MONTH(AF4+1) = MONTH(AF4), AF4<>""),AF4 + 1, "")
A5: ='MASTER STOCK'!F2 -> Fitting Gantung | B5: ='AGS 25'!AJ5:AJ367 -> 12 | G5: 2 | AH5: =SUM(C5:AG5) -> 2 | AI5: 0 | AJ5: =B5-AH5 -> 10 | AK5: =AJ5-AI5 -> 10 | AL5: ='MASTER STOCK'!I2 -> 1400 | AM5: ='MASTER STOCK'!L2 -> 1820 | AN5: =AH5*AM5 -> 3640 | AO5: =AN5-(AH5*AL5) -> 840 | AP5: =AH5*AL5 -> 2800
A6: ='MASTER STOCK'!F3 -> Colokan T | B6: ='AGS 25'!AJ6:AJ368 -> 12 | H6: 1 | AH6: =SUM(C6:AG6) -> 1 | AI6: 0 | AJ6: =B6-AH6 -> 11 | AK6: =AJ6-AI6 -> 11 | AL6: ='MASTER STOCK'!I3 -> 3000 | AM6: ='MASTER STOCK'!L3 -> 3900 | AN6: =AH6*AM6 -> 3900 | AO6: =AN6-(AH6*AL6) -> 900 | AP6: =AH6*AL6 -> 3000
A7: ='MASTER STOCK'!F4 -> Steker Bulat | B7: ='AGS 25'!AJ7:AJ369 -> 12 | AH7: =SUM(C7:AG7) -> 0 | AI7: 0 | AJ7: =B7-AH7 -> 12 | AK7: =AJ7-AI7 -> 12 | AL7: ='MASTER STOCK'!I4 -> 3000 | AM7: ='MASTER STOCK'!L4 -> 6000 | AN7: =AH7*AM7 -> 0 | AO7: =AN7-(AH7*AL7) -> 0 | AP7: =AH7*AL7 -> 0
A8: ='MASTER STOCK'!F5 -> Steker Gepeng | B8: ='AGS 25'!AJ8:AJ370 -> 12 | AH8: =SUM(C8:AG8) -> 0 | AI8: 0 | AJ8: =B8-AH8 -> 12 | AK8: =AJ8-AI8 -> 12 | AL8: ='MASTER STOCK'!I5 -> 1100 | AM8: ='MASTER STOCK'!L5 -> 1430 | AN8: =AH8*AM8 -> 0 | AO8: =AN8-(AH8*AL8) -> 0 | AP8: =AH8*AL8 -> 0
A9: ='MASTER STOCK'!F6 -> Saklar Gantung Putih jumbo | B9: ='AGS 25'!AJ9:AJ371 -> 12 | G9: 2 | V9: 1 | AH9: =SUM(C9:AG9) -> 3 | AI9: 0 | AJ9: =B9-AH9 -> 9 | AK9: =AJ9-AI9 -> 9 | AL9: ='MASTER STOCK'!I6 -> 2250 | AM9: ='MASTER STOCK'!L6 -> 4000 | AN9: =AH9*AM9 -> 12000 | AO9: =AN9-(AH9*AL9) -> 5250 | AP9: =AH9*AL9 -> 6750
A10: ='MASTER STOCK'!F7 -> Saklar Gantung Hitam | B10: ='AGS 25'!AJ10:AJ372 -> 12 | AH10: =SUM(C10:AG10) -> 0 | AI10: 0 | AJ10: =B10-AH10 -> 12 | AK10: =AJ10-AI10 -> 12 | AL10: ='MASTER STOCK'!I7 -> 1850 | AM10: ='MASTER STOCK'!L7 -> 4000 | AN10: =AH10*AM10 -> 0 | AO10: =AN10-(AH10*AL10) -> 0 | AP10: =AH10*AL10 -> 0
A11: ='MASTER STOCK'!F8 -> Isolasi Hitam National | B11: ='AGS 25'!AJ11:AJ373 -> 20 | G11: 1 | AH11: =SUM(C11:AG11) -> 1 | AI11: 0 | AJ11: =B11-AH11 -> 19 | AK11: =AJ11-AI11 -> 19 | AL11: ='MASTER STOCK'!I8 -> 5150 | AM11: ='MASTER STOCK'!L8 -> 7982.5 | AN11: =AH11*AM11 -> 7982.5 | AO11: =AN11-(AH11*AL11) -> 2832.5 | AP11: =AH11*AL11 -> 5150
A12: ='MASTER STOCK'!F9 -> Lem PVC Isarplas 40gram | B12: ='AGS 25'!AJ12:AJ374 -> 23 | Y12: 1 | AH12: =SUM(C12:AG12) -> 1 | AI12: 0 | AJ12: =B12-AH12 -> 22 | AK12: =AJ12-AI12 -> 22 | AL12: ='MASTER STOCK'!I9 -> 6900 | AM12: ='MASTER STOCK'!L9 -> 9500 | AN12: =AH12*AM12 -> 9500 | AO12: =AN12-(AH12*AL12) -> 2600 | AP12: =AH12*AL12 -> 6900
A13: ='MASTER STOCK'!F10 -> Isolasi Kran air onda | B13: ='AGS 25'!AJ13:AJ375 -> 60 | AH13: =SUM(C13:AG13) -> 0 | AI13: 0 | AJ13: =B13-AH13 -> 60 | AK13: =AJ13-AI13 -> 60 | AL13: ='MASTER STOCK'!I10 -> 1150 | AM13: ='MASTER STOCK'!L10 -> 1495 | AN13: =AH13*AM13 -> 0 | AO13: =AN13-(AH13*AL13) -> 0 | AP13: =AH13*AL13 -> 0
A14: ='MASTER STOCK'!F11 -> Tutup Pipa 3/4" | B14: ='AGS 25'!AJ14:AJ376 -> 50 | AH14: =SUM(C14:AG14) -> 0 | AI14: 0 | AJ14: =B14-AH14 -> 50 | AK14: =AJ14-AI14 -> 50 | AL14: ='MASTER STOCK'!I11 -> 850 | AM14: ='MASTER STOCK'!L11 -> 1275 | AN14: =AH14*AM14 -> 0 | AO14: =AN14-(AH14*AL14) -> 0 | AP14: =AH14*AL14 -> 0
A15: ='MASTER STOCK'!F12 -> Fitting lampu gantung outdoor (10 m 5 fitting) | B15: ='AGS 25'!AJ15:AJ377 -> 1 | AH15: =SUM(C15:AG15) -> 0 | AI15: 0 | AJ15: =B15-AH15 -> 1 | AK15: =AJ15-AI15 -> 1 | AL15: ='MASTER STOCK'!I12 -> 38000 | AM15: ='MASTER STOCK'!L12 -> 49400 | AN15: =AH15*AM15 -> 0 | AO15: =AN15-(AH15*AL15) -> 0 | AP15: =AH15*AL15 -> 0
A16: ='MASTER STOCK'!F13 -> Obeng karet 4" plus | B16: ='AGS 25'!AJ16:AJ378 -> 5 | AH16: =SUM(C16:AG16) -> 0 | AI16: 0 | AJ16: =B16-AH16 -> 5 | AK16: =AJ16-AI16 -> 5 | AL16: ='MASTER STOCK'!I13 -> 5500 | AM16: ='MASTER STOCK'!L13 -> 7150 | AN16: =AH16*AM16 -> 0 | AO16: =AN16-(AH16*AL16) -> 0 | AP16: =AH16*AL16 -> 0
A17: ='MASTER STOCK'!F14 -> Obeng karet 4" minus | B17: ='AGS 25'!AJ17:AJ379 -> 4 | AH17: =SUM(C17:AG17) -> 0 | AI17: 0 | AJ17: =B17-AH17 -> 4 | AK17: =AJ17-AI17 -> 4 | AL17: ='MASTER STOCK'!I14 -> 5500 | AM17: ='MASTER STOCK'!L14 -> 7150 | AN17: =AH17*AM17 -> 0 | AO17: =AN17-(AH17*AL17) -> 0 | AP17: =AH17*AL17 -> 0
A18: ='MASTER STOCK'!F15 -> Obeng karet 6" plus | B18: ='AGS 25'!AJ18:AJ380 -> 5 | AH18: =SUM(C18:AG18) -> 0 | AI18: 0 | AJ18: =B18-AH18 -> 5 | AK18: =AJ18-AI18 -> 5 | AL18: ='MASTER STOCK'!I15 -> 7000 | AM18: ='MASTER STOCK'!L15 -> 9100 | AN18: =AH18*AM18 -> 0 | AO18: =AN18-(AH18*AL18) -> 0 | AP18: =AH18*AL18 -> 0
A19: ='MASTER STOCK'!F16 -> Obeng karet 6" Minus | B19: ='AGS 25'!AJ19:AJ381 -> 5 | AH19: =SUM(C19:AG19) -> 0 | AI19: 0 | AJ19: =B19-AH19 -> 5 | AK19: =AJ19-AI19 -> 5 | AL19: ='MASTER STOCK'!I16 -> 7000 | AM19: ='MASTER STOCK'!L16 -> 9100 | AN19: =AH19*AM19 -> 0 | AO19: =AN19-(AH19*AL19) -> 0 | AP19: =AH19*AL19 -> 0
A20: ='MASTER STOCK'!F17 -> Kabel Awg 24 Double 2x18 merah hitam | B20: ='AGS 25'!AJ20:AJ382 -> 2 | AH20: =SUM(C20:AG20) -> 0 | AI20: 0 | AJ20: =B20-AH20 -> 2 | AK20: =AJ20-AI20 -> 2 | AL20: ='MASTER STOCK'!I17 -> 106500 | AM20: ='MASTER STOCK'!L17 -> 181050 | AN20: =AH20*AM20 -> 0 | AO20: =AN20-(AH20*AL20) -> 0 | AP20: =AH20*AL20 -> 0
A21: ='MASTER STOCK'!F18 -> Kabel bintik serabut tembaga motor mobil 20mx0.5mm/0,85mm merah 0,5mm | B21: ='AGS 25'!AJ21:AJ383 -> 2 | Q21: 1 | AH21: =SUM(C21:AG21) -> 1 | AI21: 0 | AJ21: =B21-AH21 -> 1 | AK21: =AJ21-AI21 -> 1 | AL21: ='MASTER STOCK'!I18 -> 33700 | AM21: ='MASTER STOCK'!L18 -> 57290 | AN21: =AH21*AM21 -> 57290 | AO21: =AN21-(AH21*AL21) -> 23590 | AP21: =AH21*AL21 -> 33700
A22: ='MASTER STOCK'!F19 -> Kabel bintik serabut tembaga motor mobil 20mx0.5mm/0,85mm hitam 0,5mm | B22: ='AGS 25'!AJ22:AJ384 -> 2 | Q22: 1 | AH22: =SUM(C22:AG22) -> 1 | AI22: 0 | AJ22: =B22-AH22 -> 1 | AK22: =AJ22-AI22 -> 1 | AL22: ='MASTER STOCK'!I19 -> 33700 | AM22: ='MASTER STOCK'!L19 -> 57290 | AN22: =AH22*AM22 -> 57290 | AO22: =AN22-(AH22*AL22) -> 23590 | AP22: =AH22*AL22 -> 33700
A23: ='MASTER STOCK'!F20 -> Mata Gerinda keramik 4 inch kering | B23: ='AGS 25'!AJ23:AJ385 -> 5 | AH23: =SUM(C23:AG23) -> 0 | AI23: 0 | AJ23: =B23-AH23 -> 5 | AK23: =AJ23-AI23 -> 5 | AL23: ='MASTER STOCK'!I20 -> 12000 | AM23: ='MASTER STOCK'!L20 -> 18000 | AN23: =AH23*AM23 -> 0 | AO23: =AN23-(AH23*AL23) -> 0 | AP23: =AH23*AL23 -> 0
A24: ='MASTER STOCK'!F21 -> Kabel tunggal serabut 0.8mmx25m biru 25m | B24: ='AGS 25'!AJ24:AJ386 -> 1 | AH24: =SUM(C24:AG24) -> 0 | AI24: 0 | AJ24: =B24-AH24 -> 1 | AK24: =AJ24-AI24 -> 1 | AL24: ='MASTER STOCK'!I21 -> 17500 | AM24: ='MASTER STOCK'!L21 -> 29750 | AN24: =AH24*AM24 -> 0 | AO24: =AN24-(AH24*AL24) -> 0 | AP24: =AH24*AL24 -> 0
A25: ='MASTER STOCK'!F22 -> Kabel tunggal serabut 0.8mmx25m Hitam 25m | B25: ='AGS 25'!AJ25:AJ387 -> 1 | AH25: =SUM(C25:AG25) -> 0 | AI25: 0 | AJ25: =B25-AH25 -> 1 | AK25: =AJ25-AI25 -> 1 | AL25: ='MASTER STOCK'!I22 -> 17500 | AM25: ='MASTER STOCK'!L22 -> 29750 | AN25: =AH25*AM25 -> 0 | AO25: =AN25-(AH25*AL25) -> 0 | AP25: =AH25*AL25 -> 0
A26: ='MASTER STOCK'!F23 -> Lampu Hias LED strip USB 10m+adaptor | B26: ='AGS 25'!AJ26:AJ388 -> 2 | AH26: =SUM(C26:AG26) -> 0 | AI26: 0 | AJ26: =B26-AH26 -> 2 | AK26: =AJ26-AI26 -> 2 | AL26: ='MASTER STOCK'!I23 -> 50000 | AM26: ='MASTER STOCK'!L23 -> 65000 | AN26: =AH26*AM26 -> 0 | AO26: =AN26-(AH26*AL26) -> 0 | AP26: =AH26*AL26 -> 0
A27: ='MASTER STOCK'!F24 -> Lampu LED strip outdoor rainbow 10m +adaptor | B27: ='AGS 25'!AJ27:AJ389 -> 5 | AH27: =SUM(C27:AG27) -> 0 | AI27: 0 | AJ27: =B27-AH27 -> 5 | AK27: =AJ27-AI27 -> 5 | AL27: ='MASTER STOCK'!I24 -> 27000 | AM27: ='MASTER STOCK'!L24 -> 35100 | AN27: =AH27*AM27 -> 0 | AO27: =AN27-(AH27*AL27) -> 0 | AP27: =AH27*AL27 -> 0
A28: ='MASTER STOCK'!F25 -> Lampu LED strip outdoor merah putih 10m +adaptor | B28: ='AGS 25'!AJ28:AJ390 -> 4 | AH28: =SUM(C28:AG28) -> 0 | AI28: 0 | AJ28: =B28-AH28 -> 4 | AK28: =AJ28-AI28 -> 4 | AL28: ='MASTER STOCK'!I25 -> 30000 | AM28: ='MASTER STOCK'!L25 -> 40500 | AN28: =AH28*AM28 -> 0 | AO28: =AN28-(AH28*AL28) -> 0 | AP28: =AH28*AL28 -> 0
A29: ='MASTER STOCK'!F26 -> Lampu tumbler 10m (rainbow) | B29: ='AGS 25'!AJ29:AJ391 -> 5 | AH29: =SUM(C29:AG29) -> 0 | AI29: 0 | AJ29: =B29-AH29 -> 5 | AK29: =AJ29-AI29 -> 5 | AL29: ='MASTER STOCK'!I26 -> 11000 | AM29: ='MASTER STOCK'!L26 -> 14300 | AN29: =AH29*AM29 -> 0 | AO29: =AN29-(AH29*AL29) -> 0 | AP29: =AH29*AL29 -> 0
A30: ='MASTER STOCK'!F27 -> WD Gerinda potong besi | B30: ='AGS 25'!AJ30:AJ392 -> 58 | AH30: =SUM(C30:AG30) -> 0 | AI30: 0 | AJ30: =B30-AH30 -> 58 | AK30: =AJ30-AI30 -> 58 | AL30: ='MASTER STOCK'!I27 -> 2900 | AM30: ='MASTER STOCK'!L27 -> 5000 | AN30: =AH30*AM30 -> 0 | AO30: =AN30-(AH30*AL30) -> 0 | AP30: =AH30*AL30 -> 0
A31: ='MASTER STOCK'!F28 -> Meteran karet 7,5m (merk HPP) | B31: ='AGS 25'!AJ31:AJ393 -> 3 | AH31: =SUM(C31:AG31) -> 0 | AI31: 0 | AJ31: =B31-AH31 -> 3 | AK31: =AJ31-AI31 -> 3 | AL31: ='MASTER STOCK'!I28 -> 12800 | AM31: ='MASTER STOCK'!L28 -> 16640 | AN31: =AH31*AM31 -> 0 | AO31: =AN31-(AH31*AL31) -> 0 | AP31: =AH31*AL31 -> 0
A32: ='MASTER STOCK'!F29 -> Meteran karet 5m (merk VPR) | B32: ='AGS 25'!AJ32:AJ394 -> 3 | C32: 1 | AH32: =SUM(C32:AG32) -> 1 | AI32: 0 | AJ32: =B32-AH32 -> 2 | AK32: =AJ32-AI32 -> 2 | AL32: ='MASTER STOCK'!I29 -> 7000 | AM32: ='MASTER STOCK'!L29 -> 9100 | AN32: =AH32*AM32 -> 9100 | AO32: =AN32-(AH32*AL32) -> 2100 | AP32: =AH32*AL32 -> 7000
A33: ='MASTER STOCK'!F30 -> Kuas cat 2 1/2" (merk MDN) | B33: ='AGS 25'!AJ33:AJ395 -> 5 | AH33: =SUM(C33:AG33) -> 0 | AI33: 0 | AJ33: =B33-AH33 -> 5 | AK33: =AJ33-AI33 -> 5 | AL33: ='MASTER STOCK'!I30 -> 5300 | AM33: ='MASTER STOCK'!L30 -> 6890 | AN33: =AH33*AM33 -> 0 | AO33: =AN33-(AH33*AL33) -> 0 | AP33: =AH33*AL33 -> 0
A34: ='MASTER STOCK'!F31 -> Kuas cat 2" (merk MDN) | B34: ='AGS 25'!AJ34:AJ396 -> 5 | AH34: =SUM(C34:AG34) -> 0 | AI34: 0 | AJ34: =B34-AH34 -> 5 | AK34: =AJ34-AI34 -> 5 | AL34: ='MASTER STOCK'!I31 -> 4400 | AM34: ='MASTER STOCK'!L31 -> 5720 | AN34: =AH34*AM34 -> 0 | AO34: =AN34-(AH34*AL34) -> 0 | AP34: =AH34*AL34 -> 0
A35: ='MASTER STOCK'!F32 -> Kuas cat 3" (merk MDN) | B35: ='AGS 25'!AJ35:AJ397 -> 4 | C35: 1 | AH35: =SUM(C35:AG35) -> 1 | AI35: 0 | AJ35: =B35-AH35 -> 3 | AK35: =AJ35-AI35 -> 3 | AL35: ='MASTER STOCK'!I32 -> 6300 | AM35: ='MASTER STOCK'!L32 -> 8190 | AN35: =AH35*AM35 -> 8190 | AO35: =AN35-(AH35*AL35) -> 1890 | AP35: =AH35*AL35 -> 6300
A36: ='MASTER STOCK'!F33 -> Kuas cat 1 1/2" (merk MDN) | B36: ='AGS 25'!AJ36:AJ398 -> 5 | AH36: =SUM(C36:AG36) -> 0 | AI36: 0 | AJ36: =B36-AH36 -> 5 | AK36: =AJ36-AI36 -> 5 | AL36: ='MASTER STOCK'!I33 -> 3400 | AM36: ='MASTER STOCK'!L33 -> 4420 | AN36: =AH36*AM36 -> 0 | AO36: =AN36-(AH36*AL36) -> 0 | AP36: =AH36*AL36 -> 0
A37: ='MASTER STOCK'!F34 -> Kuas cat 1" (merk MDN) | B37: ='AGS 25'!AJ37:AJ399 -> 4 | Q37: 1 | AH37: =SUM(C37:AG37) -> 1 | AI37: 0 | AJ37: =B37-AH37 -> 3 | AK37: =AJ37-AI37 -> 3 | AL37: ='MASTER STOCK'!I34 -> 2300 | AM37: ='MASTER STOCK'!L34 -> 2990 | AN37: =AH37*AM37 -> 2990 | AO37: =AN37-(AH37*AL37) -> 690 | AP37: =AH37*AL37 -> 2300
A38: ='MASTER STOCK'!F35 -> Kran PVC Tembok 3/4" | B38: ='AGS 25'!AJ38:AJ400 -> 24 | Q38: 4 | AA38: 1 | AH38: =SUM(C38:AG38) -> 5 | AI38: 0 | AJ38: =B38-AH38 -> 19 | AK38: =AJ38-AI38 -> 19 | AL38: ='MASTER STOCK'!I35 -> 4200 | AM38: ='MASTER STOCK'!L35 -> 6000 | AN38: =AH38*AM38 -> 30000 | AO38: =AN38-(AH38*AL38) -> 9000 | AP38: =AH38*AL38 -> 21000
A39: ='MASTER STOCK'!F36 -> Kran PVC Tembok 1/2" | B39: ='AGS 25'!AJ39:AJ401 -> 24 | AH39: =SUM(C39:AG39) -> 0 | AI39: 0 | AJ39: =B39-AH39 -> 24 | AK39: =AJ39-AI39 -> 24 | AL39: ='MASTER STOCK'!I36 -> 4200 | AM39: ='MASTER STOCK'!L36 -> 6000 | AN39: =AH39*AM39 -> 0 | AO39: =AN39-(AH39*AL39) -> 0 | AP39: =AH39*AL39 -> 0
A40: ='MASTER STOCK'!F37 -> Lampu bohlam inlite 5w Putih | B40: ='AGS 25'!AJ40:AJ402 -> 7 | C40: 1 | AH40: =SUM(C40:AG40) -> 1 | AI40: 0 | AJ40: =B40-AH40 -> 6 | AK40: =AJ40-AI40 -> 6 | AL40: ='MASTER STOCK'!I37 -> 13000 | AM40: ='MASTER STOCK'!L37 -> 18200 | AN40: =AH40*AM40 -> 18200 | AO40: =AN40-(AH40*AL40) -> 5200 | AP40: =AH40*AL40 -> 13000
A41: ='MASTER STOCK'!F38 -> Lampu bohlam inlite 7w Putih | B41: ='AGS 25'!AJ41:AJ403 -> 2 | AH41: =SUM(C41:AG41) -> 0 | AI41: 0 | AJ41: =B41-AH41 -> 2 | AK41: =AJ41-AI41 -> 2 | AL41: ='MASTER STOCK'!I38 -> 16200 | AM41: ='MASTER STOCK'!L38 -> 22680 | AN41: =AH41*AM41 -> 0 | AO41: =AN41-(AH41*AL41) -> 0 | AP41: =AH41*AL41 -> 0
A42: ='MASTER STOCK'!F39 -> Lampu bohlam inlite 15w Putih | B42: ='AGS 25'!AJ42:AJ404 -> 4 | C42: 1 | AH42: =SUM(C42:AG42) -> 1 | AI42: 0 | AJ42: =B42-AH42 -> 3 | AK42: =AJ42-AI42 -> 3 | AL42: ='MASTER STOCK'!I39 -> 28000 | AM42: ='MASTER STOCK'!L39 -> 39200 | AN42: =AH42*AM42 -> 39200 | AO42: =AN42-(AH42*AL42) -> 11200 | AP42: =AH42*AL42 -> 28000
A43: ='MASTER STOCK'!F40 -> Lampu bohlam inlite 12w Putih | B43: ='AGS 25'!AJ43:AJ405 -> 6 | C43: 1 | AH43: =SUM(C43:AG43) -> 1 | AI43: 0 | AJ43: =B43-AH43 -> 5 | AK43: =AJ43-AI43 -> 5 | AL43: ='MASTER STOCK'!I40 -> 25000 | AM43: ='MASTER STOCK'!L40 -> 30000 | AN43: =AH43*AM43 -> 30000 | AO43: =AN43-(AH43*AL43) -> 5000 | AP43: =AH43*AL43 -> 25000
A44: ='MASTER STOCK'!F41 -> Lampu tintin platinum LED 9w | B44: ='AGS 25'!AJ44:AJ406 -> 4 | AH44: =SUM(C44:AG44) -> 0 | AI44: 0 | AJ44: =B44-AH44 -> 4 | AK44: =AJ44-AI44 -> 4 | AL44: ='MASTER STOCK'!I41 -> 7000 | AM44: ='MASTER STOCK'!L41 -> 9800 | AN44: =AH44*AM44 -> 0 | AO44: =AN44-(AH44*AL44) -> 0 | AP44: =AH44*AL44 -> 0
A45: ='MASTER STOCK'!F42 -> Lampu tintin platinum LED 5w | B45: ='AGS 25'!AJ45:AJ407 -> 4 | AH45: =SUM(C45:AG45) -> 0 | AI45: 0 | AJ45: =B45-AH45 -> 4 | AK45: =AJ45-AI45 -> 4 | AL45: ='MASTER STOCK'!I42 -> 5000 | AM45: ='MASTER STOCK'!L42 -> 7000 | AN45: =AH45*AM45 -> 0 | AO45: =AN45-(AH45*AL45) -> 0 | AP45: =AH45*AL45 -> 0
A46: ='MASTER STOCK'!F43 -> Lampu tintin platinum LED 21w | B46: ='AGS 25'!AJ46:AJ408 -> 3 | AH46: =SUM(C46:AG46) -> 0 | AI46: 0 | AJ46: =B46-AH46 -> 3 | AK46: =AJ46-AI46 -> 3 | AL46: ='MASTER STOCK'!I43 -> 15500 | AM46: ='MASTER STOCK'!L43 -> 21700 | AN46: =AH46*AM46 -> 0 | AO46: =AN46-(AH46*AL46) -> 0 | AP46: =AH46*AL46 -> 0
A47: ='MASTER STOCK'!F44 -> Lampu tintin platinum LED 15w | B47: ='AGS 25'!AJ47:AJ409 -> 5 | AH47: =SUM(C47:AG47) -> 0 | AI47: 0 | AJ47: =B47-AH47 -> 5 | AK47: =AJ47-AI47 -> 5 | AL47: ='MASTER STOCK'!I44 -> 8800 | AM47: ='MASTER STOCK'!L44 -> 13000 | AN47: =AH47*AM47 -> 0 | AO47: =AN47-(AH47*AL47) -> 0 | AP47: =AH47*AL47 -> 0
A48: ='MASTER STOCK'!F45 -> Lampu tintin platinum LED 12w | B48: ='AGS 25'!AJ48:AJ410 -> 5 | AH48: =SUM(C48:AG48) -> 0 | AI48: 0 | AJ48: =B48-AH48 -> 5 | AK48: =AJ48-AI48 -> 5 | AL48: ='MASTER STOCK'!I45 -> 7800 | AM48: ='MASTER STOCK'!L45 -> 10920 | AN48: =AH48*AM48 -> 0 | AO48: =AN48-(AH48*AL48) -> 0 | AP48: =AH48*AL48 -> 0
A49: ='MASTER STOCK'!F46 -> Lampu tintin platinum LED 7w | B49: ='AGS 25'!AJ49:AJ411 -> 5 | AH49: =SUM(C49:AG49) -> 0 | AI49: 0 | AJ49: =B49-AH49 -> 5 | AK49: =AJ49-AI49 -> 5 | AL49: ='MASTER STOCK'!I46 -> 5800 | AM49: ='MASTER STOCK'!L46 -> 8120 | AN49: =AH49*AM49 -> 0 | AO49: =AN49-(AH49*AL49) -> 0 | AP49: =AH49*AL49 -> 0
A50: ='MASTER STOCK'!F47 -> Gergaji kayu (POPEYE) 18 inch | B50: ='AGS 25'!AJ50:AJ412 -> 4 | AH50: =SUM(C50:AG50) -> 0 | AI50: 0 | AJ50: =B50-AH50 -> 4 | AK50: =AJ50-AI50 -> 4 | AL50: ='MASTER STOCK'!I47 -> 15000 | AM50: ='MASTER STOCK'!L47 -> 19500 | AN50: =AH50*AM50 -> 0 | AO50: =AN50-(AH50*AL50) -> 0 | AP50: =AH50*AL50 -> 0
A51: ='MASTER STOCK'!F48 -> Kapi plamir plastik PVC 9" (23cm) | B51: ='AGS 25'!AJ51:AJ413 -> 10 | AH51: =SUM(C51:AG51) -> 0 | AI51: 0 | AJ51: =B51-AH51 -> 10 | AK51: =AJ51-AI51 -> 10 | AL51: ='MASTER STOCK'!I48 -> 2200 | AM51: ='MASTER STOCK'!L48 -> 3300 | AN51: =AH51*AM51 -> 0 | AO51: =AN51-(AH51*AL51) -> 0 | AP51: =AH51*AL51 -> 0
A52: ='MASTER STOCK'!F49 -> Kapi plamir plastik PVC 5" (12cm) | B52: ='AGS 25'!AJ52:AJ414 -> 5 | AH52: =SUM(C52:AG52) -> 0 | AI52: 0 | AJ52: =B52-AH52 -> 5 | AK52: =AJ52-AI52 -> 5 | AL52: ='MASTER STOCK'!I49 -> 1100 | AM52: ='MASTER STOCK'!L49 -> 1650 | AN52: =AH52*AM52 -> 0 | AO52: =AN52-(AH52*AL52) -> 0 | AP52: =AH52*AL52 -> 0
A53: ='MASTER STOCK'!F50 -> Kapi plamir plastik PVC 7" (18cm) | B53: ='AGS 25'!AJ53:AJ415 -> 10 | AH53: =SUM(C53:AG53) -> 0 | AI53: 0 | AJ53: =B53-AH53 -> 10 | AK53: =AJ53-AI53 -> 10 | AL53: ='MASTER STOCK'!I50 -> 1500 | AM53: ='MASTER STOCK'!L50 -> 2250 | AN53: =AH53*AM53 -> 0 | AO53: =AN53-(AH53*AL53) -> 0 | AP53: =AH53*AL53 -> 0
A54: ='MASTER STOCK'!F51 -> Tang Kombinasi karet 8" | B54: ='AGS 25'!AJ54:AJ416 -> 5 | AH54: =SUM(C54:AG54) -> 0 | AI54: 0 | AJ54: =B54-AH54 -> 5 | AK54: =AJ54-AI54 -> 5 | AL54: ='MASTER STOCK'!I51 -> 12000 | AM54: ='MASTER STOCK'!L51 -> 15600 | AN54: =AH54*AM54 -> 0 | AO54: =AN54-(AH54*AL54) -> 0 | AP54: =AH54*AL54 -> 0
A55: ='MASTER STOCK'!F52 -> Tang Kombinasi 8" | B55: ='AGS 25'!AJ55:AJ417 -> 5 | AH55: =SUM(C55:AG55) -> 0 | AI55: 0 | AJ55: =B55-AH55 -> 5 | AK55: =AJ55-AI55 -> 5 | AL55: ='MASTER STOCK'!I52 -> 12500 | AM55: ='MASTER STOCK'!L52 -> 16250 | AN55: =AH55*AM55 -> 0 | AO55: =AN55-(AH55*AL55) -> 0 | AP55: =AH55*AL55 -> 0
... A59: ='MASTER STOCK'!F56 -> Stop Kontak Hitam 2L 5M | B59: ='AGS 25'!AJ59:AJ421 -> 2 | AH59: =SUM(C59:AG59) -> 0 | AI59: 0 | AJ59: =B59-AH59 -> 2 | AK59: =AJ59-AI59 -> 2 | AL59: ='MASTER STOCK'!I56 -> 17000 | AM59: ='MASTER STOCK'!L56 -> 25500 | AN59: =AH59*AM59 -> 0 | AO59: =AN59-(AH59*AL59) -> 0 | AP59: =AH59*AL59 -> 0
A60: ='MASTER STOCK'!F57 -> Palu Konde besi cor gagang kayu ukuran 1LB | B60: ='AGS 25'!AJ60:AJ422 -> 3 | C60: 1 | AH60: =SUM(C60:AG60) -> 1 | AI60: 0 | AJ60: =B60-AH60 -> 2 | AK60: =AJ60-AI60 -> 2 | AL60: ='MASTER STOCK'!I57 -> 17000 | AM60: ='MASTER STOCK'!L57 -> 22100 | AN60: =AH60*AM60 -> 22100 | AO60: =AN60-(AH60*AL60) -> 5100 | AP60: =AH60*AL60 -> 17000
A61: ='MASTER STOCK'!F58 -> Lem kuning 100gr | B61: ='AGS 25'!AJ61:AJ423 -> 22 | D61: 1 | Q61: 1 | AA61: 2 | AH61: =SUM(C61:AG61) -> 4 | AI61: 0 | AJ61: =B61-AH61 -> 18 | AK61: =AJ61-AI61 -> 18 | AL61: ='MASTER STOCK'!I58 -> 10000 | AM61: ='MASTER STOCK'!L58 -> 15000 | AN61: =AH61*AM61 -> 60000 | AO61: =AN61-(AH61*AL61) -> 20000 | AP61: =AH61*AL61 -> 40000
A62: ='MASTER STOCK'!F59 -> Lem aica aibon kuning 125gr | B62: ='AGS 25'!AJ62:AJ424 -> 1 | AH62: =SUM(C62:AG62) -> 0 | AI62: 0 | AJ62: =B62-AH62 -> 1 | AK62: =AJ62-AI62 -> 1 | AL62: ='MASTER STOCK'!I59 -> 18200 | AM62: ='MASTER STOCK'!L59 -> 27300 | AN62: =AH62*AM62 -> 0 | AO62: =AN62-(AH62*AL62) -> 0 | AP62: =AH62*AL62 -> 0
A63: ='MASTER STOCK'!F60 -> Kuas 4" incco | B63: ='AGS 25'!AJ63:AJ425 -> 2 | AH63: =SUM(C63:AG63) -> 0 | AI63: 0 | AJ63: =B63-AH63 -> 2 | AK63: =AJ63-AI63 -> 2 | AL63: ='MASTER STOCK'!I60 -> 15000 | AM63: ='MASTER STOCK'!L60 -> 19500 | AN63: =AH63*AM63 -> 0 | AO63: =AN63-(AH63*AL63) -> 0 | AP63: =AH63*AL63 -> 0
A64: ='MASTER STOCK'!F61 -> Meteran Autostop Wilmer 5m*19mm | B64: ='AGS 25'!AJ64:AJ426 -> 2 | AH64: =SUM(C64:AG64) -> 0 | AI64: 0 | AJ64: =B64-AH64 -> 2 | AK64: =AJ64-AI64 -> 2 | AL64: ='MASTER STOCK'!I61 -> 25000 | AM64: ='MASTER STOCK'!L61 -> 30000 | AN64: =AH64*AM64 -> 0 | AO64: =AN64-(AH64*AL64) -> 0 | AP64: =AH64*AL64 -> 0
A65: ='MASTER STOCK'!F62 -> Precision S/Driver Obeng 6S DIY | B65: ='AGS 25'!AJ65:AJ427 -> 2 | AH65: =SUM(C65:AG65) -> 0 | AI65: 0 | AJ65: =B65-AH65 -> 2 | AK65: =AJ65-AI65 -> 2 | AL65: ='MASTER STOCK'!I62 -> 9500 | AM65: ='MASTER STOCK'!L62 -> 13300 | AN65: =AH65*AM65 -> 0 | AO65: =AN65-(AH65*AL65) -> 0 | AP65: =AH65*AL65 -> 0
A66: ='MASTER STOCK'!F63 -> Blades / Isi Cutter Besar DIY | B66: ='AGS 25'!AJ66:AJ428 -> 20 | AH66: =SUM(C66:AG66) -> 0 | AI66: 0 | AJ66: =B66-AH66 -> 20 | AK66: =AJ66-AI66 -> 20 | AL66: ='MASTER STOCK'!I63 -> 1150 | AM66: ='MASTER STOCK'!L63 -> 1495 | AN66: =AH66*AM66 -> 0 | AO66: =AN66-(AH66*AL66) -> 0 | AP66: =AH66*AL66 -> 0
A67: ='MASTER STOCK'!F64 -> Blades / Isi Cutter Kecil DIY | B67: ='AGS 25'!AJ67:AJ429 -> 20 | AH67: =SUM(C67:AG67) -> 0 | AI67: 0 | AJ67: =B67-AH67 -> 20 | AK67: =AJ67-AI67 -> 20 | AL67: ='MASTER STOCK'!I64 -> 700 | AM67: ='MASTER STOCK'!L64 -> 1050 | AN67: =AH67*AM67 -> 0 | AO67: =AN67-(AH67*AL67) -> 0 | AP67: =AH67*AL67 -> 0
A68: ='MASTER STOCK'!F65 -> Screwdriver / Obeng 4" isi 2 DIY | B68: ='AGS 25'!AJ68:AJ430 -> 2 | AH68: =SUM(C68:AG68) -> 0 | AI68: 0 | AJ68: =B68-AH68 -> 2 | AK68: =AJ68-AI68 -> 2 | AL68: ='MASTER STOCK'!I65 -> 12000 | AM68: ='MASTER STOCK'!L65 -> 15600 | AN68: =AH68*AM68 -> 0 | AO68: =AN68-(AH68*AL68) -> 0 | AP68: =AH68*AL68 -> 0
A69: ='MASTER STOCK'!F66 -> Test Pen DIY | B69: ='AGS 25'!AJ69:AJ431 -> 2 | AH69: =SUM(C69:AG69) -> 0 | AI69: 0 | AJ69: =B69-AH69 -> 2 | AK69: =AJ69-AI69 -> 2 | AL69: ='MASTER STOCK'!I66 -> 12000 | AM69: ='MASTER STOCK'!L66 -> 15600 | AN69: =AH69*AM69 -> 0 | AO69: =AN69-(AH69*AL69) -> 0 | AP69: =AH69*AL69 -> 0
A70: ='MASTER STOCK'!F67 -> Door Bolt / Selot Pintu DIY 4" | B70: ='AGS 25'!AJ70:AJ432 -> 3 | AH70: =SUM(C70:AG70) -> 0 | AI70: 0 | AJ70: =B70-AH70 -> 3 | AK70: =AJ70-AI70 -> 3 | AL70: ='MASTER STOCK'!I67 -> 7500 | AM70: ='MASTER STOCK'!L67 -> 9750 | AN70: =AH70*AM70 -> 0 | AO70: =AN70-(AH70*AL70) -> 0 | AP70: =AH70*AL70 -> 0
A71: ='MASTER STOCK'!F68 -> Door Bolt / Selot Pintu DIY 3" | B71: ='AGS 25'!AJ71:AJ433 -> 2 | AH71: =SUM(C71:AG71) -> 0 | AI71: 0 | AJ71: =B71-AH71 -> 2 | AK71: =AJ71-AI71 -> 2 | AL71: ='MASTER STOCK'!I68 -> 10500 | AM71: ='MASTER STOCK'!L68 -> 13650 | AN71: =AH71*AM71 -> 0 | AO71: =AN71-(AH71*AL71) -> 0 | AP71: =AH71*AL71 -> 0
A72: ='MASTER STOCK'!F69 -> Kuas 2" incco | B72: ='AGS 25'!AJ72:AJ434 -> 3 | AH72: =SUM(C72:AG72) -> 0 | AI72: 0 | AJ72: =B72-AH72 -> 3 | AK72: =AJ72-AI72 -> 3 | AL72: ='MASTER STOCK'!I69 -> 7000 | AM72: ='MASTER STOCK'!L69 -> 9100 | AN72: =AH72*AM72 -> 0 | AO72: =AN72-(AH72*AL72) -> 0 | AP72: =AH72*AL72 -> 0
A73: ='MASTER STOCK'!F70 -> Kuas 1" incco | B73: ='AGS 25'!AJ73:AJ435 -> 5 | AH73: =SUM(C73:AG73) -> 0 | AI73: 0 | AJ73: =B73-AH73 -> 5 | AK73: =AJ73-AI73 -> 5 | AL73: ='MASTER STOCK'!I70 -> 3500 | AM73: ='MASTER STOCK'!L70 -> 4550 | AN73: =AH73*AM73 -> 0 | AO73: =AN73-(AH73*AL73) -> 0 | AP73: =AH73*AL73 -> 0
... A97: ='MASTER STOCK'!F94 -> Keranjang serbaguna | B97: ='AGS 25'!AJ97:AJ459 -> 24 | AH97: =SUM(C97:AG97) -> 0 | AI97: 0 | AJ97: =B97-AH97 -> 24 | AK97: =AJ97-AI97 -> 24 | AL97: ='MASTER STOCK'!I94 -> 4700 | AM97: ='MASTER STOCK'!L94 | AN97: =AH97*AM97 -> 0 | AO97: =AN97-(AH97*AL97) -> 0 | AP97: =AH97*AL97 -> 0
A98: ='MASTER STOCK'!F95 -> Paku (Nail 2000) 1 1/2" | B98: ='AGS 25'!AJ98:AJ460 -> 1.3 | D98: 0.15 | Q98: 0.1 | AA98: 0.35 | AH98: =SUM(C98:AG98) -> 0.6 | AI98: 0 | AJ98: =B98-AH98 -> 0.7 | AK98: =AJ98-AI98 -> 0.7 | AL98: ='MASTER STOCK'!I95 -> 14400 | AM98: ='MASTER STOCK'!L95 -> 18720 | AN98: =AH98*AM98 -> 11232 | AO98: =AN98-(AH98*AL98) -> 2592 | AP98: =AH98*AL98 -> 8640
A99: ='MASTER STOCK'!F96 -> Paku (Nail 2000) 2 1/2" | B99: ='AGS 25'!AJ99:AJ461 -> 19.9 | C99: 0.15 | AH99: =SUM(C99:AG99) -> 0.15 | AI99: 0 | AJ99: =B99-AH99 -> 19.75 | AK99: =AJ99-AI99 -> 19.75 | AL99: ='MASTER STOCK'!I96 -> 13500 | AM99: ='MASTER STOCK'!L96 -> 17550 | AN99: =AH99*AM99 -> 2632.5 | AO99: =AN99-(AH99*AL99) -> 607.5 | AP99: =AH99*AL99 -> 2025
A100: ='MASTER STOCK'!F97 -> Paku (Nail 2000) 3" | B100: ='AGS 25'!AJ100:AJ462 -> 18.8 | Y100: 0.5 | AH100: =SUM(C100:AG100) -> 0.5 | AI100: 0 | AJ100: =B100-AH100 -> 18.3 | AK100: =AJ100-AI100 -> 18.3 | AL100: ='MASTER STOCK'!I97 -> 13500 | AM100: ='MASTER STOCK'!L97 -> 17550 | AN100: =AH100*AM100 -> 8775 | AO100: =AN100-(AH100*AL100) -> 2025 | AP100: =AH100*AL100 -> 6750
A101: ='MASTER STOCK'!F98 -> Paku (Nail 2000) 1" | B101: ='AGS 25'!AJ101:AJ463 -> 3.35 | Y101: 0.25 | AH101: =SUM(C101:AG101) -> 0.25 | AI101: 0 | AJ101: =B101-AH101 -> 3.1 | AK101: =AJ101-AI101 -> 3.1 | AL101: ='MASTER STOCK'!I98 -> 15200 | AM101: ='MASTER STOCK'!L98 -> 19760 | AN101: =AH101*AM101 -> 4940 | AO101: =AN101-(AH101*AL101) -> 1140 | AP101: =AH101*AL101 -> 3800
A102: ='MASTER STOCK'!F99 -> Paku (Nail 20000 1 3/4" | B102: ='AGS 25'!AJ102:AJ464 -> 3.05 | Y102: 0.5 | AH102: =SUM(C102:AG102) -> 0.5 | AI102: 0 | AJ102: =B102-AH102 -> 2.55 | AK102: =AJ102-AI102 -> 2.55 | AL102: ='MASTER STOCK'!I99 -> 14100 | AM102: ='MASTER STOCK'!L99 -> 18330 | AN102: =AH102*AM102 -> 9165 | AO102: =AN102-(AH102*AL102) -> 2115 | AP102: =AH102*AL102 -> 7050
A103: ='MASTER STOCK'!F100 -> Paku (Nail 2000) 2" | B103: ='AGS 25'!AJ103:AJ465 -> 14 | C103: 0.15 | D103: 0.35 | Q103: 0.1 | AH103: =SUM(C103:AG103) -> 0.6 | AI103: 0 | AJ103: =B103-AH103 -> 13.4 | AK103: =AJ103-AI103 -> 13.4 | AL103: ='MASTER STOCK'!I100 -> 13500 | AM103: ='MASTER STOCK'!L100 -> 17550 | AN103: =AH103*AM103 -> 10530 | AO103: =AN103-(AH103*AL103) -> 2430 | AP103: =AH103*AL103 -> 8100
A104: ='MASTER STOCK'!F101 -> Besi Beton 6mm SNI (U) | B104: ='AGS 25'!AJ104:AJ466 -> 10 | AH104: =SUM(C104:AG104) -> 0 | AI104: 0 | AJ104: =B104-AH104 -> 10 | AK104: =AJ104-AI104 -> 10 | AL104: ='MASTER STOCK'!I101 -> 22000 | AM104: ='MASTER STOCK'!L101 -> 26000 | AN104: =AH104*AM104 -> 0 | AO104: =AN104-(AH104*AL104) -> 0 | AP104: =AH104*AL104 -> 0
A105: ='MASTER STOCK'!F102 -> Besi Beton 8mm SNI (U) | B105: ='AGS 25'!AJ105:AJ467 -> 8 | AH105: =SUM(C105:AG105) -> 0 | AI105: 0 | AJ105: =B105-AH105 -> 8 | AK105: =AJ105-AI105 -> 8 | AL105: ='MASTER STOCK'!I102 -> 37000 | AM105: ='MASTER STOCK'!L102 -> 43000 | AN105: =AH105*AM105 -> 0 | AO105: =AN105-(AH105*AL105) -> 0 | AP105: =AH105*AL105 -> 0
A106: ='MASTER STOCK'!F103 -> Besi Beton 10mm SNI (U) | B106: ='AGS 25'!AJ106:AJ468 -> 5 | AH106: =SUM(C106:AG106) -> 0 | AI106: 0 | AJ106: =B106-AH106 -> 5 | AK106: =AJ106-AI106 -> 5 | AL106: ='MASTER STOCK'!I103 -> 58000 | AM106: ='MASTER STOCK'!L103 -> 73000 | AN106: =AH106*AM106 -> 0 | AO106: =AN106-(AH106*AL106) -> 0 | AP106: =AH106*AL106 -> 0
A107: ='MASTER STOCK'!F104 -> Hollow G Tube 20x40x0.4 | B107: ='AGS 25'!AJ107:AJ469 -> 18 | AH107: =SUM(C107:AG107) -> 0 | AI107: 0 | AJ107: =B107-AH107 -> 18 | AK107: =AJ107-AI107 -> 18 | AL107: ='MASTER STOCK'!I104 -> 21500 | AM107: ='MASTER STOCK'!L104 -> 25800 | AN107: =AH107*AM107 -> 0 | AO107: =AN107-(AH107*AL107) -> 0 | AP107: =AH107*AL107 -> 0
A108: ='MASTER STOCK'!F105 -> Hollow G Tube 40x40x0.4 | B108: ='AGS 25'!AJ108:AJ470 -> 10 | AH108: =SUM(C108:AG108) -> 0 | AI108: 0 | AJ108: =B108-AH108 -> 10 | AK108: =AJ108-AI108 -> 10 | AL108: ='MASTER STOCK'!I105 -> 28500 | AM108: ='MASTER STOCK'!L105 -> 34200 | AN108: =AH108*AM108 -> 0 | AO108: =AN108-(AH108*AL108) -> 0 | AP108: =AH108*AL108 -> 0
A109: ='MASTER STOCK'!F106 -> Reng Galvalum Kenana 0.45 (M) | B109: ='AGS 25'!AJ109:AJ471 -> 10 | AH109: =SUM(C109:AG109) -> 0 | AI109: 0 | AJ109: =B109-AH109 -> 10 | AK109: =AJ109-AI109 -> 10 | AL109: ='MASTER STOCK'!I106 -> 39000 | AM109: ='MASTER STOCK'!L106 -> 42900 | AN109: =AH109*AM109 -> 0 | AO109: =AN109-(AH109*AL109) -> 0 | AP109: =AH109*AL109 -> 0
A110: ='MASTER STOCK'!F107 -> C Truss Kencana 75x0.85 (0.75) MM | B110: ='AGS 25'!AJ110:AJ472 -> 10 | AH110: =SUM(C110:AG110) -> 0 | AI110: 0 | AJ110: =B110-AH110 -> 10 | AK110: =AJ110-AI110 -> 10 | AL110: ='MASTER STOCK'!I107 -> 85000 | AM110: ='MASTER STOCK'!L107 -> 93500 | AN110: =AH110*AM110 -> 0 | AO110: =AN110-(AH110*AL110) -> 0 | AP110: =AH110*AL110 -> 0
A111: ='MASTER STOCK'!F108 -> KAYU BALOK 4X6X4 | B111: ='AGS 25'!AJ111:AJ473 -> 12 | AB111: 3 | AH111: =SUM(C111:AG111) -> 3 | AI111: 0 | AJ111: =B111-AH111 -> 9 | AK111: =AJ111-AI111 -> 9 | AL111: ='MASTER STOCK'!I108 -> 39000 | AM111: ='MASTER STOCK'!L108 -> 42900 | AN111: =AH111*AM111 -> 128700 | AO111: =AN111-(AH111*AL111) -> 11700 | AP111: =AH111*AL111 -> 117000
A112: ='MASTER STOCK'!F109 -> KAYU BALOK 3X5X4 | B112: ='AGS 25'!AJ112:AJ474 -> 10 | Q112: 1 | AH112: =SUM(C112:AG112) -> 1 | AI112: 0 | AJ112: =B112-AH112 -> 9 | AK112: =AJ112-AI112 -> 9 | AL112: ='MASTER STOCK'!I109 -> 24000 | AM112: ='MASTER STOCK'!L109 -> 26400 | AN112: =AH112*AM112 -> 26400 | AO112: =AN112-(AH112*AL112) -> 2400 | AP112: =AH112*AL112 -> 24000
A113: ='MASTER STOCK'!F110 -> KAYU BALOK 2X3X4 | B113: ='AGS 25'!AJ113:AJ475 -> 25 | AH113: =SUM(C113:AG113) -> 0 | AI113: 0 | AJ113: =B113-AH113 -> 25 | AK113: =AJ113-AI113 -> 25 | AL113: ='MASTER STOCK'!I110 -> 9600 | AM113: ='MASTER STOCK'!L110 -> 10560 | AN113: =AH113*AM113 -> 0 | AO113: =AN113-(AH113*AL113) -> 0 | AP113: =AH113*AL113 -> 0
A114: ='MASTER STOCK'!F111 -> CANGKUL | B114: ='AGS 25'!AJ114:AJ476 -> 1 | AH114: =SUM(C114:AG114) -> 0 | AI114: 0 | AJ114: =B114-AH114 -> 1 | AK114: =AJ114-AI114 -> 1 | AL114: ='MASTER STOCK'!I111 -> 33580 | AM114: ='MASTER STOCK'!L111 -> 57086 | AN114: =AH114*AM114 -> 0 | AO114: =AN114-(AH114*AL114) -> 0 | AP114: =AH114*AL114 -> 0
A115: ='MASTER STOCK'!F112 -> SEKOP PASIR | B115: ='AGS 25'!AJ115:AJ477 -> 2 | AH115: =SUM(C115:AG115) -> 0 | AI115: 0 | AJ115: =B115-AH115 -> 2 | AK115: =AJ115-AI115 -> 2 | AL115: ='MASTER STOCK'!I112 -> 20000 | AM115: ='MASTER STOCK'!L112 -> 34000 | AN115: =AH115*AM115 -> 0 | AO115: =AN115-(AH115*AL115) -> 0 | AP115: =AH115*AL115 -> 0
A116: ='MASTER STOCK'!F113 -> Baut Drilling Galvalum Baja Ringan 100 Pcs Per Plastik - WL 12x50 100Pcs | B116: ='AGS 25'!AJ116:AJ478 -> 100 | AH116: =SUM(C116:AG116) -> 0 | AI116: 0 | AJ116: =B116-AH116 -> 100 | AK116: =AJ116-AI116 -> 100 | AL116: ='MASTER STOCK'!I113 -> 250 | AM116: ='MASTER STOCK'!L113 -> 500 | AN116: =AH116*AM116 -> 0 | AO116: =AN116-(AH116*AL116) -> 0 | AP116: =AH116*AL116 -> 0
A117: ='MASTER STOCK'!F114 -> Baut Drilling Galvalum Baja Ringan 100 Pcs Per Plastik - WL 12x60 100Pcs | B117: ='AGS 25'!AJ117:AJ479 -> 100 | AH117: =SUM(C117:AG117) -> 0 | AI117: 0 | AJ117: =B117-AH117 -> 100 | AK117: =AJ117-AI117 -> 100 | AL117: ='MASTER STOCK'!I114 -> 300 | AM117: ='MASTER STOCK'!L114 -> 600 | AN117: =AH117*AM117 -> 0 | AO117: =AN117-(AH117*AL117) -> 0 | AP117: =AH117*AL117 -> 0
A118: ='MASTER STOCK'!F115 -> Baut Drilling Galvalum Baja Ringan 100 Pcs Per Plastik - WL 12x30 100Pcs | B118: ='AGS 25'!AJ118:AJ480 -> 100 | AH118: =SUM(C118:AG118) -> 0 | AI118: 0 | AJ118: =B118-AH118 -> 100 | AK118: =AJ118-AI118 -> 100 | AL118: ='MASTER STOCK'!I115 -> 170 | AM118: ='MASTER STOCK'!L115 -> 340 | AN118: =AH118*AM118 -> 0 | AO118: =AN118-(AH118*AL118) -> 0 | AP118: =AH118*AL118 -> 0
A119: ='MASTER STOCK'!F116 -> Baut Drilling Galvalum Baja Ringan 100 Pcs Per Plastik - WL 12x40 100Pcs | B119: ='AGS 25'!AJ119:AJ481 -> 100 | AH119: =SUM(C119:AG119) -> 0 | AI119: 0 | AJ119: =B119-AH119 -> 100 | AK119: =AJ119-AI119 -> 100 | AL119: ='MASTER STOCK'!I116 -> 220 | AM119: ='MASTER STOCK'!L116 -> 440 | AN119: =AH119*AM119 -> 0 | AO119: =AN119-(AH119*AL119) -> 0 | AP119: =AH119*AL119 -> 0
A120: ='MASTER STOCK'!F117 -> Baut Drilling Galvalum Baja Ringan 100 Pcs Per Plastik - WL 12x20 100Pcs | B120: ='AGS 25'!AJ120:AJ482 -> 100 | AH120: =SUM(C120:AG120) -> 0 | AI120: 0 | AJ120: =B120-AH120 -> 100 | AK120: =AJ120-AI120 -> 100 | AL120: ='MASTER STOCK'!I117 -> 150 | AM120: ='MASTER STOCK'!L117 -> 300 | AN120: =AH120*AM120 -> 0 | AO120: =AN120-(AH120*AL120) -> 0 | AP120: =AH120*AL120 -> 0
A121: ='MASTER STOCK'!F118 -> Batu Kumbung | B121: ='AGS 25'!AJ121:AJ483 -> 528 | S121: 150 | AH121: =SUM(C121:AG121) -> 150 | AI121: 0 | AJ121: =B121-AH121 -> 378 | AK121: =AJ121-AI121 -> 378 | AL121: ='MASTER STOCK'!I118 -> 8000 | AM121: ='MASTER STOCK'!L118 -> 12000 | AN121: =AH121*AM121 -> 1800000 | AO121: =AN121-(AH121*AL121) -> 600000 | AP121: =AH121*AL121 -> 1200000
A122: ='MASTER STOCK'!F119 -> Triplek 8m sengon | B122: ='AGS 25'!AJ122:AJ484 -> 5 | AH122: =SUM(C122:AG122) -> 0 | AI122: 0 | AJ122: =B122-AH122 -> 5 | AK122: =AJ122-AI122 -> 5 | AL122: ='MASTER STOCK'!I119 -> 67000 | AM122: ='MASTER STOCK'!L119 -> 70350 | AN122: =AH122*AM122 -> 0 | AO122: =AN122-(AH122*AL122) -> 0 | AP122: =AH122*AL122 -> 0
A123: ='MASTER STOCK'!F120 -> Triplek 6m sengon | B123: ='AGS 25'!AJ123:AJ485 -> 10 | H123: 1 | AH123: =SUM(C123:AG123) -> 1 | AI123: 0 | AJ123: =B123-AH123 -> 9 | AK123: =AJ123-AI123 -> 9 | AL123: ='MASTER STOCK'!I120 -> 56500 | AM123: ='MASTER STOCK'!L120 -> 59325 | AN123: =AH123*AM123 -> 59325 | AO123: =AN123-(AH123*AL123) -> 2825 | AP123: =AH123*AL123 -> 56500
A124: ='MASTER STOCK'!F121 -> Triplek 3m sengon | B124: ='AGS 25'!AJ124:AJ486 -> 10 | AH124: =SUM(C124:AG124) -> 0 | AI124: 0 | AJ124: =B124-AH124 -> 10 | AK124: =AJ124-AI124 -> 10 | AL124: ='MASTER STOCK'!I121 -> 38500 | AM124: ='MASTER STOCK'!L121 -> 40425 | AN124: =AH124*AM124 -> 0 | AO124: =AN124-(AH124*AL124) -> 0 | AP124: =AH124*AL124 -> 0
A125: ='MASTER STOCK'!F122 -> Semen Gresik | B125: ='AGS 25'!AJ125:AJ487 -> 104 | Q125: 1 | R125: 4 | U125: 1 | V125: 2 | AH125: =SUM(C125:AG125) -> 8 | AI125: 0 | AJ125: =B125-AH125 -> 96 | AK125: =AJ125-AI125 -> 96 | AL125: ='MASTER STOCK'!I122 -> 55000 | AM125: ='MASTER STOCK'!L122 -> 56485 | AN125: =AH125*AM125 -> 451880 | AO125: =AN125-(AH125*AL125) -> 11880 | AP125: =AH125*AL125 -> 440000
A126: ='MASTER STOCK'!F123 -> Kapur | B126: ='AGS 25'!AJ126:AJ488 -> 100 | V126: 1 | AH126: =SUM(C126:AG126) -> 1 | AI126: 0 | AJ126: =B126-AH126 -> 99 | AK126: =AJ126-AI126 -> 99 | AL126: ='MASTER STOCK'!I123 -> 17000 | AM126: ='MASTER STOCK'!L123 -> 18700 | AN126: =AH126*AM126 -> 18700 | AO126: =AN126-(AH126*AL126) -> 1700 | AP126: =AH126*AL126 -> 17000
...

Sheet OKT 25
A1: LAPORAN PENJUALAN BULANAN | AQ1: 45931
A2: NAMA BARANG | B2: STOK AWAL | C2: =UPPER("HARI / BULAN : " & TEXT(AQ1, "MMMM YYYY")) -> HARI / BULAN : OKTOBER 2025
C3: =TEXT(C4,"dddd") -> Rabu | D3: =TEXT(D4,"dddd") -> Kamis | E3: =TEXT(E4,"dddd") -> Jumat | F3: =TEXT(F4,"dddd") -> Sabtu | G3: =TEXT(G4,"dddd") -> Minggu | H3: =TEXT(H4,"dddd") -> Senin | I3: =TEXT(I4,"dddd") -> Selasa | J3: =TEXT(J4,"dddd") -> Rabu | ... AG3: =TEXT(AG4,"dddd") -> Jumat | AH3: TOTAL | AI3: STOCK | AJ3: SYSTEM | AK3: KET/SELISIH | AL3: HARGA BELI | AM3: HARGA JUAL | AN3: OMSET | AO3: PROFIT | AP3: TOTAL MODAL
C4: =AQ1 -> 45931 | D4: =IF(AND(MONTH(C4+1) = MONTH(C4), C4<>""),C4 + 1, "") -> 45932 | E4: =IF(AND(MONTH(D4+1) = MONTH(D4), D4<>""),D4 + 1, "") -> 45933 | F4: =IF(AND(MONTH(E4+1) = MONTH(E4), E4<>""),E4 + 1, "") -> 45934 | G4: =IF(AND(MONTH(F4+1) = MONTH(F4), F4<>""),F4 + 1, "") -> 45935 | H4: =IF(AND(MONTH(G4+1) = MONTH(G4), G4<>""),G4 + 1, "") -> 45936 | I4: =IF(AND(MONTH(H4+1) = MONTH(H4), H4<>""),H4 + 1, "") -> 45937 | J4: =IF(AND(MONTH(I4+1) = MONTH(I4), I4<>""),I4 + 1, "") -> 45938 | K4: =IF(AND(MONTH(J4+1) = MONTH(J4), J4<>""),J4 + 1, "") -> 45939 | ... AG4: =IF(AND(MONTH(AF4+1) = MONTH(AF4), AF4<>""),AF4 + 1, "") -> 45961
A5: ='MASTER STOCK'!F2 -> Fitting Gantung | B5: ='SEP 25'!AJ5:AJ364 -> 10 | AG5: 2 | AH5: =SUM(C5:AG5) -> 2 | AI5: 0 | AJ5: =B5-AH5 -> 8 | AK5: =AJ5-AI5 -> 8 | AL5: ='MASTER STOCK'!I2 -> 1400 | AM5: ='MASTER STOCK'!L2 -> 1820 | AN5: =AH5*AM5 -> 3640 | AO5: =AN5-(AH5*AL5) -> 840 | AP5: =AH5*AL5 -> 2800
A6: ='MASTER STOCK'!F3 -> Colokan T | B6: ='AGS 25'!AI6 -> 12 | AH6: =SUM(C6:AG6) -> 0 | AI6: 0 | AJ6: =B6-AH6 -> 12 | AK6: =AJ6-AI6 -> 12 | AL6: ='MASTER STOCK'!I3 -> 3000 | AM6: ='MASTER STOCK'!L3 -> 3900 | AN6: =AH6*AM6 -> 0 | AO6: =AN6-(AH6*AL6) -> 0 | AP6: =AH6*AL6 -> 0
A7: ='MASTER STOCK'!F4 -> Steker Bulat | B7: ='AGS 25'!AI7 -> 12 | E7: 1 | AH7: =SUM(C7:AG7) -> 1 | AI7: 0 | AJ7: =B7-AH7 -> 11 | AK7: =AJ7-AI7 -> 11 | AL7: ='MASTER STOCK'!I4 -> 3000 | AM7: ='MASTER STOCK'!L4 -> 6000 | AN7: =AH7*AM7 -> 6000 | AO7: =AN7-(AH7*AL7) -> 3000 | AP7: =AH7*AL7 -> 3000
A8: ='MASTER STOCK'!F5 -> Steker Gepeng | B8: ='AGS 25'!AI8 -> 12 | H8: 2 | AH8: =SUM(C8:AG8) -> 2 | AI8: 0 | AJ8: =B8-AH8 -> 10 | AK8: =AJ8-AI8 -> 10 | AL8: ='MASTER STOCK'!I5 -> 1100 | AM8: ='MASTER STOCK'!L5 -> 1430 | AN8: =AH8*AM8 -> 2860 | AO8: =AN8-(AH8*AL8) -> 660 | AP8: =AH8*AL8 -> 2200
A9: ='MASTER STOCK'!F6 -> Saklar Gantung Putih jumbo | B9: ='AGS 25'!AI9 -> 12 | W9: 1 | AH9: =SUM(C9:AG9) -> 1 | AI9: 0 | AJ9: =B9-AH9 -> 11 | AK9: =AJ9-AI9 -> 11 | AL9: ='MASTER STOCK'!I6 -> 2250 | AM9: ='MASTER STOCK'!L6 -> 4000 | AN9: =AH9*AM9 -> 4000 | AO9: =AN9-(AH9*AL9) -> 1750 | AP9: =AH9*AL9 -> 2250
A10: ='MASTER STOCK'!F7 -> Saklar Gantung Hitam | B10: ='AGS 25'!AI10 -> 12 | K10: 1 | AH10: =SUM(C10:AG10) -> 1 | AI10: 0 | AJ10: =B10-AH10 -> 11 | AK10: =AJ10-AI10 -> 11 | AL10: ='MASTER STOCK'!I7 -> 1850 | AM10: ='MASTER STOCK'!L7 -> 4000 | AN10: =AH10*AM10 -> 4000 | AO10: =AN10-(AH10*AL10) -> 2150 | AP10: =AH10*AL10 -> 1850
A11: ='MASTER STOCK'!F8 -> Isolasi Hitam National | B11: ='AGS 25'!AI11 -> 20 | AD11: 1 | AH11: =SUM(C11:AG11) -> 1 | AI11: 0 | AJ11: =B11-AH11 -> 19 | AK11: =AJ11-AI11 -> 19 | AL11: ='MASTER STOCK'!I8 -> 5150 | AM11: ='MASTER STOCK'!L8 -> 7982.5 | AN11: =AH11*AM11 -> 7982.5 | AO11: =AN11-(AH11*AL11) -> 2832.5 | AP11: =AH11*AL11 -> 5150
A12: ='MASTER STOCK'!F9 -> Lem PVC Isarplas 40gram | B12: ='AGS 25'!AI12 -> 23 | AH12: =SUM(C12:AG12) -> 0 | AI12: 0 | AJ12: =B12-AH12 -> 23 | AK12: =AJ12-AI12 -> 23 | AL12: ='MASTER STOCK'!I9 -> 6900 | AM12: ='MASTER STOCK'!L9 -> 9500 | AN12: =AH12*AM12 -> 0 | AO12: =AN12-(AH12*AL12) -> 0 | AP12: =AH12*AL12 -> 0
A13: ='MASTER STOCK'!F10 -> Isolasi Kran air onda | B13: ='AGS 25'!AI13 -> 60 | AH13: =SUM(C13:AG13) -> 0 | AI13: 0 | AJ13: =B13-AH13 -> 60 | AK13: =AJ13-AI13 -> 60 | AL13: ='MASTER STOCK'!I10 -> 1150 | AM13: ='MASTER STOCK'!L10 -> 1495 | AN13: =AH13*AM13 -> 0 | AO13: =AN13-(AH13*AL13) -> 0 | AP13: =AH13*AL13 -> 0
A14: ='MASTER STOCK'!F11 -> Tutup Pipa 3/4" | B14: ='AGS 25'!AI14 -> 50 | AH14: =SUM(C14:AG14) -> 0 | AI14: 0 | AJ14: =B14-AH14 -> 50 | AK14: =AJ14-AI14 -> 50 | AL14: ='MASTER STOCK'!I11 -> 850 | AM14: ='MASTER STOCK'!L11 -> 1275 | AN14: =AH14*AM14 -> 0 | AO14: =AN14-(AH14*AL14) -> 0 | AP14: =AH14*AL14 -> 0
A15: ='MASTER STOCK'!F12 -> Fitting lampu gantung outdoor (10 m 5 fitting) | B15: ='AGS 25'!AI15 -> 1 | AH15: =SUM(C15:AG15) -> 0 | AI15: 0 | AJ15: =B15-AH15 -> 1 | AK15: =AJ15-AI15 -> 1 | AL15: ='MASTER STOCK'!I12 -> 38000 | AM15: ='MASTER STOCK'!L12 -> 49400 | AN15: =AH15*AM15 -> 0 | AO15: =AN15-(AH15*AL15) -> 0 | AP15: =AH15*AL15 -> 0
A16: ='MASTER STOCK'!F13 -> Obeng karet 4" plus | B16: ='AGS 25'!AI16 -> 5 | AH16: =SUM(C16:AG16) -> 0 | AI16: 0 | AJ16: =B16-AH16 -> 5 | AK16: =AJ16-AI16 -> 5 | AL16: ='MASTER STOCK'!I13 -> 5500 | AM16: ='MASTER STOCK'!L13 -> 7150 | AN16: =AH16*AM16 -> 0 | AO16: =AN16-(AH16*AL16) -> 0 | AP16: =AH16*AL16 -> 0
A17: ='MASTER STOCK'!F14 -> Obeng karet 4" minus | B17: ='AGS 25'!AI17 -> 4 | AH17: =SUM(C17:AG17) -> 0 | AI17: 0 | AJ17: =B17-AH17 -> 4 | AK17: =AJ17-AI17 -> 4 | AL17: ='MASTER STOCK'!I14 -> 5500 | AM17: ='MASTER STOCK'!L14 -> 7150 | AN17: =AH17*AM17 -> 0 | AO17: =AN17-(AH17*AL17) -> 0 | AP17: =AH17*AL17 -> 0
A18: ='MASTER STOCK'!F15 -> Obeng karet 6" plus | B18: ='AGS 25'!AI18 -> 5 | AH18: =SUM(C18:AG18) -> 0 | AI18: 0 | AJ18: =B18-AH18 -> 5 | AK18: =AJ18-AI18 -> 5 | AL18: ='MASTER STOCK'!I15 -> 7000 | AM18: ='MASTER STOCK'!L15 -> 9100 | AN18: =AH18*AM18 -> 0 | AO18: =AN18-(AH18*AL18) -> 0 | AP18: =AH18*AL18 -> 0
A19: ='MASTER STOCK'!F16 -> Obeng karet 6" Minus | B19: ='AGS 25'!AI19 -> 5 | AH19: =SUM(C19:AG19) -> 0 | AI19: 0 | AJ19: =B19-AH19 -> 5 | AK19: =AJ19-AI19 -> 5 | AL19: ='MASTER STOCK'!I16 -> 7000 | AM19: ='MASTER STOCK'!L16 -> 9100 | AN19: =AH19*AM19 -> 0 | AO19: =AN19-(AH19*AL19) -> 0 | AP19: =AH19*AL19 -> 0
A20: ='MASTER STOCK'!F17 -> Kabel Awg 24 Double 2x18 merah hitam | B20: ='AGS 25'!AI20 -> 2 | AH20: =SUM(C20:AG20) -> 0 | AI20: 0 | AJ20: =B20-AH20 -> 2 | AK20: =AJ20-AI20 -> 2 | AL20: ='MASTER STOCK'!I17 -> 106500 | AM20: ='MASTER STOCK'!L17 -> 181050 | AN20: =AH20*AM20 -> 0 | AO20: =AN20-(AH20*AL20) -> 0 | AP20: =AH20*AL20 -> 0
A21: ='MASTER STOCK'!F18 -> Kabel bintik serabut tembaga motor mobil 20mx0.5mm/0,85mm merah 0,5mm | B21: ='AGS 25'!AI21 -> 2 | AH21: =SUM(C21:AG21) -> 0 | AI21: 0 | AJ21: =B21-AH21 -> 2 | AK21: =AJ21-AI21 -> 2 | AL21: ='MASTER STOCK'!I18 -> 33700 | AM21: ='MASTER STOCK'!L18 -> 57290 | AN21: =AH21*AM21 -> 0 | AO21: =AN21-(AH21*AL21) -> 0 | AP21: =AH21*AL21 -> 0
A22: ='MASTER STOCK'!F19 -> Kabel bintik serabut tembaga motor mobil 20mx0.5mm/0,85mm hitam 0,5mm | B22: ='AGS 25'!AI22 -> 2 | AH22: =SUM(C22:AG22) -> 0 | AI22: 0 | AJ22: =B22-AH22 -> 2 | AK22: =AJ22-AI22 -> 2 | AL22: ='MASTER STOCK'!I19 -> 33700 | AM22: ='MASTER STOCK'!L19 -> 57290 | AN22: =AH22*AM22 -> 0 | AO22: =AN22-(AH22*AL22) -> 0 | AP22: =AH22*AL22 -> 0
A23: ='MASTER STOCK'!F20 -> Mata Gerinda keramik 4 inch kering | B23: ='AGS 25'!AI23 -> 5 | AH23: =SUM(C23:AG23) -> 0 | AI23: 0 | AJ23: =B23-AH23 -> 5 | AK23: =AJ23-AI23 -> 5 | AL23: ='MASTER STOCK'!I20 -> 12000 | AM23: ='MASTER STOCK'!L20 -> 18000 | AN23: =AH23*AM23 -> 0 | AO23: =AN23-(AH23*AL23) -> 0 | AP23: =AH23*AL23 -> 0
... A37: ='MASTER STOCK'!F34 -> Kuas cat 1" (merk MDN) | B37: ='AGS 25'!AI37 -> 4 | AH37: =SUM(C37:AG37) -> 0 | AI37: 0 | AJ37: =B37-AH37 -> 4 | AK37: =AJ37-AI37 -> 4 | AL37: ='MASTER STOCK'!I34 -> 2300 | AM37: ='MASTER STOCK'!L34 -> 2990 | AN37: =AH37*AM37 -> 0 | AO37: =AN37-(AH37*AL37) -> 0 | AP37: =AH37*AL37 -> 0
A38: ='MASTER STOCK'!F35 -> Kran PVC Tembok 3/4" | B38: ='AGS 25'!AI38 -> 24 | AG38: 1 | AH38: =SUM(C38:AG38) -> 1 | AI38: 0 | AJ38: =B38-AH38 -> 23 | AK38: =AJ38-AI38 -> 23 | AL38: ='MASTER STOCK'!I35 -> 4200 | AM38: ='MASTER STOCK'!L35 -> 6000 | AN38: =AH38*AM38 -> 6000 | AO38: =AN38-(AH38*AL38) -> 1800 | AP38: =AH38*AL38 -> 4200
A39: ='MASTER STOCK'!F36 -> Kran PVC Tembok 1/2" | B39: ='AGS 25'!AI39 -> 24 | AH39: =SUM(C39:AG39) -> 0 | AI39: 0 | AJ39: =B39-AH39 -> 24 | AK39: =AJ39-AI39 -> 24 | AL39: ='MASTER STOCK'!I36 -> 4200 | AM39: ='MASTER STOCK'!L36 -> 6000 | AN39: =AH39*AM39 -> 0 | AO39: =AN39-(AH39*AL39) -> 0 | AP39: =AH39*AL39 -> 0
A40: ='MASTER STOCK'!F37 -> Lampu bohlam inlite 5w Putih | B40: ='AGS 25'!AI40 -> 7 | AH40: =SUM(C40:AG40) -> 0 | AI40: 0 | AJ40: =B40-AH40 -> 7 | AK40: =AJ40-AI40 -> 7 | AL40: ='MASTER STOCK'!I37 -> 13000 | AM40: ='MASTER STOCK'!L37 -> 18200 | AN40: =AH40*AM40 -> 0 | AO40: =AN40-(AH40*AL40) -> 0 | AP40: =AH40*AL40 -> 0
A41: ='MASTER STOCK'!F38 -> Lampu bohlam inlite 7w Putih | B41: ='AGS 25'!AI41 -> 2 | AH41: =SUM(C41:AG41) -> 0 | AI41: 0 | AJ41: =B41-AH41 -> 2 | AK41: =AJ41-AI41 -> 2 | AL41: ='MASTER STOCK'!I38 -> 16200 | AM41: ='MASTER STOCK'!L38 -> 22680 | AN41: =AH41*AM41 -> 0 | AO41: =AN41-(AH41*AL41) -> 0 | AP41: =AH41*AL41 -> 0
A42: ='MASTER STOCK'!F39 -> Lampu bohlam inlite 15w Putih | B42: ='AGS 25'!AI42 -> 4 | AH42: =SUM(C42:AG42) -> 0 | AI42: 0 | AJ42: =B42-AH42 -> 4 | AK42: =AJ42-AI42 -> 4 | AL42: ='MASTER STOCK'!I39 -> 28000 | AM42: ='MASTER STOCK'!L39 -> 39200 | AN42: =AH42*AM42 -> 0 | AO42: =AN42-(AH42*AL42) -> 0 | AP42: =AH42*AL42 -> 0
A43: ='MASTER STOCK'!F40 -> Lampu bohlam inlite 12w Putih | B43: ='AGS 25'!AI43 -> 6 | AE43: 1 | AH43: =SUM(C43:AG43) -> 1 | AI43: 0 | AJ43: =B43-AH43 -> 5 | AK43: =AJ43-AI43 -> 5 | AL43: ='MASTER STOCK'!I40 -> 25000 | AM43: ='MASTER STOCK'!L40 -> 30000 | AN43: =AH43*AM43 -> 30000 | AO43: =AN43-(AH43*AL43) -> 5000 | AP43: =AH43*AL43 -> 25000
A44: ='MASTER STOCK'!F41 -> Lampu tintin platinum LED 9w | B44: ='AGS 25'!AI44 -> 4 | AH44: =SUM(C44:AG44) -> 0 | AI44: 0 | AJ44: =B44-AH44 -> 4 | AK44: =AJ44-AI44 -> 4 | AL44: ='MASTER STOCK'!I41 -> 7000 | AM44: ='MASTER STOCK'!L41 -> 9800 | AN44: =AH44*AM44 -> 0 | AO44: =AN44-(AH44*AL44) -> 0 | AP44: =AH44*AL44 -> 0
A45: ='MASTER STOCK'!F42 -> Lampu tintin platinum LED 5w | B45: ='AGS 25'!AI45 -> 4 | AH45: =SUM(C45:AG45) -> 0 | AI45: 0 | AJ45: =B45-AH45 -> 4 | AK45: =AJ45-AI45 -> 4 | AL45: ='MASTER STOCK'!I42 -> 5000 | AM45: ='MASTER STOCK'!L42 -> 7000 | AN45: =AH45*AM45 -> 0 | AO45: =AN45-(AH45*AL45) -> 0 | AP45: =AH45*AL45 -> 0
A46: ='MASTER STOCK'!F43 -> Lampu tintin platinum LED 21w | B46: ='AGS 25'!AI46 -> 3 | AH46: =SUM(C46:AG46) -> 0 | AI46: 0 | AJ46: =B46-AH46 -> 3 | AK46: =AJ46-AI46 -> 3 | AL46: ='MASTER STOCK'!I43 -> 15500 | AM46: ='MASTER STOCK'!L43 -> 21700 | AN46: =AH46*AM46 -> 0 | AO46: =AN46-(AH46*AL46) -> 0 | AP46: =AH46*AL46 -> 0
A47: ='MASTER STOCK'!F44 -> Lampu tintin platinum LED 15w | B47: ='AGS 25'!AI47 -> 5 | AH47: =SUM(C47:AG47) -> 0 | AI47: 0 | AJ47: =B47-AH47 -> 5 | AK47: =AJ47-AI47 -> 5 | AL47: ='MASTER STOCK'!I44 -> 8800 | AM47: ='MASTER STOCK'!L44 -> 13000 | AN47: =AH47*AM47 -> 0 | AO47: =AN47-(AH47*AL47) -> 0 | AP47: =AH47*AL47 -> 0
A48: ='MASTER STOCK'!F45 -> Lampu tintin platinum LED 12w | B48: ='AGS 25'!AI48 -> 5 | AH48: =SUM(C48:AG48) -> 0 | AI48: 0 | AJ48: =B48-AH48 -> 5 | AK48: =AJ48-AI48 -> 5 | AL48: ='MASTER STOCK'!I45 -> 7800 | AM48: ='MASTER STOCK'!L45 -> 10920 | AN48: =AH48*AM48 -> 0 | AO48: =AN48-(AH48*AL48) -> 0 | AP48: =AH48*AL48 -> 0
A49: ='MASTER STOCK'!F46 -> Lampu tintin platinum LED 7w | B49: ='AGS 25'!AI49 -> 5 | AH49: =SUM(C49:AG49) -> 0 | AI49: 0 | AJ49: =B49-AH49 -> 5 | AK49: =AJ49-AI49 -> 5 | AL49: ='MASTER STOCK'!I46 -> 5800 | AM49: ='MASTER STOCK'!L46 -> 8120 | AN49: =AH49*AM49 -> 0 | AO49: =AN49-(AH49*AL49) -> 0 | AP49: =AH49*AL49 -> 0
A50: ='MASTER STOCK'!F47 -> Gergaji kayu (POPEYE) 18 inch | B50: ='AGS 25'!AI50 -> 4 | AH50: =SUM(C50:AG50) -> 0 | AI50: 0 | AJ50: =B50-AH50 -> 4 | AK50: =AJ50-AI50 -> 4 | AL50: ='MASTER STOCK'!I47 -> 15000 | AM50: ='MASTER STOCK'!L47 -> 19500 | AN50: =AH50*AM50 -> 0 | AO50: =AN50-(AH50*AL50) -> 0 | AP50: =AH50*AL50 -> 0
A51: ='MASTER STOCK'!F48 -> Kapi plamir plastik PVC 9" (23cm) | B51: ='AGS 25'!AI51 -> 10 | AH51: =SUM(C51:AG51) -> 0 | AI51: 0 | AJ51: =B51-AH51 -> 10 | AK51: =AJ51-AI51 -> 10 | AL51: ='MASTER STOCK'!I48 -> 2200 | AM51: ='MASTER STOCK'!L48 -> 3300 | AN51: =AH51*AM51 -> 0 | AO51: =AN51-(AH51*AL51) -> 0 | AP51: =AH51*AL51 -> 0
A52: ='MASTER STOCK'!F49 -> Kapi plamir plastik PVC 5" (12cm) | B52: ='AGS 25'!AI52 -> 5 | AH52: =SUM(C52:AG52) -> 0 | AI52: 0 | AJ52: =B52-AH52 -> 5 | AK52: =AJ52-AI52 -> 5 | AL52: ='MASTER STOCK'!I49 -> 1100 | AM52: ='MASTER STOCK'!L49 -> 1650 | AN52: =AH52*AM52 -> 0 | AO52: =AN52-(AH52*AL52) -> 0 | AP52: =AH52*AL52 -> 0
A53: ='MASTER STOCK'!F50 -> Kapi plamir plastik PVC 7" (18cm) | B53: ='AGS 25'!AI53 -> 10 | AH53: =SUM(C53:AG53) -> 0 | AI53: 0 | AJ53: =B53-AH53 -> 10 | AK53: =AJ53-AI53 -> 10 | AL53: ='MASTER STOCK'!I50 -> 1500 | AM53: ='MASTER STOCK'!L50 -> 2250 | AN53: =AH53*AM53 -> 0 | AO53: =AN53-(AH53*AL53) -> 0 | AP53: =AH53*AL53 -> 0
A54: ='MASTER STOCK'!F51 -> Tang Kombinasi karet 8" | B54: ='AGS 25'!AI54 -> 5 | AH54: =SUM(C54:AG54) -> 0 | AI54: 0 | AJ54: =B54-AH54 -> 5 | AK54: =AJ54-AI54 -> 5 | AL54: ='MASTER STOCK'!I51 -> 12000 | AM54: ='MASTER STOCK'!L51 -> 15600 | AN54: =AH54*AM54 -> 0 | AO54: =AN54-(AH54*AL54) -> 0 | AP54: =AH54*AL54 -> 0
A55: ='MASTER STOCK'!F52 -> Tang Kombinasi 8" | B55: ='AGS 25'!AI55 -> 5 | AH55: =SUM(C55:AG55) -> 0 | AI55: 0 | AJ55: =B55-AH55 -> 5 | AK55: =AJ55-AI55 -> 5 | AL55: ='MASTER STOCK'!I52 -> 12500 | AM55: ='MASTER STOCK'!L52 -> 16250 | AN55: =AH55*AM55 -> 0 | AO55: =AN55-(AH55*AL55) -> 0 | AP55: =AH55*AL55 -> 0
... A89: ='MASTER STOCK'!F86 -> Kabel Transparan 2x50 90M full serabut per roll 2line | B89: ='AGS 25'!AI89 -> 1 | AH89: =SUM(C89:AG89) -> 0 | AI89: 0 | AJ89: =B89-AH89 -> 1 | AK89: =AJ89-AI89 -> 1 | AL89: ='MASTER STOCK'!I86 -> 140000 | AM89: ='MASTER STOCK'!L86 -> 238000 | AN89: =AH89*AM89 -> 0 | AO89: =AN89-(AH89*AL89) -> 0 | AP89: =AH89*AL89 -> 0
A90: ='MASTER STOCK'!F87 -> Solder listrik gagang kayu 60watt | B90: ='AGS 25'!AI90 -> 5 | AG90: 1 | AH90: =SUM(C90:AG90) -> 1 | AI90: 0 | AJ90: =B90-AH90 -> 4 | AK90: =AJ90-AI90 -> 4 | AL90: ='MASTER STOCK'!I87 -> 13000 | AM90: ='MASTER STOCK'!L87 -> 16900 | AN90: =AH90*AM90 -> 16900 | AO90: =AN90-(AH90*AL90) -> 3900 | AP90: =AH90*AL90 -> 13000
A91: ='MASTER STOCK'!F88 -> Timah gulung solder tenol elektrik | B91: ='AGS 25'!AI91 -> 3 | AG91: 1 | AH91: =SUM(C91:AG91) -> 1 | AI91: 0 | AJ91: =B91-AH91 -> 2 | AK91: =AJ91-AI91 -> 2 | AL91: ='MASTER STOCK'!I88 -> 10500 | AM91: ='MASTER STOCK'!L88 -> 13650 | AN91: =AH91*AM91 -> 13650 | AO91: =AN91-(AH91*AL91) -> 3150 | AP91: =AH91*AL91 -> 10500
A92: ='MASTER STOCK'!F89 -> Solasi lakban coklat | B92: ='AGS 25'!AI92 -> 6 | AH92: =SUM(C92:AG92) -> 0 | AI92: 0 | AJ92: =B92-AH92 -> 6 | AK92: =AJ92-AI92 -> 6 | AL92: ='MASTER STOCK'!I89 -> 3600 | AM92: ='MASTER STOCK'!L89 -> 5400 | AN92: =AH92*AM92 -> 0 | AO92: =AN92-(AH92*AL92) -> 0 | AP92: =AH92*AL92 -> 0
A93: ='MASTER STOCK'!F90 -> Spidol Kecil snowman Hitam | B93: ='AGS 25'!AI93 -> 12 | AH93: =SUM(C93:AG93) -> 0 | AI93: 0 | AJ93: =B93-AH93 -> 12 | AK93: =AJ93-AI93 -> 12 | AL93: ='MASTER STOCK'!I90 -> 1700 | AM93: ='MASTER STOCK'!L90 -> 2550 | AN93: =AH93*AM93 -> 0 | AO93: =AN93-(AH93*AL93) -> 0 | AP93: =AH93*AL93 -> 0
A94: ='MASTER STOCK'!F91 -> Spidol Kecil snowman Merah | B94: ='AGS 25'!AI94 -> 12 | AH94: =SUM(C94:AG94) -> 0 | AI94: 0 | AJ94: =B94-AH94 -> 12 | AK94: =AJ94-AI94 -> 12 | AL94: ='MASTER STOCK'!I91 -> 1700 | AM94: ='MASTER STOCK'!L91 -> 2550 | AN94: =AH94*AM94 -> 0 | AO94: =AN94-(AH94*AL94) -> 0 | AP94: =AH94*AL94 -> 0
A95: ='MASTER STOCK'!F92 -> isolasi Lakban Packing bening | B95: ='AGS 25'!AI95 -> 6 | AH95: =SUM(C95:AG95) -> 0 | AI95: 0 | AJ95: =B95-AH95 -> 6 | AK95: =AJ95-AI95 -> 6 | AL95: ='MASTER STOCK'!I92 -> 4500 | AM95: ='MASTER STOCK'!L92 -> 5850 | AN95: =AH95*AM95 -> 0 | AO95: =AN95-(AH95*AL95) -> 0 | AP95: =AH95*AL95 -> 0
A96: ='MASTER STOCK'!F93 -> Tali tampar/ Tali tukang | B96: ='AGS 25'!AI96 -> 20 | AH96: =SUM(C96:AG96) -> 0 | AI96: 0 | AJ96: =B96-AH96 -> 20 | AK96: =AJ96-AI96 -> 20 | AL96: ='MASTER STOCK'!I93 -> 1750 | AM96: ='MASTER STOCK'!L93 -> 2275 | AN96: =AH96*AM96 -> 0 | AO96: =AN96-(AH96*AL96) -> 0 | AP96: =AH96*AL96 -> 0
A97: ='MASTER STOCK'!F94 -> Keranjang serbaguna | B97: ='AGS 25'!AI97 -> 24 | AH97: =SUM(C97:AG97) -> 0 | AI97: 0 | AJ97: =B97-AH97 -> 24 | AK97: =AJ97-AI97 -> 24 | AL97: ='MASTER STOCK'!I94 -> 4700 | AM97: ='MASTER STOCK'!L94 | AN97: =AH97*AM97 -> 0 | AO97: =AN97-(AH97*AL97) -> 0 | AP97: =AH97*AL97 -> 0
A98: ='MASTER STOCK'!F95 -> Paku (Nail 2000) 1 1/2" | B98: ='AGS 25'!AI98 -> 1.3 | AH98: =SUM(C98:AG98) -> 0 | AI98: 0 | AJ98: =B98-AH98 -> 1.3 | AK98: =AJ98-AI98 -> 1.3 | AL98: ='MASTER STOCK'!I95 -> 14400 | AM98: ='MASTER STOCK'!L95 -> 18720 | AN98: =AH98*AM98 -> 0 | AO98: =AN98-(AH98*AL98) -> 0 | AP98: =AH98*AL98 -> 0
A99: ='MASTER STOCK'!F96 -> Paku (Nail 2000) 2 1/2" | B99: ='AGS 25'!AI99 -> 19.9 | AH99: =SUM(C99:AG99) -> 0 | AI99: 0 | AJ99: =B99-AH99 -> 19.9 | AK99: =AJ99-AI99 -> 19.9 | AL99: ='MASTER STOCK'!I96 -> 13500 | AM99: ='MASTER STOCK'!L96 -> 17550 | AN99: =AH99*AM99 -> 0 | AO99: =AN99-(AH99*AL99) -> 0 | AP99: =AH99*AL99 -> 0
A100: ='MASTER STOCK'!F97 -> Paku (Nail 2000) 3" | B100: ='AGS 25'!AI100 -> 18.8 | H100: 1 | J100: 0.35 | Y100: 1 | AH100: =SUM(C100:AG100) -> 2.35 | AI100: 0 | AJ100: =B100-AH100 -> 16.45 | AK100: =AJ100-AI100 -> 16.45 | AL100: ='MASTER STOCK'!I97 -> 13500 | AM100: ='MASTER STOCK'!L97 -> 17550 | AN100: =AH100*AM100 -> 41242.5 | AO100: =AN100-(AH100*AL100) -> 9517.5 | AP100: =AH100*AL100 -> 31725
A101: ='MASTER STOCK'!F98 -> Paku (Nail 2000) 1" | B101: ='AGS 25'!AI101 -> 3.35 | AD101: 0.5 | AH101: =SUM(C101:AG101) -> 0.5 | AI101: 0 | AJ101: =B101-AH101 -> 2.85 | AK101: =AJ101-AI101 -> 2.85 | AL101: ='MASTER STOCK'!I98 -> 15200 | AM101: ='MASTER STOCK'!L98 -> 19760 | AN101: =AH101*AM101 -> 9880 | AO101: =AN101-(AH101*AL101) -> 2280 | AP101: =AH101*AL101 -> 7600
A102: ='MASTER STOCK'!F99 -> Paku (Nail 20000 1 3/4" | B102: ='AGS 25'!AI102 -> 3.05 | AH102: =SUM(C102:AG102) -> 0 | AI102: 0 | AJ102: =B102-AH102 -> 3.05 | AK102: =AJ102-AI102 -> 3.05 | AL102: ='MASTER STOCK'!I99 -> 14100 | AM102: ='MASTER STOCK'!L99 -> 18330 | AN102: =AH102*AM102 -> 0 | AO102: =AN102-(AH102*AL102) -> 0 | AP102: =AH102*AL102 -> 0
A103: ='MASTER STOCK'!F100 -> Paku (Nail 2000) 2" | B103: ='AGS 25'!AI103 -> 14 | D103: 1 | H103: 1 | I103: 0.5 | AD103: 1 | AH103: =SUM(C103:AG103) -> 3.5 | AI103: 0 | AJ103: =B103-AH103 -> 10.5 | AK103: =AJ103-AI103 -> 10.5 | AL103: ='MASTER STOCK'!I100 -> 13500 | AM103: ='MASTER STOCK'!L100 -> 17550 | AN103: =AH103*AM103 -> 61425 | AO103: =AN103-(AH103*AL103) -> 14175 | AP103: =AH103*AL103 -> 47250
A104: ='MASTER STOCK'!F101 -> Besi Beton 6mm SNI (U) | B104: ='AGS 25'!AI104 -> 10 | AH104: =SUM(C104:AG104) -> 0 | AI104: 0 | AJ104: =B104-AH104 -> 10 | AK104: =AJ104-AI104 -> 10 | AL104: ='MASTER STOCK'!I101 -> 22000 | AM104: ='MASTER STOCK'!L101 -> 26000 | AN104: =AH104*AM104 -> 0 | AO104: =AN104-(AH104*AL104) -> 0 | AP104: =AH104*AL104 -> 0
A105: ='MASTER STOCK'!F102 -> Besi Beton 8mm SNI (U) | B105: ='AGS 25'!AI105 -> 8 | AH105: =SUM(C105:AG105) -> 0 | AI105: 0 | AJ105: =B105-AH105 -> 8 | AK105: =AJ105-AI105 -> 8 | AL105: ='MASTER STOCK'!I102 -> 37000 | AM105: ='MASTER STOCK'!L102 -> 43000 | AN105: =AH105*AM105 -> 0 | AO105: =AN105-(AH105*AL105) -> 0 | AP105: =AH105*AL105 -> 0
A106: ='MASTER STOCK'!F103 -> Besi Beton 10mm SNI (U) | B106: ='AGS 25'!AI106 -> 5 | AH106: =SUM(C106:AG106) -> 0 | AI106: 0 | AJ106: =B106-AH106 -> 5 | AK106: =AJ106-AI106 -> 5 | AL106: ='MASTER STOCK'!I103 -> 58000 | AM106: ='MASTER STOCK'!L103 -> 73000 | AN106: =AH106*AM106 -> 0 | AO106: =AN106-(AH106*AL106) -> 0 | AP106: =AH106*AL106 -> 0
A107: ='MASTER STOCK'!F104 -> Hollow G Tube 20x40x0.4 | B107: ='AGS 25'!AI107 -> 18 | AH107: =SUM(C107:AG107) -> 0 | AI107: 0 | AJ107: =B107-AH107 -> 18 | AK107: =AJ107-AI107 -> 18 | AL107: ='MASTER STOCK'!I104 -> 21500 | AM107: ='MASTER STOCK'!L104 -> 25800 | AN107: =AH107*AM107 -> 0 | AO107: =AN107-(AH107*AL107) -> 0 | AP107: =AH107*AL107 -> 0
A108: ='MASTER STOCK'!F105 -> Hollow G Tube 40x40x0.4 | B108: ='AGS 25'!AI108 -> 10 | AH108: =SUM(C108:AG108) -> 0 | AI108: 0 | AJ108: =B108-AH108 -> 10 | AK108: =AJ108-AI108 -> 10 | AL108: ='MASTER STOCK'!I105 -> 28500 | AM108: ='MASTER STOCK'!L105 -> 34200 | AN108: =AH108*AM108 -> 0 | AO108: =AN108-(AH108*AL108) -> 0 | AP108: =AH108*AL108 -> 0
A109: ='MASTER STOCK'!F106 -> Reng Galvalum Kenana 0.45 (M) | B109: ='AGS 25'!AI109 -> 10 | AH109: =SUM(C109:AG109) -> 0 | AI109: 0 | AJ109: =B109-AH109 -> 10 | AK109: =AJ109-AI109 -> 10 | AL109: ='MASTER STOCK'!I106 -> 39000 | AM109: ='MASTER STOCK'!L106 -> 42900 | AN109: =AH109*AM109 -> 0 | AO109: =AN109-(AH109*AL109) -> 0 | AP109: =AH109*AL109 -> 0
A110: ='MASTER STOCK'!F107 -> C Truss Kencana 75x0.85 (0.75) MM | B110: ='AGS 25'!AI110 -> 10 | AH110: =SUM(C110:AG110) -> 0 | AI110: 0 | AJ110: =B110-AH110 -> 10 | AK110: =AJ110-AI110 -> 10 | AL110: ='MASTER STOCK'!I107 -> 85000 | AM110: ='MASTER STOCK'!L107 -> 93500 | AN110: =AH110*AM110 -> 0 | AO110: =AN110-(AH110*AL110) -> 0 | AP110: =AH110*AL110 -> 0
A111: ='MASTER STOCK'!F108 -> KAYU BALOK 4X6X4 | B111: ='AGS 25'!AI111 -> 12 | AH111: =SUM(C111:AG111) -> 0 | AI111: 0 | AJ111: =B111-AH111 -> 12 | AK111: =AJ111-AI111 -> 12 | AL111: ='MASTER STOCK'!I108 -> 39000 | AM111: ='MASTER STOCK'!L108 -> 42900 | AN111: =AH111*AM111 -> 0 | AO111: =AN111-(AH111*AL111) -> 0 | AP111: =AH111*AL111 -> 0
A112: ='MASTER STOCK'!F109 -> KAYU BALOK 3X5X4 | B112: ='AGS 25'!AI112 -> 10 | AH112: =SUM(C112:AG112) -> 0 | AI112: 0 | AJ112: =B112-AH112 -> 10 | AK112: =AJ112-AI112 -> 10 | AL112: ='MASTER STOCK'!I109 -> 24000 | AM112: ='MASTER STOCK'!L109 -> 26400 | AN112: =AH112*AM112 -> 0 | AO112: =AN112-(AH112*AL112) -> 0 | AP112: =AH112*AL112 -> 0
A113: ='MASTER STOCK'!F110 -> KAYU BALOK 2X3X4 | B113: ='AGS 25'!AI113 -> 25 | AH113: =SUM(C113:AG113) -> 0 | AI113: 0 | AJ113: =B113-AH113 -> 25 | AK113: =AJ113-AI113 -> 25 | AL113: ='MASTER STOCK'!I110 -> 9600 | AM113: ='MASTER STOCK'!L110 -> 10560 | AN113: =AH113*AM113 -> 0 | AO113: =AN113-(AH113*AL113) -> 0 | AP113: =AH113*AL113 -> 0
A114: ='MASTER STOCK'!F111 -> CANGKUL | B114: ='AGS 25'!AI114 -> 1 | AH114: =SUM(C114:AG114) -> 0 | AI114: 0 | AJ114: =B114-AH114 -> 1 | AK114: =AJ114-AI114 -> 1 | AL114: ='MASTER STOCK'!I111 -> 33580 | AM114: ='MASTER STOCK'!L111 -> 57086 | AN114: =AH114*AM114 -> 0 | AO114: =AN114-(AH114*AL114) -> 0 | AP114: =AH114*AL114 -> 0
A115: ='MASTER STOCK'!F112 -> SEKOP PASIR | B115: ='AGS 25'!AI115 -> 2 | AH115: =SUM(C115:AG115) -> 0 | AI115: 0 | AJ115: =B115-AH115 -> 2 | AK115: =AJ115-AI115 -> 2 | AL115: ='MASTER STOCK'!I112 -> 20000 | AM115: ='MASTER STOCK'!L112 -> 34000 | AN115: =AH115*AM115 -> 0 | AO115: =AN115-(AH115*AL115) -> 0 | AP115: =AH115*AL115 -> 0
... A120: ='MASTER STOCK'!F117 -> Baut Drilling Galvalum Baja Ringan 100 Pcs Per Plastik - WL 12x20 100Pcs | B120: ='AGS 25'!AI120 -> 100 | AH120: =SUM(C120:AG120) -> 0 | AI120: 0 | AJ120: =B120-AH120 -> 100 | AK120: =AJ120-AI120 -> 100 | AL120: ='MASTER STOCK'!I117 -> 150 | AM120: ='MASTER STOCK'!L117 -> 300 | AN120: =AH120*AM120 -> 0 | AO120: =AN120-(AH120*AL120) -> 0 | AP120: =AH120*AL120 -> 0
A121: ='MASTER STOCK'!F118 -> Batu Kumbung | B121: ='AGS 25'!AI121 -> 528 | AD121: 30 | AH121: =SUM(C121:AG121) -> 30 | AI121: 0 | AJ121: =B121-AH121 -> 498 | AK121: =AJ121-AI121 -> 498 | AL121: ='MASTER STOCK'!I118 -> 8000 | AM121: ='MASTER STOCK'!L118 -> 12000 | AN121: =AH121*AM121 -> 360000 | AO121: =AN121-(AH121*AL121) -> 120000 | AP121: =AH121*AL121 -> 240000
A122: ='MASTER STOCK'!F119 -> Triplek 8m sengon | B122: ='AGS 25'!AI122 -> 5 | AH122: =SUM(C122:AG122) -> 0 | AI122: 0 | AJ122: =B122-AH122 -> 5 | AK122: =AJ122-AI122 -> 5 | AL122: ='MASTER STOCK'!I119 -> 67000 | AM122: ='MASTER STOCK'!L119 -> 70350 | AN122: =AH122*AM122 -> 0 | AO122: =AN122-(AH122*AL122) -> 0 | AP122: =AH122*AL122 -> 0
A123: ='MASTER STOCK'!F120 -> Triplek 6m sengon | B123: ='AGS 25'!AI123 -> 10 | AH123: =SUM(C123:AG123) -> 0 | AI123: 0 | AJ123: =B123-AH123 -> 10 | AK123: =AJ123-AI123 -> 10 | AL123: ='MASTER STOCK'!I120 -> 56500 | AM123: ='MASTER STOCK'!L120 -> 59325 | AN123: =AH123*AM123 -> 0 | AO123: =AN123-(AH123*AL123) -> 0 | AP123: =AH123*AL123 -> 0
A124: ='MASTER STOCK'!F121 -> Triplek 3m sengon | B124: ='AGS 25'!AI124 -> 10 | AH124: =SUM(C124:AG124) -> 0 | AI124: 0 | AJ124: =B124-AH124 -> 10 | AK124: =AJ124-AI124 -> 10 | AL124: ='MASTER STOCK'!I121 -> 38500 | AM124: ='MASTER STOCK'!L121 -> 40425 | AN124: =AH124*AM124 -> 0 | AO124: =AN124-(AH124*AL124) -> 0 | AP124: =AH124*AL124 -> 0
A125: ='MASTER STOCK'!F122 -> Semen Gresik | B125: ='AGS 25'!AI125 -> 104 | C125: 2 | D125: 15 | E125: 5 | AD125: 10 | AF125: 2 | AG125: 2 | AH125: =SUM(C125:AG125) -> 36 | AI125: 0 | AJ125: =B125-AH125 -> 68 | AK125: =AJ125-AI125 -> 68 | AL125: ='MASTER STOCK'!I122 -> 55000 | AM125: ='MASTER STOCK'!L122 -> 56485 | AN125: =AH125*AM125 -> 2033460 | AO125: =AN125-(AH125*AL125) -> 53460 | AP125: =AH125*AL125 -> 1980000
A126: ='MASTER STOCK'!F123 -> Kapur | B126: ='AGS 25'!AI126 -> 100 | V126: 1 | AH126: =SUM(C126:AG126) -> 1 | AI126: 0 | AJ126: =B126-AH126 -> 99 | AK126: =AJ126-AI126 -> 99 | AL126: ='MASTER STOCK'!I123 -> 17000 | AM126: ='MASTER STOCK'!L123 -> 18700 | AN126: =AH126*AM126 -> 18700 | AO126: =AN126-(AH126*AL126) -> 1700 | AP126: =AH126*AL126 -> 17000
A127: ='MASTER STOCK'!F124 -> Pasir | B127: ='AGS 25'!AI127 -> 1 | AH127: =SUM(C127:AG127) -> 0 | AI127: 0 | AJ127: =B127-AH127 -> 1 | AK127: =AJ127-AI127 -> 1 | AL127: ='MASTER STOCK'!I124 -> 1000000 | AM127: ='MASTER STOCK'!L124 -> 1100000 | AN127: =AH127*AM127 -> 0 | AO127: =AN127-(AH127*AL127) -> 0 | AP127: =AH127*AL127 -> 0
A128: ='MASTER STOCK'!F125 -> Stop kontak 1 lubang | B128: ='AGS 25'!AI128 -> 5 | AH128: =SUM(C128:AG128) -> 0 | AI128: 0 | AJ128: =B128-AH128 -> 5 | AK128: =AJ128-AI128 -> 5 | AL128: ='MASTER STOCK'!I125 -> 4125 | AM128: ='MASTER STOCK'!L125 -> 416625 | AN128: =AH128*AM128 -> 0 | AO128: =AN128-(AH128*AL128) -> 0 | AP128: =AH128*AL128 -> 0
A129: ='MASTER STOCK'!F126 -> Stop kontak 2 lubang | B129: ='AGS 25'!AI129 -> 5 | V129: 1 | AH129: =SUM(C129:AG129) -> 1 | AI129: 0 | AJ129: =B129-AH129 -> 4 | AK129: =AJ129-AI129 -> 4 | AL129: ='MASTER STOCK'!I126 -> 5250 | AM129: ='MASTER STOCK'!L126 -> 8925 | AN129: =AH129*AM129 -> 8925 | AO129: =AN129-(AH129*AL129) -> 3675 | AP129: =AH129*AL129 -> 5250
A130: ='MASTER STOCK'!F127 -> Stop kontak 3 lubang | B130: ='AGS 25'!AI130 -> 5 | AH130: =SUM(C130:AG130) -> 0 | AI130: 0 | AJ130: =B130-AH130 -> 5 | AK130: =AJ130-AI130 -> 5 | AL130: ='MASTER STOCK'!I127 -> 6750 | AM130: ='MASTER STOCK'!L127 -> 14000 | AN130: =AH130*AM130 -> 0 | AO130: =AN130-(AH130*AL130) -> 0 | AP130: =AH130*AL130 -> 0
A131: ='MASTER STOCK'!F128 -> Stop kontak 4 lubang | B131: ='AGS 25'!AI131 -> 5 | AH131: =SUM(C131:AG131) -> 0 | AI131: 0 | AJ131: =B131-AH131 -> 5 | AK131: =AJ131-AI131 -> 5 | AL131: ='MASTER STOCK'!I128 -> 8100 | AM131: ='MASTER STOCK'!L128 -> 16000 | AN131: =AH131*AM131 -> 0 | AO131: =AN131-(AH131*AL131) -> 0 | AP131: =AH131*AL131 -> 0
A132: ='MASTER STOCK'!F129 -> Stop kontak 5 lubang | B132: ='AGS 25'!AI132 -> 5 | AH132: =SUM(C132:AG132) -> 0 | AI132: 0 | AJ132: =B132-AH132 -> 5 | AK132: =AJ132-AI132 -> 5 | AL132: ='MASTER STOCK'!I129 -> 9750 | AM132: ='MASTER STOCK'!L129 -> 16575 | AN132: =AH132*AM132 -> 0 | AO132: =AN132-(AH132*AL132) -> 0 | AP132: =AH132*AL132 -> 0
A133: ='MASTER STOCK'!F130 -> Baterai ABC | B133: ='AGS 25'!AI133 -> 24 | AH133: =SUM(C133:AG133) -> 0 | AI133: 0 | AJ133: =B133-AH133 -> 24 | AK133: =AJ133-AI133 -> 24 | AL133: ='MASTER STOCK'!I130 -> 2600 | AM133: ='MASTER STOCK'!L130 -> 3900 | AN133: =AH133*AM133 -> 0 | AO133: =AN133-(AH133*AL133) -> 0 | AP133: =AH133*AL133 -> 0
A134: ='MASTER STOCK'!F131 -> NAIL PAKU PAYUNG 2" | B134: ='AGS 25'!AI134 -> 5 | AH134: =SUM(C134:AG134) -> 0 | AI134: 0 | AJ134: =B134-AH134 -> 5 | AK134: =AJ134-AI134 -> 5 | AL134: ='MASTER STOCK'!I131 -> 17500 | AM134: ='MASTER STOCK'!L131 -> 26250 | AN134: =AH134*AM134 -> 0 | AO134: =AN134-(AH134*AL134) -> 0 | AP134: =AH134*AL134 -> 0
A135: ='MASTER STOCK'!F132 -> NAIL PAKU PAYUNG ULIR 3" | B135: ='AGS 25'!AI135 -> 5 | AH135: =SUM(C135:AG135) -> 0 | AI135: 0 | AJ135: =B135-AH135 -> 5 | AK135: =AJ135-AI135 -> 5 | AL135: ='MASTER STOCK'!I132 -> 18500 | AM135: ='MASTER STOCK'!L132 -> 27750 | AN135: =AH135*AM135 -> 0 | AO135: =AN135-(AH135*AL135) -> 0 | AP135: =AH135*AL135 -> 0
A136: ='MASTER STOCK'!F133 -> NAIL PAKU PAYUNG ULIR 4" | B136: ='AGS 25'!AI136 -> 5 | AH136: =SUM(C136:AG136) -> 0 | AI136: 0 | AJ136: =B136-AH136 -> 5 | AK136: =AJ136-AI136 -> 5 | AL136: ='MASTER STOCK'!I133 -> 16500 | AM136: ='MASTER STOCK'!L133 -> 24750 | AN136: =AH136*AM136 -> 0 | AO136: =AN136-(AH136*AL136) -> 0 | AP136: =AH136*AL136 -> 0
A137: ='MASTER STOCK'!F134 -> PAKU PINES | B137: ='AGS 25'!AI137 -> 7 | AH137: =SUM(C137:AG137) -> 0 | AI137: 0 | AJ137: =B137-AH137 -> 7 | AK137: =AJ137-AI137 -> 7 | AL137: ='MASTER STOCK'!I134 -> 1200 | AM137: ='MASTER STOCK'!L134 -> 2040 | AN137: =AH137*AM137 -> 0 | AO137: =AN137-(AH137*AL137) -> 0 | AP137: =AH137*AL137 -> 0
A138: ='MASTER STOCK'!F135 -> KIKIR 3 INC | B138: ='AGS 25'!AI138 -> 5 | AH138: =SUM(C138:AG138) -> 0 | AI138: 0 | AJ138: =B138-AH138 -> 5 | AK138: =AJ138-AI138 -> 5 | AL138: ='MASTER STOCK'!I135 -> 8000 | AM138: ='MASTER STOCK'!L135 -> 17200 | AN138: =AH138*AM138 -> 0 | AO138: =AN138-(AH138*AL138) -> 0 | AP138: =AH138*AL138 -> 0
A139: ='MASTER STOCK'!F136 -> KIKIR 3.5 INC | B139: ='AGS 25'!AI139 -> 2 | AH139: =SUM(C139:AG139) -> 0 | AI139: 0 | AJ139: =B139-AH139 -> 2 | AK139: =AJ139-AI139 -> 2 | AL139: ='MASTER STOCK'!I136 -> 7500 | AM139: ='MASTER STOCK'!L136 -> 19125 | AN139: =AH139*AM139 -> 0 | AO139: =AN139-(AH139*AL139) -> 0 | AP139: =AH139*AL139 -> 0
A140: ='MASTER STOCK'!F137 -> KIKIR 4 INC | B140: ='AGS 25'!AI140 -> 2 | AH140: =SUM(C140:AG140) -> 0 | AI140: 0 | AJ140: =B140-AH140 -> 2 | AK140: =AJ140-AI140 -> 2 | AL140: ='MASTER STOCK'!I137 -> 9000 | AM140: ='MASTER STOCK'!L137 -> 20700 | AN140: =AH140*AM140 -> 0 | AO140: =AN140-(AH140*AL140) -> 0 | AP140: =AH140*AL140 -> 0
A141: ='MASTER STOCK'!F138 -> AVIAN 192 VERMILLION 25CC | B141: ='AGS 25'!AI141 -> 5 | AH141: =SUM(C141:AG141) -> 0 | AI141: 0 | AJ141: =B141-AH141 -> 5 | AK141: =AJ141-AI141 -> 5 | AL141: ='MASTER STOCK'!I138 -> 4500 | AM141: ='MASTER STOCK'!L138 -> 5580 | AN141: =AH141*AM141 -> 0 | AO141: =AN141-(AH141*AL141) -> 0 | AP141: =AH141*AL141 -> 0
... A161: ='MASTER STOCK'!F158 -> knee 1/2 dim | B161: ='AGS 25'!AI161 -> 46 | AH161: =SUM(C161:AG161) -> 0 | AI161: 0 | AJ161: =B161-AH161 -> 46 | AK161: =AJ161-AI161 -> 46 | AL161: ='MASTER STOCK'!I158 -> 2500 | AM161: ='MASTER STOCK'!L158 -> 2500 | AN161: =AH161*AM161 -> 0 | AO161: =AN161-(AH161*AL161) -> 0 | AP161: =AH161*AL161 -> 0
A162: ='MASTER STOCK'!F159 -> knee 3/4 dim | B162: ='AGS 25'!AI162 -> 38 | L162: 2 | AH162: =SUM(C162:AG162) -> 2 | AI162: 0 | AJ162: =B162-AH162 -> 36 | AK162: =AJ162-AI162 -> 36 | AL162: ='MASTER STOCK'!I159 -> 3500 | AM162: ='MASTER STOCK'!L159 -> 3500 | AN162: =AH162*AM162 -> 7000 | AO162: =AN162-(AH162*AL162) -> 0 | AP162: =AH162*AL162 -> 7000
A163: ='MASTER STOCK'!F160 -> knee drat dalam 3/4 dim | B163: ='AGS 25'!AI163 -> 8 | AH163: =SUM(C163:AG163) -> 0 | AI163: 0 | AJ163: =B163-AH163 -> 8 | AK163: =AJ163-AI163 -> 8 | AL163: ='MASTER STOCK'!I160 -> 4500 | AM163: ='MASTER STOCK'!L160 -> 4500 | AN163: =AH163*AM163 -> 0 | AO163: =AN163-(AH163*AL163) -> 0 | AP163: =AH163*AL163 -> 0
A164: ='MASTER STOCK'!F161 -> paku 1 1/2 | B164: ='AGS 25'!AI164 -> 1 | AH164: =SUM(C164:AG164) -> 0 | AI164: 0 | AJ164: =B164-AH164 -> 1 | AK164: =AJ164-AI164 -> 1 | AL164: ='MASTER STOCK'!I161 -> 25000 | AM164: ='MASTER STOCK'!L161 -> 25000 | AN164: =AH164*AM164 -> 0 | AO164: =AN164-(AH164*AL164) -> 0 | AP164: =AH164*AL164 -> 0
A165: ='MASTER STOCK'!F162 -> paku 3/4 | B165: ='AGS 25'!AI165 -> 1 | AH165: =SUM(C165:AG165) -> 0 | AI165: 0 | AJ165: =B165-AH165 -> 1 | AK165: =AJ165-AI165 -> 1 | AL165: ='MASTER STOCK'!I162 -> 25000 | AM165: ='MASTER STOCK'!L162 -> 25000 | AN165: =AH165*AM165 -> 0 | AO165: =AN165-(AH165*AL165) -> 0 | AP165: =AH165*AL165 -> 0
A166: ='MASTER STOCK'!F163 -> t 1/2 dim | B166: ='AGS 25'!AI166 -> 9 | AH166: =SUM(C166:AG166) -> 0 | AI166: 0 | AJ166: =B166-AH166 -> 9 | AK166: =AJ166-AI166 -> 9 | AL166: ='MASTER STOCK'!I163 -> 2500 | AM166: ='MASTER STOCK'!L163 -> 2500 | AN166: =AH166*AM166 -> 0 | AO166: =AN166-(AH166*AL166) -> 0 | AP166: =AH166*AL166 -> 0
A167: ='MASTER STOCK'!F164 -> knee 1 dim | B167: ='AGS 25'!AI167 -> 18 | AH167: =SUM(C167:AG167) -> 0 | AI167: 0 | AJ167: =B167-AH167 -> 18 | AK167: =AJ167-AI167 -> 18 | AL167: ='MASTER STOCK'!I164 -> 4000 | AM167: ='MASTER STOCK'!L164 -> 4000 | AN167: =AH167*AM167 -> 0 | AO167: =AN167-(AH167*AL167) -> 0 | AP167: =AH167*AL167 -> 0
A168: ='MASTER STOCK'!F165 -> t 1/2 dim | B168: ='AGS 25'!AI168 -> 15 | AH168: =SUM(C168:AG168) -> 0 | AI168: 0 | AJ168: =B168-AH168 -> 15 | AK168: =AJ168-AI168 -> 15 | AL168: ='MASTER STOCK'!I165 -> 2500 | AM168: ='MASTER STOCK'!L165 -> 2500 | AN168: =AH168*AM168 -> 0 | AO168: =AN168-(AH168*AL168) -> 0 | AP168: =AH168*AL168 -> 0
A169: ='MASTER STOCK'!F166 -> t 1/4 dim | B169: ='AGS 25'!AI169 -> 5 | AH169: =SUM(C169:AG169) -> 0 | AI169: 0 | AJ169: =B169-AH169 -> 5 | AK169: =AJ169-AI169 -> 5 | AL169: ='MASTER STOCK'!I166 -> 2500 | AM169: ='MASTER STOCK'!L166 -> 2500 | AN169: =AH169*AM169 -> 0 | AO169: =AN169-(AH169*AL169) -> 0 | AP169: =AH169*AL169 -> 0
...

Sheet NOV 25
A1: LAPORAN PENJUALAN BULANAN | AQ1: 45962
A2: NAMA BARANG | B2: STOK AWAL | C2: =UPPER("HARI / BULAN : " & TEXT(AQ1, "MMMM YYYY")) -> HARI / BULAN : NOVEMBER 2025
C3: =TEXT(C4,"dddd") -> Sabtu | D3: =TEXT(D4,"dddd") -> Minggu | E3: =TEXT(E4,"dddd") -> Senin | F3: =TEXT(F4,"dddd") -> Selasa | G3: =TEXT(G4,"dddd") -> Rabu | H3: =TEXT(H4,"dddd") -> Kamis | I3: =TEXT(I4,"dddd") -> Jumat | J3: =TEXT(J4,"dddd") -> Sabtu | ... AG3: =TEXT(AG4,"dddd") | AH3: TOTAL | AI3: STOCK | AJ3: SYSTEM | AK3: KET/SELISIH | AL3: HARGA BELI | AM3: HARGA JUAL | AN3: OMSET | AO3: PROFIT | AP3: TOTAL MODAL
C4: =AQ1 -> 45962 | D4: =IF(AND(MONTH(C4+1) = MONTH(C4), C4<>""),C4 + 1, "") -> 45963 | E4: =IF(AND(MONTH(D4+1) = MONTH(D4), D4<>""),D4 + 1, "") -> 45964 | F4: =IF(AND(MONTH(E4+1) = MONTH(E4), E4<>""),E4 + 1, "") -> 45965 | G4: =IF(AND(MONTH(F4+1) = MONTH(F4), F4<>""),F4 + 1, "") -> 45966 | H4: =IF(AND(MONTH(G4+1) = MONTH(G4), G4<>""),G4 + 1, "") -> 45967 | I4: =IF(AND(MONTH(H4+1) = MONTH(H4), H4<>""),H4 + 1, "") -> 45968 | J4: =IF(AND(MONTH(I4+1) = MONTH(I4), I4<>""),I4 + 1, "") -> 45969 | K4: =IF(AND(MONTH(J4+1) = MONTH(J4), J4<>""),J4 + 1, "") -> 45970 | ... AG4: =IF(AND(MONTH(AF4+1) = MONTH(AF4), AF4<>""),AF4 + 1, "")
A5: ='MASTER STOCK'!F2 -> Fitting Gantung | B5: ='OKT 25'!AJ5:AJ388 -> 8 | AH5: =SUM(C5:AG5) -> 0 | AI5: 0 | AJ5: =B5-AH5 -> 8 | AK5: =AJ5-AI5 -> 8 | AL5: ='MASTER STOCK'!I2 -> 1400 | AM5: ='MASTER STOCK'!L2 -> 1820 | AN5: =AH5*AM5 -> 0 | AO5: =AN5-(AH5*AL5) -> 0 | AP5: =AH5*AL5 -> 0
A6: ='MASTER STOCK'!F3 -> Colokan T | B6: ='OKT 25'!AJ6:AJ389 -> 12 | AH6: =SUM(C6:AG6) -> 0 | AI6: 0 | AJ6: =B6-AH6 -> 12 | AK6: =AJ6-AI6 -> 12 | AL6: ='MASTER STOCK'!I3 -> 3000 | AM6: ='MASTER STOCK'!L3 -> 3900 | AN6: =AH6*AM6 -> 0 | AO6: =AN6-(AH6*AL6) -> 0 | AP6: =AH6*AL6 -> 0
A7: ='MASTER STOCK'!F4 -> Steker Bulat | B7: ='OKT 25'!AJ7:AJ390 -> 11 | F7: 1 | AH7: =SUM(C7:AG7) -> 1 | AI7: 0 | AJ7: =B7-AH7 -> 10 | AK7: =AJ7-AI7 -> 10 | AL7: ='MASTER STOCK'!I4 -> 3000 | AM7: ='MASTER STOCK'!L4 -> 6000 | AN7: =AH7*AM7 -> 6000 | AO7: =AN7-(AH7*AL7) -> 3000 | AP7: =AH7*AL7 -> 3000
A8: ='MASTER STOCK'!F5 -> Steker Gepeng | B8: ='OKT 25'!AJ8:AJ391 -> 10 | AH8: =SUM(C8:AG8) -> 0 | AI8: 0 | AJ8: =B8-AH8 -> 10 | AK8: =AJ8-AI8 -> 10 | AL8: ='MASTER STOCK'!I5 -> 1100 | AM8: ='MASTER STOCK'!L5 -> 1430 | AN8: =AH8*AM8 -> 0 | AO8: =AN8-(AH8*AL8) -> 0 | AP8: =AH8*AL8 -> 0
A9: ='MASTER STOCK'!F6 -> Saklar Gantung Putih jumbo | B9: ='OKT 25'!AJ9:AJ392 -> 11 | E9: 2 | S9: 1 | V9: 1 | AH9: =SUM(C9:AG9) -> 4 | AI9: 0 | AJ9: =B9-AH9 -> 7 | AK9: =AJ9-AI9 -> 7 | AL9: ='MASTER STOCK'!I6 -> 2250 | AM9: ='MASTER STOCK'!L6 -> 4000 | AN9: =AH9*AM9 -> 16000 | AO9: =AN9-(AH9*AL9) -> 7000 | AP9: =AH9*AL9 -> 9000
A10: ='MASTER STOCK'!F7 -> Saklar Gantung Hitam | B10: ='OKT 25'!AJ10:AJ393 -> 11 | S10: 1 | AH10: =SUM(C10:AG10) -> 1 | AI10: 0 | AJ10: =B10-AH10 -> 10 | AK10: =AJ10-AI10 -> 10 | AL10: ='MASTER STOCK'!I7 -> 1850 | AM10: ='MASTER STOCK'!L7 -> 4000 | AN10: =AH10*AM10 -> 4000 | AO10: =AN10-(AH10*AL10) -> 2150 | AP10: =AH10*AL10 -> 1850
A11: ='MASTER STOCK'!F8 -> Isolasi Hitam National | B11: ='OKT 25'!AJ11:AJ394 -> 19 | AH11: =SUM(C11:AG11) -> 0 | AI11: 0 | AJ11: =B11-AH11 -> 19 | AK11: =AJ11-AI11 -> 19 | AL11: ='MASTER STOCK'!I8 -> 5150 | AM11: ='MASTER STOCK'!L8 -> 7982.5 | AN11: =AH11*AM11 -> 0 | AO11: =AN11-(AH11*AL11) -> 0 | AP11: =AH11*AL11 -> 0
A12: ='MASTER STOCK'!F9 -> Lem PVC Isarplas 40gram | B12: ='OKT 25'!AJ12:AJ395 -> 23 | I12: 1 | N12: 1 | AH12: =SUM(C12:AG12) -> 2 | AI12: 0 | AJ12: =B12-AH12 -> 21 | AK12: =AJ12-AI12 -> 21 | AL12: ='MASTER STOCK'!I9 -> 6900 | AM12: ='MASTER STOCK'!L9 -> 9500 | AN12: =AH12*AM12 -> 19000 | AO12: =AN12-(AH12*AL12) -> 5200 | AP12: =AH12*AL12 -> 13800
A13: ='MASTER STOCK'!F10 -> Isolasi Kran air onda | B13: ='OKT 25'!AJ13:AJ396 -> 60 | AH13: =SUM(C13:AG13) -> 0 | AI13: 0 | AJ13: =B13-AH13 -> 60 | AK13: =AJ13-AI13 -> 60 | AL13: ='MASTER STOCK'!I10 -> 1150 | AM13: ='MASTER STOCK'!L10 -> 1495 | AN13: =AH13*AM13 -> 0 | AO13: =AN13-(AH13*AL13) -> 0 | AP13: =AH13*AL13 -> 0
A14: ='MASTER STOCK'!F11 -> Tutup Pipa 3/4" | B14: ='OKT 25'!AJ14:AJ397 -> 50 | AH14: =SUM(C14:AG14) -> 0 | AI14: 0 | AJ14: =B14-AH14 -> 50 | AK14: =AJ14-AI14 -> 50 | AL14: ='MASTER STOCK'!I11 -> 850 | AM14: ='MASTER STOCK'!L11 -> 1275 | AN14: =AH14*AM14 -> 0 | AO14: =AN14-(AH14*AL14) -> 0 | AP14: =AH14*AL14 -> 0
A15: ='MASTER STOCK'!F12 -> Fitting lampu gantung outdoor (10 m 5 fitting) | B15: ='OKT 25'!AJ15:AJ398 -> 1 | AH15: =SUM(C15:AG15) -> 0 | AI15: 0 | AJ15: =B15-AH15 -> 1 | AK15: =AJ15-AI15 -> 1 | AL15: ='MASTER STOCK'!I12 -> 38000 | AM15: ='MASTER STOCK'!L12 -> 49400 | AN15: =AH15*AM15 -> 0 | AO15: =AN15-(AH15*AL15) -> 0 | AP15: =AH15*AL15 -> 0
A16: ='MASTER STOCK'!F13 -> Obeng karet 4" plus | B16: ='OKT 25'!AJ16:AJ399 -> 5 | AH16: =SUM(C16:AG16) -> 0 | AI16: 0 | AJ16: =B16-AH16 -> 5 | AK16: =AJ16-AI16 -> 5 | AL16: ='MASTER STOCK'!I13 -> 5500 | AM16: ='MASTER STOCK'!L13 -> 7150 | AN16: =AH16*AM16 -> 0 | AO16: =AN16-(AH16*AL16) -> 0 | AP16: =AH16*AL16 -> 0
A17: ='MASTER STOCK'!F14 -> Obeng karet 4" minus | B17: ='OKT 25'!AJ17:AJ400 -> 4 | AH17: =SUM(C17:AG17) -> 0 | AI17: 0 | AJ17: =B17-AH17 -> 4 | AK17: =AJ17-AI17 -> 4 | AL17: ='MASTER STOCK'!I14 -> 5500 | AM17: ='MASTER STOCK'!L14 -> 7150 | AN17: =AH17*AM17 -> 0 | AO17: =AN17-(AH17*AL17) -> 0 | AP17: =AH17*AL17 -> 0
A18: ='MASTER STOCK'!F15 -> Obeng karet 6" plus | B18: ='OKT 25'!AJ18:AJ401 -> 5 | AH18: =SUM(C18:AG18) -> 0 | AI18: 0 | AJ18: =B18-AH18 -> 5 | AK18: =AJ18-AI18 -> 5 | AL18: ='MASTER STOCK'!I15 -> 7000 | AM18: ='MASTER STOCK'!L15 -> 9100 | AN18: =AH18*AM18 -> 0 | AO18: =AN18-(AH18*AL18) -> 0 | AP18: =AH18*AL18 -> 0
A19: ='MASTER STOCK'!F16 -> Obeng karet 6" Minus | B19: ='OKT 25'!AJ19:AJ402 -> 5 | AH19: =SUM(C19:AG19) -> 0 | AI19: 0 | AJ19: =B19-AH19 -> 5 | AK19: =AJ19-AI19 -> 5 | AL19: ='MASTER STOCK'!I16 -> 7000 | AM19: ='MASTER STOCK'!L16 -> 9100 | AN19: =AH19*AM19 -> 0 | AO19: =AN19-(AH19*AL19) -> 0 | AP19: =AH19*AL19 -> 0
A20: ='MASTER STOCK'!F17 -> Kabel Awg 24 Double 2x18 merah hitam | B20: ='OKT 25'!AJ20:AJ403 -> 2 | AH20: =SUM(C20:AG20) -> 0 | AI20: 0 | AJ20: =B20-AH20 -> 2 | AK20: =AJ20-AI20 -> 2 | AL20: ='MASTER STOCK'!I17 -> 106500 | AM20: ='MASTER STOCK'!L17 -> 181050 | AN20: =AH20*AM20 -> 0 | AO20: =AN20-(AH20*AL20) -> 0 | AP20: =AH20*AL20 -> 0
A21: ='MASTER STOCK'!F18 -> Kabel bintik serabut tembaga motor mobil 20mx0.5mm/0,85mm merah 0,5mm | B21: ='OKT 25'!AJ21:AJ404 -> 2 | AH21: =SUM(C21:AG21) -> 0 | AI21: 0 | AJ21: =B21-AH21 -> 2 | AK21: =AJ21-AI21 -> 2 | AL21: ='MASTER STOCK'!I18 -> 33700 | AM21: ='MASTER STOCK'!L18 -> 57290 | AN21: =AH21*AM21 -> 0 | AO21: =AN21-(AH21*AL21) -> 0 | AP21: =AH21*AL21 -> 0
A22: ='MASTER STOCK'!F19 -> Kabel bintik serabut tembaga motor mobil 20mx0.5mm/0,85mm hitam 0,5mm | B22: ='OKT 25'!AJ22:AJ405 -> 2 | AH22: =SUM(C22:AG22) -> 0 | AI22: 0 | AJ22: =B22-AH22 -> 2 | AK22: =AJ22-AI22 -> 2 | AL22: ='MASTER STOCK'!I19 -> 33700 | AM22: ='MASTER STOCK'!L19 -> 57290 | AN22: =AH22*AM22 -> 0 | AO22: =AN22-(AH22*AL22) -> 0 | AP22: =AH22*AL22 -> 0
A23: ='MASTER STOCK'!F20 -> Mata Gerinda keramik 4 inch kering | B23: ='OKT 25'!AJ23:AJ406 -> 5 | AH23: =SUM(C23:AG23) -> 0 | AI23: 0 | AJ23: =B23-AH23 -> 5 | AK23: =AJ23-AI23 -> 5 | AL23: ='MASTER STOCK'!I20 -> 12000 | AM23: ='MASTER STOCK'!L20 -> 18000 | AN23: =AH23*AM23 -> 0 | AO23: =AN23-(AH23*AL23) -> 0 | AP23: =AH23*AL23 -> 0
A24: ='MASTER STOCK'!F21 -> Kabel tunggal serabut 0.8mmx25m biru 25m | B24: ='OKT 25'!AJ24:AJ407 -> 1 | AH24: =SUM(C24:AG24) -> 0 | AI24: 0 | AJ24: =B24-AH24 -> 1 | AK24: =AJ24-AI24 -> 1 | AL24: ='MASTER STOCK'!I21 -> 17500 | AM24: ='MASTER STOCK'!L21 -> 29750 | AN24: =AH24*AM24 -> 0 | AO24: =AN24-(AH24*AL24) -> 0 | AP24: =AH24*AL24 -> 0
... A29: ='MASTER STOCK'!F26 -> Lampu tumbler 10m (rainbow) | B29: ='OKT 25'!AJ29:AJ412 -> 5 | AH29: =SUM(C29:AG29) -> 0 | AI29: 0 | AJ29: =B29-AH29 -> 5 | AK29: =AJ29-AI29 -> 5 | AL29: ='MASTER STOCK'!I26 -> 11000 | AM29: ='MASTER STOCK'!L26 -> 14300 | AN29: =AH29*AM29 -> 0 | AO29: =AN29-(AH29*AL29) -> 0 | AP29: =AH29*AL29 -> 0
A30: ='MASTER STOCK'!F27 -> WD Gerinda potong besi | B30: ='OKT 25'!AJ30:AJ413 -> 58 | O30: 1 | AH30: =SUM(C30:AG30) -> 1 | AI30: 0 | AJ30: =B30-AH30 -> 57 | AK30: =AJ30-AI30 -> 57 | AL30: ='MASTER STOCK'!I27 -> 2900 | AM30: ='MASTER STOCK'!L27 -> 5000 | AN30: =AH30*AM30 -> 5000 | AO30: =AN30-(AH30*AL30) -> 2100 | AP30: =AH30*AL30 -> 2900
A31: ='MASTER STOCK'!F28 -> Meteran karet 7,5m (merk HPP) | B31: ='OKT 25'!AJ31:AJ414 -> 3 | AH31: =SUM(C31:AG31) -> 0 | AI31: 0 | AJ31: =B31-AH31 -> 3 | AK31: =AJ31-AI31 -> 3 | AL31: ='MASTER STOCK'!I28 -> 12800 | AM31: ='MASTER STOCK'!L28 -> 16640 | AN31: =AH31*AM31 -> 0 | AO31: =AN31-(AH31*AL31) -> 0 | AP31: =AH31*AL31 -> 0
A32: ='MASTER STOCK'!F29 -> Meteran karet 5m (merk VPR) | B32: ='OKT 25'!AJ32:AJ415 -> 3 | AH32: =SUM(C32:AG32) -> 0 | AI32: 0 | AJ32: =B32-AH32 -> 3 | AK32: =AJ32-AI32 -> 3 | AL32: ='MASTER STOCK'!I29 -> 7000 | AM32: ='MASTER STOCK'!L29 -> 9100 | AN32: =AH32*AM32 -> 0 | AO32: =AN32-(AH32*AL32) -> 0 | AP32: =AH32*AL32 -> 0
A33: ='MASTER STOCK'!F30 -> Kuas cat 2 1/2" (merk MDN) | B33: ='OKT 25'!AJ33:AJ416 -> 5 | AH33: =SUM(C33:AG33) -> 0 | AI33: 0 | AJ33: =B33-AH33 -> 5 | AK33: =AJ33-AI33 -> 5 | AL33: ='MASTER STOCK'!I30 -> 5300 | AM33: ='MASTER STOCK'!L30 -> 6890 | AN33: =AH33*AM33 -> 0 | AO33: =AN33-(AH33*AL33) -> 0 | AP33: =AH33*AL33 -> 0
A34: ='MASTER STOCK'!F31 -> Kuas cat 2" (merk MDN) | B34: ='OKT 25'!AJ34:AJ417 -> 5 | AH34: =SUM(C34:AG34) -> 0 | AI34: 0 | AJ34: =B34-AH34 -> 5 | AK34: =AJ34-AI34 -> 5 | AL34: ='MASTER STOCK'!I31 -> 4400 | AM34: ='MASTER STOCK'!L31 -> 5720 | AN34: =AH34*AM34 -> 0 | AO34: =AN34-(AH34*AL34) -> 0 | AP34: =AH34*AL34 -> 0
A35: ='MASTER STOCK'!F32 -> Kuas cat 3" (merk MDN) | B35: ='OKT 25'!AJ35:AJ418 -> 4 | Q35: 1 | AH35: =SUM(C35:AG35) -> 1 | AI35: 0 | AJ35: =B35-AH35 -> 3 | AK35: =AJ35-AI35 -> 3 | AL35: ='MASTER STOCK'!I32 -> 6300 | AM35: ='MASTER STOCK'!L32 -> 8190 | AN35: =AH35*AM35 -> 8190 | AO35: =AN35-(AH35*AL35) -> 1890 | AP35: =AH35*AL35 -> 6300
A36: ='MASTER STOCK'!F33 -> Kuas cat 1 1/2" (merk MDN) | B36: ='OKT 25'!AJ36:AJ419 -> 5 | AH36: =SUM(C36:AG36) -> 0 | AI36: 0 | AJ36: =B36-AH36 -> 5 | AK36: =AJ36-AI36 -> 5 | AL36: ='MASTER STOCK'!I33 -> 3400 | AM36: ='MASTER STOCK'!L33 -> 4420 | AN36: =AH36*AM36 -> 0 | AO36: =AN36-(AH36*AL36) -> 0 | AP36: =AH36*AL36 -> 0
A37: ='MASTER STOCK'!F34 -> Kuas cat 1" (merk MDN) | B37: ='OKT 25'!AJ37:AJ420 -> 4 | AH37: =SUM(C37:AG37) -> 0 | AI37: 0 | AJ37: =B37-AH37 -> 4 | AK37: =AJ37-AI37 -> 4 | AL37: ='MASTER STOCK'!I34 -> 2300 | AM37: ='MASTER STOCK'!L34 -> 2990 | AN37: =AH37*AM37 -> 0 | AO37: =AN37-(AH37*AL37) -> 0 | AP37: =AH37*AL37 -> 0
A38: ='MASTER STOCK'!F35 -> Kran PVC Tembok 3/4" | B38: ='OKT 25'!AJ38:AJ421 -> 23 | AA38: 1 | AH38: =SUM(C38:AG38) -> 1 | AI38: 0 | AJ38: =B38-AH38 -> 22 | AK38: =AJ38-AI38 -> 22 | AL38: ='MASTER STOCK'!I35 -> 4200 | AM38: ='MASTER STOCK'!L35 -> 6000 | AN38: =AH38*AM38 -> 6000 | AO38: =AN38-(AH38*AL38) -> 1800 | AP38: =AH38*AL38 -> 4200
A39: ='MASTER STOCK'!F36 -> Kran PVC Tembok 1/2" | B39: ='OKT 25'!AJ39:AJ422 -> 24 | AH39: =SUM(C39:AG39) -> 0 | AI39: 0 | AJ39: =B39-AH39 -> 24 | AK39: =AJ39-AI39 -> 24 | AL39: ='MASTER STOCK'!I36 -> 4200 | AM39: ='MASTER STOCK'!L36 -> 6000 | AN39: =AH39*AM39 -> 0 | AO39: =AN39-(AH39*AL39) -> 0 | AP39: =AH39*AL39 -> 0
A40: ='MASTER STOCK'!F37 -> Lampu bohlam inlite 5w Putih | B40: ='OKT 25'!AJ40:AJ423 -> 7 | AH40: =SUM(C40:AG40) -> 0 | AI40: 0 | AJ40: =B40-AH40 -> 7 | AK40: =AJ40-AI40 -> 7 | AL40: ='MASTER STOCK'!I37 -> 13000 | AM40: ='MASTER STOCK'!L37 -> 18200 | AN40: =AH40*AM40 -> 0 | AO40: =AN40-(AH40*AL40) -> 0 | AP40: =AH40*AL40 -> 0
A41: ='MASTER STOCK'!F38 -> Lampu bohlam inlite 7w Putih | B41: ='OKT 25'!AJ41:AJ424 -> 2 | AH41: =SUM(C41:AG41) -> 0 | AI41: 0 | AJ41: =B41-AH41 -> 2 | AK41: =AJ41-AI41 -> 2 | AL41: ='MASTER STOCK'!I38 -> 16200 | AM41: ='MASTER STOCK'!L38 -> 22680 | AN41: =AH41*AM41 -> 0 | AO41: =AN41-(AH41*AL41) -> 0 | AP41: =AH41*AL41 -> 0
A42: ='MASTER STOCK'!F39 -> Lampu bohlam inlite 15w Putih | B42: ='OKT 25'!AJ42:AJ425 -> 4 | AH42: =SUM(C42:AG42) -> 0 | AI42: 0 | AJ42: =B42-AH42 -> 4 | AK42: =AJ42-AI42 -> 4 | AL42: ='MASTER STOCK'!I39 -> 28000 | AM42: ='MASTER STOCK'!L39 -> 39200 | AN42: =AH42*AM42 -> 0 | AO42: =AN42-(AH42*AL42) -> 0 | AP42: =AH42*AL42 -> 0
A43: ='MASTER STOCK'!F40 -> Lampu bohlam inlite 12w Putih | B43: ='OKT 25'!AJ43:AJ426 -> 5 | I43: 1 | AB43: 1 | AH43: =SUM(C43:AG43) -> 2 | AI43: 0 | AJ43: =B43-AH43 -> 3 | AK43: =AJ43-AI43 -> 3 | AL43: ='MASTER STOCK'!I40 -> 25000 | AM43: ='MASTER STOCK'!L40 -> 30000 | AN43: =AH43*AM43 -> 60000 | AO43: =AN43-(AH43*AL43) -> 10000 | AP43: =AH43*AL43 -> 50000
A44: ='MASTER STOCK'!F41 -> Lampu tintin platinum LED 9w | B44: ='OKT 25'!AJ44:AJ427 -> 4 | AH44: =SUM(C44:AG44) -> 0 | AI44: 0 | AJ44: =B44-AH44 -> 4 | AK44: =AJ44-AI44 -> 4 | AL44: ='MASTER STOCK'!I41 -> 7000 | AM44: ='MASTER STOCK'!L41 -> 9800 | AN44: =AH44*AM44 -> 0 | AO44: =AN44-(AH44*AL44) -> 0 | AP44: =AH44*AL44 -> 0
A45: ='MASTER STOCK'!F42 -> Lampu tintin platinum LED 5w | B45: ='OKT 25'!AJ45:AJ428 -> 4 | T45: 1 | AH45: =SUM(C45:AG45) -> 1 | AI45: 0 | AJ45: =B45-AH45 -> 3 | AK45: =AJ45-AI45 -> 3 | AL45: ='MASTER STOCK'!I42 -> 5000 | AM45: ='MASTER STOCK'!L42 -> 7000 | AN45: =AH45*AM45 -> 7000 | AO45: =AN45-(AH45*AL45) -> 2000 | AP45: =AH45*AL45 -> 5000
A46: ='MASTER STOCK'!F43 -> Lampu tintin platinum LED 21w | B46: ='OKT 25'!AJ46:AJ429 -> 3 | AH46: =SUM(C46:AG46) -> 0 | AI46: 0 | AJ46: =B46-AH46 -> 3 | AK46: =AJ46-AI46 -> 3 | AL46: ='MASTER STOCK'!I43 -> 15500 | AM46: ='MASTER STOCK'!L43 -> 21700 | AN46: =AH46*AM46 -> 0 | AO46: =AN46-(AH46*AL46) -> 0 | AP46: =AH46*AL46 -> 0
A47: ='MASTER STOCK'!F44 -> Lampu tintin platinum LED 15w | B47: ='OKT 25'!AJ47:AJ430 -> 5 | T47: 1 | AH47: =SUM(C47:AG47) -> 1 | AI47: 0 | AJ47: =B47-AH47 -> 4 | AK47: =AJ47-AI47 -> 4 | AL47: ='MASTER STOCK'!I44 -> 8800 | AM47: ='MASTER STOCK'!L44 -> 13000 | AN47: =AH47*AM47 -> 13000 | AO47: =AN47-(AH47*AL47) -> 4200 | AP47: =AH47*AL47 -> 8800
A48: ='MASTER STOCK'!F45 -> Lampu tintin platinum LED 12w | B48: ='OKT 25'!AJ48:AJ431 -> 5 | AH48: =SUM(C48:AG48) -> 0 | AI48: 0 | AJ48: =B48-AH48 -> 5 | AK48: =AJ48-AI48 -> 5 | AL48: ='MASTER STOCK'!I45 -> 7800 | AM48: ='MASTER STOCK'!L45 -> 10920 | AN48: =AH48*AM48 -> 0 | AO48: =AN48-(AH48*AL48) -> 0 | AP48: =AH48*AL48 -> 0
A49: ='MASTER STOCK'!F46 -> Lampu tintin platinum LED 7w | B49: ='OKT 25'!AJ49:AJ432 -> 5 | S49: 1 | V49: 1 | AH49: =SUM(C49:AG49) -> 2 | AI49: 0 | AJ49: =B49-AH49 -> 3 | AK49: =AJ49-AI49 -> 3 | AL49: ='MASTER STOCK'!I46 -> 5800 | AM49: ='MASTER STOCK'!L46 -> 8120 | AN49: =AH49*AM49 -> 16240 | AO49: =AN49-(AH49*AL49) -> 4640 | AP49: =AH49*AL49 -> 11600
